Workbook
Name ___F: [1]Hoja3!#REF!
Name _1TEXAS_LONG: #REF!
Name _ACC53: #REF!
Name _ACC54: #REF!
Name _ACC56: #REF!
Name _BUT38: #REF!
Name _BUT78: #REF!
Name _EPD15: #REF!
Name _F: [1]Hoja3!#REF!
Name _PAG1: #REF!
Name _TCA704: #REF!
Name _TOR10: #REF!
Name _TOR14: #REF!
Name _TR4: #REF!
Name A: '[3]Encofrado BVR Unispan'!$C$10
Name A_001: [4]puni!$H$51
Name A_002: [4]puni!$H$97
Name A_003: [4]puni!$H$143
Name A_004: [4]puni!$H$189
Name A_005: [4]puni!$H$235
Name A_006: [4]puni!$H$281
Name A_007: [4]puni!$H$327
Name A_008: [4]puni!$H$373
Name A_009: [4]puni!$H$425
Name A_512: [5]puni!$H$143
Name A_IMPRESIÓN_IM: #REF!
Name AA: #REF!
Name abc: #REF!
Name ABRAZ: #REF!
Name ACCESORIOS: #REF!
Name ACER.: #REF!
Name acero: #REF!
Name ACT: #REF!
Name ADEL: #REF!
Name ADELANTO: #REF!
Name ADELANTOAPT: #REF!
Name AE: #REF!
Name AFI: #REF!
Name afirmado: #REF!
Name AFN: #REF!
Name AFNIT: #REF!
Name AFP: #REF!
Name AFPYN: #REF!
Name Agua: #REF!
Name aj_e1: #REF!
Name alambre: #REF!
Name Alizadora: #REF!
Name Almacén_sótano: #REF!
Name AMI: #REF!
Name AN: #REF!
Name ANAC: #REF!
Name Analisis: #REF!
Name AÑO: #REF!
Name apisonadora: #REF!
Name Arancel: #REF!
Name AREA: #REF!
Name Area__cm2: #REF!
Name AREA_COLUMNAS: #REF!
Name Area_mezzanine: #REF!
Name Area_piso1: #REF!

Sheet FLUJO DE CAJA PROYECTADO  (2)
J5: =J12 -> 9 | K5: =K12 -> 10 | L5: =L12 -> 11 | M5: =M12 -> 12 | N5: =N12 -> 13 | O5: =O12 -> 14 | P5: =P12 -> 15 | Q5: =Q12 -> 16 | ... AN5: =AN12 -> 39
I6: Valor total | J6: Valor Unitario | K6: semana 1 | L6: semana 2 | M6: semana 3 | N6: semana 4 | O6: Total Abril 2026 | P6: semana 5 | Q6: semana 6 | R6: semana 7 | S6: semana 8 | T6: Total mayo 2026 | U6: semana 9 | V6: semana 10 | W6: semana 11 | X6: semana 12 | Y6: Total junio 2026 | Z6: semana 13 | AA6: semana 14 | AB6: semana 15 | AC6: semana 16 | AD6: Total julio 2026 | AE6: semana 17 | AF6: semana 18 | AG6: semana 19 | AH6: semana 20 | AI6: Total Agosto 2026 | AJ6: semana 17 | AK6: semana 18 | AL6: semana 19 | AM6: semana 20 | AN6: Total Septiembre 2026
C7: % DE FACTURACIÓN | D7: 530000 | E7: Kg | F7: 4753.95 | G7: =+D7*F7 -> 2519593500 | O7: =SUM(K7:N7) -> 0 | S7: 0 | T7: =SUM(P7:S7) -> 0 | W7: 54616.82 | Y7: =SUM(U7:X7) -> 54616.82 | AA7: 23957.46 | AC7: 25521.41 | AD7: =SUM(Z7:AC7) -> 49478.87 | AF7: 80000 | AH7: 100000 | AI7: =SUM(AE7:AH7) -> 180000 | AK7: 100000 | AM7: 145904.31 | AN7: =SUM(AJ7:AM7) -> 245904.31
I8: =(O7+T7+Y7+AD7+AI7)*J8 -> 1.5690605e+09 | J8: 5523 | M8: 870811200 | O8: =M8 -> 870811200 | T8: =$J$8*T7 -> 0 | U8: =$J$8*U7 -> 0 | V8: =$J$8*V7 -> 0 | W8: =$J$8*W7 -> 3.016487e+08 | X8: =$J$8*X7 -> 0 | Y8: =$J$8*Y7 -> 3.016487e+08 | Z8: =$J$8*Z7 -> 0 | AA8: =$J$8*AA7 -> 1.3231705e+08 | ... AN8: =$J$8*AN7 -> 1.3581295e+09
B12: 1 | C12: 2 | D12: 3 | E12: 4 | F12: 5 | G12: 6 | H12: 7 | I12: 8 | J12: 9 | K12: 10 | L12: 11 | M12: 12 | N12: 13 | O12: 14 | P12: 15 | Q12: 16 | R12: 17 | S12: 18 | T12: 19 | U12: 20 | V12: 21 | W12: 22 | X12: 23 | Y12: 24 | Z12: 25 | AA12: 26 | AB12: 27 | AC12: 28 | AD12: 29 | AE12: 30 | AF12: 31 | AG12: 32 | AH12: 33 | AI12: 34 | AJ12: 35 | AK12: 36 | AL12: 37 | AM12: 38 | AN12: 39
B13: Código | C13: ITEM | D13: Cantidad+desp. | E13: Unidad de medida | F13: Valor Unitario | G13: Total presupuesto | I13: Valor total | J13: Valor Unitario | K13: semana 1 | L13: semana 2 | M13: semana 3 | N13: semana 4 | O13: Total Abril 2026 | P13: semana 5 | Q13: semana 6 | R13: semana 7 | S13: semana 8 | T13: Total mayo 2026 | U13: semana 9 | V13: semana 10 | W13: semana 11 | X13: semana 12 | Y13: Total junio 2026 | Z13: semana 13 | AA13: semana 14 | AB13: semana 15 | AC13: semana 16 | AD13: Total julio 2026 | AE13: semana 17 | AF13: semana 18 | AG13: semana 19 | AH13: semana 20 | AI13: Total Agosto 2026 | AJ13: semana 17 | AK13: semana 18 | AL13: semana 19 | AM13: semana 20 | AN13: Total Septiembre 2026
B14: 1 | C14: Indirectos | G14: =SUM(G15,G22,G26,G29,G39) -> 1.5053398e+08 | I14: =SUM(I15,I22,I26,I29,I39) -> 1.5530062e+08 | J14: =SUM(J15,J22,J26,J29,J39) -> 123876289 | K14: =SUM(K15,K22,K26,K29,K39) -> 0 | L14: =SUM(L15,L22,L26,L29,L39) -> 0 | M14: =SUM(M15,M22,M26,M29,M39) -> 64463869 | N14: =SUM(N15,N22,N26,N29,N39) -> 3097443 | O14: =SUM(O15,O22,O26,O29,O39) -> 67561312 | P14: =SUM(P15,P22,P26,P29,P39) -> 0 | ... AN14: =SUM(AN15,AN22,AN26,AN29,AN39) -> 60108545
B15: 1.1 | C15: Polizas talleres | D15: =SUM(D16:D21) -> 6 | E15: =SUM(E16:E21) -> 0 | F15: =SUM(F16:F21) -> 18295782 | G15: =SUM(G16:G21) -> 18295782 | I15: =SUM(I16:I21) -> 13451751 | J15: =SUM(J16:J21) -> 5917366 | K15: =SUM(K16:K21) -> 0 | L15: =SUM(L16:L21) -> 0 | M15: =SUM(M16:M21) -> 5917366 | N15: =SUM(N16:N21) -> 0 | O15: =SUM(O16:O21) -> 5917366 | P15: =SUM(P16:P21) -> 0 | ... AN15: =SUM(AN16:AN21) -> 7534385
B16: 1.1.1 | C16: Buen manejo de anticipo | D16: 1 | E16: glb | F16: 3512790.2 | G16: =+D16*F16 -> 3512790.2 | I16: =(O16+T16+Y16+AD16+AI16+AN16) -> 1844836.1 | J16: 516713.12 | M16: 516713.12 | O16: =SUM(K16:N16) -> 516713.12 | T16: =SUM(P16:S16) -> 0 | Y16: =SUM(U16:X16) -> 0 | AD16: =SUM(Z16:AC16) -> 0 | AI16: =SUM(AE16:AH16) -> 0 | AM16: 1328123 | AN16: =SUM(AJ16:AM16) -> 1328123
B17: 1.1.2 | C17: Cumplimiento | D17: 1 | E17: glb | F17: 3073691.4 | G17: =+D17*F17 -> 3073691.4 | I17: =(O17+T17+Y17+AD17+AI17+AN17) -> 910373.43 | J17: 465741.43 | M17: 465741.43 | O17: =SUM(K17:N17) -> 465741.43 | T17: =SUM(P17:S17) -> 0 | Y17: =SUM(U17:X17) -> 0 | AD17: =SUM(Z17:AC17) -> 0 | AI17: =SUM(AE17:AH17) -> 0 | AM17: 444632 | AN17: =SUM(AJ17:AM17) -> 444632
B18: 1.1.3 | C18: Salarios y prestaciones sociales | D18: 1 | E18: glb | F18: 2049127.6 | G18: =+D18*F18 -> 2049127.6 | I18: =(O18+T18+Y18+AD18+AI18+AN18) -> 612043.07 | J18: 349306.07 | M18: 349306.07 | O18: =SUM(K18:N18) -> 349306.07 | T18: =SUM(P18:S18) -> 0 | Y18: =SUM(U18:X18) -> 0 | AD18: =SUM(Z18:AC18) -> 0 | AI18: =SUM(AE18:AH18) -> 0 | AM18: 262737 | AN18: =SUM(AJ18:AM18) -> 262737
B19: 1.1.4 | C19: Estabilidad de obra | D19: 1 | E19: glb | F19: 3073691.4 | G19: =+D19*F19 -> 3073691.4 | I19: =(O19+T19+Y19+AD19+AI19+AN19) -> 7879684.9 | J19: 4184037.9 | M19: 4184037.9 | O19: =SUM(K19:N19) -> 4184037.9 | T19: =SUM(P19:S19) -> 0 | Y19: =SUM(U19:X19) -> 0 | AD19: =SUM(Z19:AC19) -> 0 | AI19: =SUM(AE19:AH19) -> 0 | AM19: 3695647 | AN19: =SUM(AJ19:AM19) -> 3695647
B20: 1.1.5 | C20: Calidad de obra | D20: 1 | E20: glb | F20: 3073691.4 | G20: =+D20*F20 -> 3073691.4 | I20: =(O20+T20+Y20+AD20+AI20+AN20) -> 1222251 | J20: 9282 | M20: 9282 | O20: =SUM(K20:N20) -> 9282 | T20: =SUM(P20:S20) -> 0 | Y20: =SUM(U20:X20) -> 0 | AD20: =SUM(Z20:AC20) -> 0 | AI20: =SUM(AE20:AH20) -> 0 | AM20: 1212969 | AN20: =SUM(AJ20:AM20) -> 1212969
B21: 1.1.6 | C21: Responsabilidad civil extracontractural | D21: 1 | E21: glb | F21: 3512790.2 | G21: =+D21*F21 -> 3512790.2 | I21: =(O21+T21+Y21+AD21+AI21+AN21) -> 982562.52 | J21: =197018.52+195267 -> 392285.52 | M21: =197018.52+195267 -> 392285.52 | O21: =SUM(K21:N21) -> 392285.52 | T21: =SUM(P21:S21) -> 0 | Y21: =SUM(U21:X21) -> 0 | AD21: =SUM(Z21:AC21) -> 0 | AI21: =SUM(AE21:AH21) -> 0 | AM21: 590277 | AN21: =SUM(AJ21:AM21) -> 590277
B22: 1.2. | C22: Impuestos | G22: =SUM(G23:G25) -> 48300865 | I22: =SUM(I23:I25) -> 48300865 | J22: =SUM(J23:J25) -> 48300863 | K22: =SUM(K23:K25) -> 0 | L22: =SUM(L23:L25) -> 0 | M22: =SUM(M23:M25) -> 0 | N22: =SUM(N23:N25) -> 0 | O22: =SUM(O23:O25) -> 0 | P22: =SUM(P23:P25) -> 0 | ... AN22: =SUM(AN23:AN25) -> 48300865
B23: 1.2.1 | C23: FIC | D23: 1 | E23: glb | F23: 7318312.9 | G23: =+D23*F23 -> 7318312.9 | I23: =(O23+T23+Y23+AD23+AI23+AN23) -> 7318312.9 | J23: 7318312 | O23: =SUM(K23:N23) -> 0 | T23: =SUM(P23:S23) -> 0 | Y23: =SUM(U23:X23) -> 0 | AD23: =SUM(Z23:AC23) -> 0 | AI23: =SUM(AE23:AH23) -> 0 | AK23: 7318312.9 | AN23: =SUM(AJ23:AM23) -> 7318312.9
B24: 1.2.2 | C24: ICA | D24: 1 | E24: glb | F24: 29273252 | G24: =+D24*F24 -> 29273252 | I24: =(O24+T24+Y24+AD24+AI24+AN24) -> 29273252 | J24: 29273251 | O24: =SUM(K24:N24) -> 0 | T24: =SUM(P24:S24) -> 0 | Y24: =SUM(U24:X24) -> 0 | AD24: =SUM(Z24:AC24) -> 0 | AI24: =SUM(AE24:AH24) -> 0 | AK24: 29273252 | AN24: =SUM(AJ24:AM24) -> 29273252
B25: 1.2.3 | C25: Cuatro por 1000 | D25: 1 | E25: glb | F25: 11709301 | G25: =+D25*F25 -> 11709301 | I25: =(O25+T25+Y25+AD25+AI25+AN25) -> 11709301 | J25: 11709300 | O25: =SUM(K25:N25) -> 0 | T25: =SUM(P25:S25) -> 0 | Y25: =SUM(U25:X25) -> 0 | AD25: =SUM(Z25:AC25) -> 0 | AI25: =SUM(AE25:AH25) -> 0 | AK25: 11709301 | AN25: =SUM(AJ25:AM25) -> 11709301
B26: 1.3 | C26: Personal administración | G26: =G27 -> 24640000 | I26: =SUM(I27:I28) -> 34339945 | J26: =SUM(J27:J28) -> 10450000 | K26: =SUM(K27:K28) -> 0 | L26: =SUM(L27:L28) -> 0 | M26: =SUM(M27:M28) -> 0 | N26: =SUM(N27:N28) -> 2435886 | O26: =SUM(O27:O28) -> 2435886 | P26: =SUM(P27:P28) -> 0 | ... AN26: =SUM(AN27:AN28) -> 4273295
B27: 1.3.1 | C27: Profesional de calidad 100% | D27: 4 | E27: mes | F27: 6160000 | G27: =+D27*F27 -> 24640000 | I27: =(O27+T27+Y27+AD27+AI27+AN27) -> 17089945 | J27: 7000000 | N27: 2435886 | O27: =SUM(K27:N27) -> 2435886 | S27: 6915382 | T27: =SUM(P27:S27) -> 6915382 | X27: 6915382 | Y27: =SUM(U27:X27) -> 6915382 | AD27: =SUM(Z27:AC27) -> 0 | AI27: =SUM(AE27:AH27) -> 0 | AM27: 823295 | AN27: =SUM(AJ27:AM27) -> 823295
B28: 1.3.2 | C28: Residente administrativo | D28: 4 | E28: mes | F28: =2300000*1.5 -> 3450000 | G28: =F28*D28 -> 13800000 | I28: =(O28+T28+Y28+AD28+AI28+AN28) -> 17250000 | J28: =2300000*1.5 -> 3450000 | O28: =SUM(K28:N28) -> 0 | S28: 3450000 | T28: =SUM(P28:S28) -> 3450000 | X28: =2300000*1.5 -> 3450000 | Y28: =SUM(U28:X28) -> 3450000 | AC28: =2300000*1.5 -> 3450000 | AD28: =SUM(Z28:AC28) -> 3450000 | AH28: =2300000*1.5 -> 3450000 | AI28: =SUM(AE28:AH28) -> 3450000 | AM28: =2300000*1.5 -> 3450000 | AN28: =SUM(AJ28:AM28) -> 3450000
B29: 1.4 | C29: Campamentos, protecciones e insumos de obra | G29: =SUM(G30:G38) -> 750834.4 | I29: =SUM(I30:I38) -> 661557 | J29: =SUM(J30:J38) -> 661557 | K29: =SUM(K30:K38) -> 0 | L29: =SUM(L30:L38) -> 0 | M29: =SUM(M30:M38) -> 0 | N29: =SUM(N30:N38) -> 661557 | O29: =SUM(O30:O38) -> 661557 | P29: =SUM(P30:P38) -> 0 | ... AN29: =SUM(AN30:AN38) -> 0
B30: 1.4.1 | C30: Kit señalización para campamentos (hasta 120 m2) | D30: 3 | E30: und | F30: 125384.3 | G30: =+D30*F30 -> 376152.9 | I30: =(O30+T30+Y30+AD30+AI30+AN30) -> 150000 | J30: 150000 | N30: 150000 | O30: =SUM(K30:N30) -> 150000 | T30: =SUM(P30:S30) -> 0 | Y30: =SUM(U30:X30) -> 0 | AD30: =SUM(Z30:AC30) -> 0 | AI30: =SUM(AE30:AH30) -> 0 | AN30: =SUM(AJ30:AM30) -> 0
B31: 1.4.2 | C31: Cascos de seguridad | D31: 1 | E31: und | F31: 17867 | G31: =+D31*F31 -> 17867 | I31: =(O31+T31+Y31+AD31+AI31+AN31) -> 17850 | J31: 17850 | N31: 17850 | O31: =SUM(K31:N31) -> 17850 | T31: =SUM(P31:S31) -> 0 | Y31: =SUM(U31:X31) -> 0 | AD31: =SUM(Z31:AC31) -> 0 | AI31: =SUM(AE31:AH31) -> 0 | AN31: =SUM(AJ31:AM31) -> 0
B32: 1.4.3 | C32: Protección auditiva | D32: 3 | E32: und | F32: 2627.5 | G32: =+D32*F32 -> 7882.5 | I32: =(O32+T32+Y32+AD32+AI32+AN32) -> 4341 | J32: 4341 | N32: 4341 | O32: =SUM(K32:N32) -> 4341 | T32: =SUM(P32:S32) -> 0 | Y32: =SUM(U32:X32) -> 0 | AD32: =SUM(Z32:AC32) -> 0 | AI32: =SUM(AE32:AH32) -> 0 | AN32: =SUM(AJ32:AM32) -> 0
B33: 1.4.4 | C33: Guantes de nitrilo | D33: 3 | E33: und | F33: 5780.5 | G33: =+D33*F33 -> 17341.5 | I33: =(O33+T33+Y33+AD33+AI33+AN33) -> 23324 | J33: 23324 | N33: 23324 | O33: =SUM(K33:N33) -> 23324 | T33: =SUM(P33:S33) -> 0 | Y33: =SUM(U33:X33) -> 0 | AD33: =SUM(Z33:AC33) -> 0 | AI33: =SUM(AE33:AH33) -> 0 | AN33: =SUM(AJ33:AM33) -> 0
B34: 1.4.5 | C34: Par de botas de agua | D34: 1 | E34: und | F34: 72519 | G34: =+D34*F34 -> 72519 | I34: =(O34+T34+Y34+AD34+AI34+AN34) -> 66640 | J34: 66640 | N34: 66640 | O34: =SUM(K34:N34) -> 66640 | T34: =SUM(P34:S34) -> 0 | Y34: =SUM(U34:X34) -> 0 | AD34: =SUM(Z34:AC34) -> 0 | AI34: =SUM(AE34:AH34) -> 0 | AN34: =SUM(AJ34:AM34) -> 0
B35: 1.4.6 | C35: Par de botas de seguridad | D35: 1 | E35: und | F35: 118763 | G35: =+D35*F35 -> 118763 | I35: =(O35+T35+Y35+AD35+AI35+AN35) -> 116739 | J35: 116739 | N35: 116739 | O35: =SUM(K35:N35) -> 116739 | T35: =SUM(P35:S35) -> 0 | Y35: =SUM(U35:X35) -> 0 | AD35: =SUM(Z35:AC35) -> 0 | AI35: =SUM(AE35:AH35) -> 0 | AN35: =SUM(AJ35:AM35) -> 0
B36: 1.4.7 | C36: Gafas de seguridad | D36: 3 | E36: und | F36: 3678.5 | G36: =+D36*F36 -> 11035.5 | I36: =(O36+T36+Y36+AD36+AI36+AN36) -> 14756 | J36: 14756 | N36: 14756 | O36: =SUM(K36:N36) -> 14756 | T36: =SUM(P36:S36) -> 0 | Y36: =SUM(U36:X36) -> 0 | AD36: =SUM(Z36:AC36) -> 0 | AI36: =SUM(AE36:AH36) -> 0 | AN36: =SUM(AJ36:AM36) -> 0
B37: 1.4.8 | C37: Chalecos reflectivos | D37: 1 | E37: und | F37: 78825 | G37: =+D37*F37 -> 78825 | I37: =(O37+T37+Y37+AD37+AI37+AN37) -> 81037 | J37: 81037 | N37: 81037 | O37: =SUM(K37:N37) -> 81037 | T37: =SUM(P37:S37) -> 0 | Y37: =SUM(U37:X37) -> 0 | AD37: =SUM(Z37:AC37) -> 0 | AI37: =SUM(AE37:AH37) -> 0 | AN37: =SUM(AJ37:AM37) -> 0
B38: 1.4.9 | C38: Overoles | D38: 1 | E38: und | F38: 50448 | G38: =+D38*F38 -> 50448 | I38: =(O38+T38+Y38+AD38+AI38+AN38) -> 186870 | J38: 186870 | N38: 186870 | O38: =SUM(K38:N38) -> 186870 | T38: =SUM(P38:S38) -> 0 | Y38: =SUM(U38:X38) -> 0 | AD38: =SUM(Z38:AC38) -> 0 | AI38: =SUM(AE38:AH38) -> 0 | AN38: =SUM(AJ38:AM38) -> 0
B39: 1.5 | C39: G.C. | D39: =SUM(D40) -> 1 | E39: =SUM(E40) -> 0 | F39: =SUM(F40) -> 58546503 | G39: =SUM(G40) -> 58546503 | I39: =SUM(I40) -> 58546503 | J39: =SUM(J40) -> 58546503 | K39: =SUM(K40) -> 0 | L39: =SUM(L40) -> 0 | M39: =SUM(M40) -> 58546503 | N39: =SUM(N40) -> 0 | O39: =SUM(O40) -> 58546503 | P39: =SUM(P40) -> 0 | ... AN39: =SUM(AN40) -> 0
B40: 1.5.1 | C40: TRANSPORTES | D40: 1 | E40: glb | F40: 58546503 | G40: =+D40*F40 -> 58546503 | I40: =(O40+T40+Y40+AD40+AI40+AN40) -> 58546503 | J40: 58546503 | M40: 58546503 | O40: =SUM(K40:N40) -> 58546503 | T40: =SUM(P40:S40) -> 0 | Y40: =SUM(U40:X40) -> 0 | AD40: =SUM(Z40:AC40) -> 0 | AI40: =SUM(AE40:AH40) -> 0 | AN40: =SUM(AJ40:AM40) -> 0
B41: 3 | C41: Viaticos | G41: =G42 -> 0 | I41: =I42 -> 17881010 | J41: =J42 -> 4200000 | K41: =K42 -> 0 | L41: =L42 -> 0 | M41: =M42 -> 0 | N41: =N42 -> 0 | O41: =O42 -> 0 | P41: =P42 -> 1497410 | ... AN41: =AN42 -> 4716200
B42: 3.1 | C42: Viaticos | G42: =SUM(G43:G46) -> 0 | I42: =SUM(I43:I46) -> 17881010 | J42: =SUM(J43:J46) -> 4200000 | K42: =SUM(K43:K46) -> 0 | L42: =SUM(L43:L46) -> 0 | M42: =SUM(M43:M46) -> 0 | N42: =SUM(N43:N46) -> 0 | O42: =SUM(O43:O46) -> 0 | P42: =SUM(P43:P46) -> 1497410 | ... AN42: =SUM(AN43:AN46) -> 4716200
B43: 3.1.1 | C43: Hospedaje | I43: =(O43+T43+Y43+AD43+AI43+AN43) -> 9048000 | J43: 1237600 | O43: =SUM(K43:N43) -> 0 | P43: 500000 | T43: =SUM(P43:S43) -> 500000 | V43: 1348000 | Y43: =SUM(U43:X43) -> 1348000 | AB43: 2400000 | AD43: =SUM(Z43:AC43) -> 2400000 | AG43: 2400000 | AI43: =SUM(AE43:AH43) -> 2400000 | AL43: 2400000 | AN43: =SUM(AJ43:AM43) -> 2400000
B44: 3.1.2 | C44: Transportes | I44: =(O44+T44+Y44+AD44+AI44+AN44) -> 586500 | J44: 292400 | O44: =SUM(K44:N44) -> 0 | P44: 147900 | T44: =SUM(P44:S44) -> 147900 | Y44: =SUM(U44:X44) -> 0 | AB44: 146200 | AD44: =SUM(Z44:AC44) -> 146200 | AG44: 146200 | AI44: =SUM(AE44:AH44) -> 146200 | AL44: 146200 | AN44: =SUM(AJ44:AM44) -> 146200
B45: 3.1.3 | C45: Pasajes | I45: =(O45+T45+Y45+AD45+AI45+AN45) -> 1539510 | J45: 2190000 | O45: =SUM(K45:N45) -> 0 | P45: 609510 | T45: =SUM(P45:S45) -> 609510 | Y45: =SUM(U45:X45) -> 0 | AB45: 310000 | AD45: =SUM(Z45:AC45) -> 310000 | AG45: 310000 | AI45: =SUM(AE45:AH45) -> 310000 | AL45: 310000 | AN45: =SUM(AJ45:AM45) -> 310000
B46: 3.1.4 | C46: Alimentacion | I46: =(O46+T46+Y46+AD46+AI46+AN46) -> 6707000 | J46: 480000 | O46: =SUM(K46:N46) -> 0 | P46: 240000 | T46: =SUM(P46:S46) -> 240000 | V46: 887000 | Y46: =SUM(U46:X46) -> 887000 | AB46: 1860000 | AD46: =SUM(Z46:AC46) -> 1860000 | AG46: 1860000 | AI46: =SUM(AE46:AH46) -> 1860000 | AL46: 1860000 | AN46: =SUM(AJ46:AM46) -> 1860000
B47: 4 | C47: INGENIERÍA | G47: =G48 -> 0 | I47: =I48 -> 11448636 | J47: =J48 -> 11448635 | K47: =K48 -> 0 | L47: =L48 -> 0 | M47: =M48 -> 0 | N47: =N48 -> 0 | O47: =O48 -> 0 | P47: =P48 -> 0 | ... AN47: =AN48 -> 0
B48: 4.1 | C48: Ingenieria de taller | G48: =G49 -> 0 | I48: =I49 -> 11448636 | J48: =J49 -> 11448635 | K48: =K49 -> 0 | L48: =L49 -> 0 | M48: =M49 -> 0 | N48: =N49 -> 0 | O48: =O49 -> 0 | P48: =P49 -> 0 | ... AN48: =AN49 -> 0
B49: 4.1.1 | C49: Ingenieria de taller | I49: =(O49+T49+Y49+AD49+AI49+AN49) -> 11448636 | J49: 11448635 | O49: =SUM(K49:N49) -> 0 | T49: =SUM(P49:S49) -> 0 | Y49: =SUM(U49:X49) -> 0 | AD49: =SUM(Z49:AC49) -> 0 | AF49: 5724317.5 | AH49: 5724318 | AI49: =SUM(AE49:AH49) -> 11448636 | AN49: =SUM(AJ49:AM49) -> 0
B50: 5 | C50: Suministros | G50: =SUM(G51) -> 0 | I50: =SUM(I51) -> 2.4344444e+08 | J50: =SUM(J51) -> 2045743.3 | K50: =SUM(K51) -> 0 | L50: =SUM(L51) -> 0 | M50: =SUM(M51) -> 0 | N50: =SUM(N51) -> 0 | O50: =SUM(O51) -> 0 | P50: =SUM(P51) -> 0 | ... AN50: =SUM(AN51) -> 0
B51: 5.1 | C51: PINTURA | G51: =G53 -> 0 | I51: =I52+I56 -> 2.4344444e+08 | J51: =J52+J56 -> 2045743.3 | K51: =K52+K56 -> 0 | L51: =L52+L56 -> 0 | M51: =M52+M56 -> 0 | N51: =N52+N56 -> 0 | O51: =O52+O56 -> 0 | P51: =P52+P56 -> 0 | ... AN51: =AN52+AN56 -> 0
B52: 5.1.1 | C52: Epoxico | I52: =SUM(I53:I55) -> 93907565 | J52: =SUM(J53:J55) -> 866096.28 | K52: =SUM(K53:K55) -> 0 | L52: =SUM(L53:L55) -> 0 | M52: =SUM(M53:M55) -> 0 | N52: =SUM(N53:N55) -> 0 | O52: =SUM(O53:O55) -> 0 | P52: =SUM(P53:P55) -> 0 | ... AN52: =SUM(AN53:AN55) -> 0
B53: 5.1.1.1 | C53: Anticorrosivo epoxico x cuñete | D53: 136 | E53: Cuñetes | I53: =(O53+T53+Y53+AD53+AI53+AN53)*J53 -> 91167061 | J53: =563316*1.19 -> 670346.04 | O53: =SUM(K53:N53) -> 0 | Q53: 43 | S53: 93 | T53: =SUM(P53:S53) -> 136 | Y53: =SUM(U53:X53) -> 0 | AD53: =SUM(Z53:AC53) -> 0 | AI53: =SUM(AE53:AH53) -> 0 | AN53: =SUM(AJ53:AM53) -> 0
B54: 5.1.1.2 | C54: Catalizador | I54: =(O54+T54+Y54+AD54+AI54+AN54)*J54 -> 0 | O54: =SUM(K54:N54) -> 0 | T54: =SUM(P54:S54) -> 0 | Y54: =SUM(U54:X54) -> 0 | AD54: =SUM(Z54:AC54) -> 0 | AI54: =SUM(AE54:AH54) -> 0 | AN54: =SUM(AJ54:AM54) -> 0
B55: 5.1.1.3 | C55: Disolvente epoxicco cuñete | D55: 13 | E55: Cuñetes | I55: =(O55+T55+Y55+AD55+AI55+AN55)*J55 -> 2740503.4 | J55: =164496*1.19 -> 195750.24 | O55: =SUM(K55:N55) -> 0 | Q55: 5 | S55: 9 | T55: =SUM(P55:S55) -> 14 | Y55: =SUM(U55:X55) -> 0 | AD55: =SUM(Z55:AC55) -> 0 | AI55: =SUM(AE55:AH55) -> 0 | AN55: =SUM(AJ55:AM55) -> 0
B56: 5.1.2 | C56: Pintura | I56: =SUM(I57:I59) -> 1.4953687e+08 | J56: =SUM(J57:J59) -> 1179647 | K56: =SUM(K57:K59) -> 0 | L56: =SUM(L57:L59) -> 0 | M56: =SUM(M57:M59) -> 0 | N56: =SUM(N57:N59) -> 0 | O56: =SUM(O57:O59) -> 0 | P56: =SUM(P57:P59) -> 0 | ... AN56: =SUM(AN57:AN59) -> 0
B57: 5.1.2.1 | C57: Esmalte Urretano | D57: 149 | E57: Cuñetes | I57: =(O57+T57+Y57+AD57+AI57+AN57)*J57 -> 1.4660062e+08 | J57: =826804*1.19 -> 983896.76 | O57: =SUM(K57:N57) -> 0 | T57: =SUM(P57:S57) -> 0 | Y57: =SUM(U57:X57) -> 0 | AA57: 149 | AD57: =SUM(Z57:AC57) -> 149 | AI57: =SUM(AE57:AH57) -> 0 | AN57: =SUM(AJ57:AM57) -> 0
B58: 5.1.2.2 | C58: Catalizador Urretano | I58: =(O58+T58+Y58+AD58+AI58+AN58)*J58 -> 0 | O58: =SUM(K58:N58) -> 0 | T58: =SUM(P58:S58) -> 0 | Y58: =SUM(U58:X58) -> 0 | AD58: =SUM(Z58:AC58) -> 0 | AI58: =SUM(AE58:AH58) -> 0 | AN58: =SUM(AJ58:AM58) -> 0
B59: 5.1.2.3 | C59: Solvente Uretano | D59: 15 | E59: Cuñetes | I59: =(O59+T59+Y59+AD59+AI59+AN59)*J59 -> 2936253.6 | J59: =164496*1.19 -> 195750.24 | O59: =SUM(K59:N59) -> 0 | T59: =SUM(P59:S59) -> 0 | Y59: =SUM(U59:X59) -> 0 | AA59: 15 | AD59: =SUM(Z59:AC59) -> 15 | AI59: =SUM(AE59:AH59) -> 0 | AN59: =SUM(AJ59:AM59) -> 0
B60: 6 | C60: Mano de obra | G60: =SUM(G61) -> #REF! | I60: =SUM(I61) -> 2.3690257e+09 | J60: =SUM(J61) -> 9025.4277 | K60: =SUM(K61) -> 0 | L60: =SUM(L61) -> 0 | M60: =SUM(M61) -> 0 | N60: =SUM(N61) -> 0 | O60: =SUM(O61) -> 0 | P60: =SUM(P61) -> 0 | ... AN60: =SUM(AN61) -> 86200
B61: 6.1 | C61: Fabricación de EEMM | G61: =#REF! -> #REF! | I61: =SUM(I62:I63) -> 2.3690257e+09 | J61: =SUM(J62:J63) -> 9025.4277 | K61: =SUM(K62:K63) -> 0 | L61: =SUM(L62:L63) -> 0 | M61: =SUM(M62:M63) -> 0 | N61: =SUM(N62:N63) -> 0 | O61: =SUM(O62:O63) -> 0 | P61: =SUM(P62:P63) -> 0 | ... AN61: =SUM(AN62:AN63) -> 86200
B62: 6.1.1. | C62: Proveedor 1 | D62: =O62+T62+Y62+AD62+AI62+AN62 -> 330008.6 | I62: =(O62+T62+Y62+AD62+AI62+AN62)*J62 -> 1.4314829e+09 | J62: 4337.7139 | O62: =SUM(K62:N62) -> 0 | P62: 0 | Q62: 5072.4 | R62: 9583 | S62: 17682.2 | T62: =SUM(P62:S62) -> 32337.6 | V62: 11678 | W62: 17785 | X62: 6305 | Y62: =SUM(U62:X62) -> 35768 | Z62: 10678 | AA62: 5287 | AB62: 14738 | AC62: 25000 | AD62: =SUM(Z62:AC62) -> 55703 | AG62: 40000 | AH62: 80000 | AI62: =SUM(AE62:AH62) -> 120000 | AJ62: 85000 | AK62: 1200 | AN62: =SUM(AJ62:AM62) -> 86200
B63: 6.1.2. | C63: Proveedor 2 | I63: =(O63+T63+Y63+AD63+AI63+AN63)*J63 -> 9.3754277e+08 | J63: =J62+350 -> 4687.7139 | T63: =SUM(P63:S63) -> 0 | Y63: =SUM(U63:X63) -> 0 | AD63: =SUM(Z63:AC63) -> 0 | AE63: 80000 | AF63: 80000 | AG63: 40000 | AI63: =SUM(AE63:AH63) -> 200000
C66: Totales | F66: =F53*D53 -> 0 | G66: =G60+G50+G47+G41+G14 -> #REF! | I66: =I60+I50+I47+I41+I14 -> 2.7971004e+09 | K66: =(K60*#REF!)+(K53*$J$53)+(K54*$J$54)+(K55*$J$55)+(K57*$J$57)+(K58*$J$58)+(K59*$J$59)+K47+K41+K14 -> #REF! | L66: =(L60*#REF!)+(L53*$J$53)+(L54*$J$54)+(L55*$J$55)+(L57*$J$57)+(L58*$J$58)+(L59*$J$59)+L47+L41+L14 -> #REF! | M66: =(M60*#REF!)+(M53*$J$53)+(M54*$J$54)+(M55*$J$55)+(M57*$J$57)+(M58*$J$58)+(M59*$J$59)+M47+M41+M14 -> #REF! | N66: =(N60*#REF!)+(N53*$J$53)+(N54*$J$54)+(N55*$J$55)+(N57*$J$57)+(N58*$J$58)+(N59*$J$59)+N47+N41+N14 -> #REF! | O66: =(O60*#REF!)+(O53*$J$53)+(O54*$J$54)+(O55*$J$55)+(O57*$J$57)+(O58*$J$58)+(O59*$J$59)+O47+O41+O14 -> #REF! | P66: =(P60*#REF!)+(P53*$J$53)+(P54*$J$54)+(P55*$J$55)+(P57*$J$57)+(P58*$J$58)+(P59*$J$59)+P47+P41+P14 -> #REF! | Q66: =(Q60*#REF!)+(Q53*$J$53)+(Q54*$J$54)+(Q55*$J$55)+(Q57*$J$57)+(Q58*$J$58)+(Q59*$J$59)+Q47+Q41+Q14 -> #REF! | R66: =(R60*#REF!)+(R53*$J$53)+(R54*$J$54)+(R55*$J$55)+(R57*$J$57)+(R58*$J$58)+(R59*$J$59)+R47+R41+R14 -> #REF! | ... U66: =(U60*#REF!)+(U53*$J$53)+(U54*$J$54)+(U55*$J$55)+(U57*$J$57)+(U58*$J$58)+(U59*$J$59)+U47+U41+U14 -> #REF! | V66: =(V60*#REF!)+(V53*$J$53)+(V54*$J$54)+(V55*$J$55)+(AA57*$J$57)+(AA58*$J$58)+(AA59*$J$59)+V47+V41+V14 -> #REF! | W66: =(W60*#REF!)+(W53*$J$53)+(W54*$J$54)+(W55*$J$55)+(W57*$J$57)+(W58*$J$58)+(W59*$J$59)+W47+W41+W14 -> #REF! | X66: =(X60*#REF!)+(X53*$J$53)+(X54*$J$54)+(X55*$J$55)+(X57*$J$57)+(X58*$J$58)+(X59*$J$59)+X47+X41+X14 -> #REF! | Y66: =(Y60*#REF!)+(Y53*$J$53)+(Y54*$J$54)+(Y55*$J$55)+(Y57*$J$57)+(Y58*$J$58)+(Y59*$J$59)+Y47+Y41+Y14 -> #REF! | Z66: =(Z60*#REF!)+(Z53*$J$53)+(Z54*$J$54)+(Z55*$J$55)+(Z57*$J$57)+(Z58*$J$58)+(Z59*$J$59)+Z47+Z41+Z14 -> #REF! | AA66: =(AA60*#REF!)+(AA53*$J$53)+(AA54*$J$54)+(AA55*$J$55)+(#REF!*$J$57)+(#REF!*$J$58)+(#REF!*$J$59)+AA47+AA41+AA14 -> #REF! | AB66: =(AB60*#REF!)+(AB53*$J$53)+(AB54*$J$54)+(AB55*$J$55)+(AB57*$J$57)+(AB58*$J$58)+(AB59*$J$59)+AB47+AB41+AB14 -> #REF!
B75: OPC 1
B76: Costo | C76: 3824.47
B77: A | C77: =C76*6.42% -> 245.53097 | G77: =SUM(C77:C79)/C76 -> 0.1342
B78: I | C78: =C76*2% -> 76.4894
B79: U | C79: =C76*5% -> 191.2235
B80: IVA | C80: =C79*19% -> 36.332465
B81: Total | C81: =SUM(C76:C80) -> 4374.0463 | D81: 530000 | E81: =C81*D81 -> 2.3182446e+09
B83: Costo | C83: 3970.41
B84: A | C84: 254.9
B85: I | C85: 79.41
B86: U | C86: 198.52
B87: IVA | C87: =C86*19% -> 37.7188
B88: Total | C88: =SUM(C83:C87) -> 4540.9588 | D88: 530000 | E88: =C88*D88 -> 2.4067082e+09
L104: Anticipo | P104: Corte avance (2 semanas) 50 ton pago en 30 días | R104: Corte avance (2 semanas) 50 ton pago en 30 días | U104: Corte avance (2 semanas) 50 ton pago en 30 días | W104: Corte avance (2 semanas) 50 ton pago en 30 días | Z104: Corte avance (2 semanas) 50 ton pago en 30 días | AB104: Corte avance entrega final 30 ton pago en 30 días
J105: 530000 | L105: 151169.52 | P105: 50000 | S105: 50000 | U105: 88000 | W105: 88000 | Z105: 88000 | AB105: 14830.48 | AE105: 64869261
J106: =J105*#REF! -> #REF! | L106: =L105*#REF! -> #REF! | P106: =P105*#REF! -> #REF! | S106: =S105*#REF! -> #REF! | U106: =U105*#REF! -> #REF! | W106: =W105*#REF! -> #REF! | Z106: =W106 -> #REF! | AB106: =AB105*#REF! -> #REF!

Sheet FLUJO DE CAJA PROYECTADO  (V1)
B5: 1 | C5: 2 | D5: 3 | E5: 4 | F5: 5 | G5: 6 | H5: 7 | I5: 8 | J5: 9 | K5: 10 | L5: 11 | M5: 12 | N5: 13 | O5: 14 | P5: 15 | Q5: 16 | R5: 17 | S5: 18 | T5: 19 | U5: 20 | V5: 21 | W5: 22 | X5: 23 | Y5: 24 | Z5: 25 | AA5: 26 | AB5: 27 | AC5: 28 | AD5: 29 | AE5: 30 | AF5: 31 | AG5: 32 | AH5: 33 | AI5: 34
B6: Código | C6: ITEM | D6: Cantidad+desp. | E6: Unidad de medida | F6: Valor Unitario | G6: Total presupuesto | I6: Valor total | J6: Valor Unitario | K6: semana 1 | L6: semana 2 | M6: semana 3 | N6: semana 4 | O6: Total Abril 2026 | P6: semana 5 | Q6: semana 6 | R6: semana 7 | S6: semana 8 | T6: Total mayo 2026 | U6: semana 9 | V6: semana 10 | W6: semana 11 | X6: semana 12 | Y6: Total junio 2026 | Z6: semana 13 | AA6: semana 14 | AB6: semana 15 | AC6: semana 16 | AD6: Total julio 2026 | AE6: semana 17 | AF6: semana 18 | AG6: semana 19 | AH6: semana 20 | AI6: Total Agosto 2026
B7: 1 | C7: Indirectos | G7: =SUM(G8,G15,G19,G21,G31) -> 1.5053398e+08 | I7: =SUM(I8,I15,I19,I21,I31) -> 1.5105809e+08 | J7: =SUM(J8,J15,J19,J21,J31) -> 120426289 | K7: =SUM(K8,K15,K19,K21,K31) -> 0 | L7: =SUM(L8,L15,L19,L21,L31) -> 0 | M7: =SUM(M8,M15,M19,M21,M31) -> 64463869 | N7: =SUM(N8,N15,N19,N21,N31) -> 3097443 | O7: =SUM(O8,O15,O19,O21,O31) -> 67561312 | P7: =SUM(P8,P15,P19,P21,P31) -> 0 | ... AI7: =SUM(AI8,AI15,AI19,AI21,AI31) -> 14449767
B8: 1.1 | C8: Polizas talleres | D8: =SUM(D9:D14) -> 6 | E8: =SUM(E9:E14) -> 0 | F8: =SUM(F9:F14) -> 18295782 | G8: =SUM(G9:G14) -> 18295782 | I8: =SUM(I9:I14) -> 13451751 | J8: =SUM(J9:J14) -> 5917366 | K8: =SUM(K9:K14) -> 0 | L8: =SUM(L9:L14) -> 0 | M8: =SUM(M9:M14) -> 5917366 | N8: =SUM(N9:N14) -> 0 | O8: =SUM(O9:O14) -> 5917366 | P8: =SUM(P9:P14) -> 0 | ... AI8: =SUM(AI9:AI14) -> 7534385
B9: 1.1.1 | C9: Buen manejo de anticipo | D9: 1 | E9: glb | F9: 3512790.2 | G9: =+D9*F9 -> 3512790.2 | I9: =O9+T9+Y9+AD9+AI9 -> 1844836.1 | J9: 516713.12 | M9: 516713.12 | O9: =SUM(K9:N9) -> 516713.12 | T9: =SUM(P9:S9) -> 0 | Y9: =SUM(U9:X9) -> 0 | AD9: =SUM(Z9:AC9) -> 0 | AH9: 1328123 | AI9: =SUM(AE9:AH9) -> 1328123
B10: 1.1.2 | C10: Cumplimiento | D10: 1 | E10: glb | F10: 3073691.4 | G10: =+D10*F10 -> 3073691.4 | I10: =O10+T10+Y10+AD10+AI10 -> 910373.43 | J10: 465741.43 | M10: 465741.43 | O10: =SUM(K10:N10) -> 465741.43 | T10: =SUM(P10:S10) -> 0 | Y10: =SUM(U10:X10) -> 0 | AD10: =SUM(Z10:AC10) -> 0 | AH10: 444632 | AI10: =SUM(AE10:AH10) -> 444632
B11: 1.1.3 | C11: Salarios y prestaciones sociales | D11: 1 | E11: glb | F11: 2049127.6 | G11: =+D11*F11 -> 2049127.6 | I11: =O11+T11+Y11+AD11+AI11 -> 612043.07 | J11: 349306.07 | M11: 349306.07 | O11: =SUM(K11:N11) -> 349306.07 | T11: =SUM(P11:S11) -> 0 | Y11: =SUM(U11:X11) -> 0 | AD11: =SUM(Z11:AC11) -> 0 | AH11: 262737 | AI11: =SUM(AE11:AH11) -> 262737
B12: 1.1.4 | C12: Estabilidad de obra | D12: 1 | E12: glb | F12: 3073691.4 | G12: =+D12*F12 -> 3073691.4 | I12: =O12+T12+Y12+AD12+AI12 -> 7879684.9 | J12: 4184037.9 | M12: 4184037.9 | O12: =SUM(K12:N12) -> 4184037.9 | T12: =SUM(P12:S12) -> 0 | Y12: =SUM(U12:X12) -> 0 | AD12: =SUM(Z12:AC12) -> 0 | AH12: 3695647 | AI12: =SUM(AE12:AH12) -> 3695647
B13: 1.1.5 | C13: Calidad de obra | D13: 1 | E13: glb | F13: 3073691.4 | G13: =+D13*F13 -> 3073691.4 | I13: =O13+T13+Y13+AD13+AI13 -> 1222251 | J13: 9282 | M13: 9282 | O13: =SUM(K13:N13) -> 9282 | T13: =SUM(P13:S13) -> 0 | Y13: =SUM(U13:X13) -> 0 | AD13: =SUM(Z13:AC13) -> 0 | AH13: 1212969 | AI13: =SUM(AE13:AH13) -> 1212969
B14: 1.1.6 | C14: Responsabilidad civil extracontractural | D14: 1 | E14: glb | F14: 3512790.2 | G14: =+D14*F14 -> 3512790.2 | I14: =O14+T14+Y14+AD14+AI14 -> 982562.52 | J14: =197018.52+195267 -> 392285.52 | M14: =197018.52+195267 -> 392285.52 | O14: =SUM(K14:N14) -> 392285.52 | T14: =SUM(P14:S14) -> 0 | Y14: =SUM(U14:X14) -> 0 | AD14: =SUM(Z14:AC14) -> 0 | AH14: 590277 | AI14: =SUM(AE14:AH14) -> 590277
B15: 1.2. | C15: Impuestos | G15: =SUM(G16:G18) -> 48300865 | I15: =SUM(I16:I18) -> 48300865 | J15: =SUM(J16:J18) -> 48300863 | K15: =SUM(K16:K18) -> 0 | L15: =SUM(L16:L18) -> 0 | M15: =SUM(M16:M18) -> 0 | N15: =SUM(N16:N18) -> 0 | O15: =SUM(O16:O18) -> 0 | P15: =SUM(P16:P18) -> 0 | ... AI15: =SUM(AI16:AI18) -> 0
B16: 1.2.1 | C16: FIC | D16: 1 | E16: glb | F16: 7318312.9 | G16: =+D16*F16 -> 7318312.9 | I16: =O16+T16+Y16+AD16+AI16 -> 7318312.9 | J16: 7318312 | O16: =SUM(K16:N16) -> 0 | T16: =SUM(P16:S16) -> 0 | Y16: =SUM(U16:X16) -> 0 | AC16: 7318312.9 | AD16: =SUM(Z16:AC16) -> 7318312.9 | AI16: =SUM(AE16:AH16) -> 0
B17: 1.2.2 | C17: ICA | D17: 1 | E17: glb | F17: 29273252 | G17: =+D17*F17 -> 29273252 | I17: =O17+T17+Y17+AD17+AI17 -> 29273252 | J17: 29273251 | O17: =SUM(K17:N17) -> 0 | T17: =SUM(P17:S17) -> 0 | Y17: =SUM(U17:X17) -> 0 | AC17: 29273252 | AD17: =SUM(Z17:AC17) -> 29273252 | AI17: =SUM(AE17:AH17) -> 0
B18: 1.2.3 | C18: Cuatro por 1000 | D18: 1 | E18: glb | F18: 11709301 | G18: =+D18*F18 -> 11709301 | I18: =O18+T18+Y18+AD18+AI18 -> 11709301 | J18: 11709300 | O18: =SUM(K18:N18) -> 0 | T18: =SUM(P18:S18) -> 0 | Y18: =SUM(U18:X18) -> 0 | AC18: 11709301 | AD18: =SUM(Z18:AC18) -> 11709301 | AI18: =SUM(AE18:AH18) -> 0
B19: 1.3 | C19: Personal administración | G19: =G20 -> 24640000 | I19: =I20 -> 30097414 | J19: =J20 -> 7000000 | K19: =K20 -> 0 | L19: =L20 -> 0 | M19: =M20 -> 0 | N19: =N20 -> 2435886 | O19: =O20 -> 2435886 | P19: =P20 -> 0 | ... AI19: =AI20 -> 6915382
B20: 1.3.1 | C20: Profesional de calidad 100% | D20: 4 | E20: mes | F20: 6160000 | G20: =+D20*F20 -> 24640000 | I20: =O20+T20+Y20+AD20+AI20 -> 30097414 | J20: 7000000 | N20: 2435886 | O20: =SUM(K20:N20) -> 2435886 | S20: 6915382 | T20: =SUM(P20:S20) -> 6915382 | X20: 6915382 | Y20: =SUM(U20:X20) -> 6915382 | AC20: 6915382 | AD20: =SUM(Z20:AC20) -> 6915382 | AH20: 6915382 | AI20: =SUM(AE20:AH20) -> 6915382
B21: 1.4 | C21: Campamentos, protecciones e insumos de obra | G21: =SUM(G22:G30) -> 750834.4 | I21: =SUM(I22:I30) -> 661557 | J21: =SUM(J22:J30) -> 661557 | K21: =SUM(K22:K30) -> 0 | L21: =SUM(L22:L30) -> 0 | M21: =SUM(M22:M30) -> 0 | N21: =SUM(N22:N30) -> 661557 | O21: =SUM(O22:O30) -> 661557 | P21: =SUM(P22:P30) -> 0 | ... AI21: =SUM(AI22:AI30) -> 0
B22: 1.4.1 | C22: Kit señalización para campamentos (hasta 120 m2) | D22: 3 | E22: und | F22: 125384.3 | G22: =+D22*F22 -> 376152.9 | I22: =O22+T22+Y22+AD22+AI22 -> 150000 | J22: 150000 | N22: 150000 | O22: =SUM(K22:N22) -> 150000 | T22: =SUM(P22:S22) -> 0 | Y22: =SUM(U22:X22) -> 0 | AD22: =SUM(Z22:AC22) -> 0 | AI22: =SUM(AE22:AH22) -> 0
B23: 1.4.2 | C23: Cascos de seguridad | D23: 1 | E23: und | F23: 17867 | G23: =+D23*F23 -> 17867 | I23: =O23+T23+Y23+AD23+AI23 -> 17850 | J23: 17850 | N23: 17850 | O23: =SUM(K23:N23) -> 17850 | T23: =SUM(P23:S23) -> 0 | Y23: =SUM(U23:X23) -> 0 | AD23: =SUM(Z23:AC23) -> 0 | AI23: =SUM(AE23:AH23) -> 0
B24: 1.4.3 | C24: Protección auditiva | D24: 3 | E24: und | F24: 2627.5 | G24: =+D24*F24 -> 7882.5 | I24: =O24+T24+Y24+AD24+AI24 -> 4341 | J24: 4341 | N24: 4341 | O24: =SUM(K24:N24) -> 4341 | T24: =SUM(P24:S24) -> 0 | Y24: =SUM(U24:X24) -> 0 | AD24: =SUM(Z24:AC24) -> 0 | AI24: =SUM(AE24:AH24) -> 0
B25: 1.4.4 | C25: Guantes de nitrilo | D25: 3 | E25: und | F25: 5780.5 | G25: =+D25*F25 -> 17341.5 | I25: =O25+T25+Y25+AD25+AI25 -> 23324 | J25: 23324 | N25: 23324 | O25: =SUM(K25:N25) -> 23324 | T25: =SUM(P25:S25) -> 0 | Y25: =SUM(U25:X25) -> 0 | AD25: =SUM(Z25:AC25) -> 0 | AI25: =SUM(AE25:AH25) -> 0
B26: 1.4.5 | C26: Par de botas de agua | D26: 1 | E26: und | F26: 72519 | G26: =+D26*F26 -> 72519 | I26: =O26+T26+Y26+AD26+AI26 -> 66640 | J26: 66640 | N26: 66640 | O26: =SUM(K26:N26) -> 66640 | T26: =SUM(P26:S26) -> 0 | Y26: =SUM(U26:X26) -> 0 | AD26: =SUM(Z26:AC26) -> 0 | AI26: =SUM(AE26:AH26) -> 0
B27: 1.4.6 | C27: Par de botas de seguridad | D27: 1 | E27: und | F27: 118763 | G27: =+D27*F27 -> 118763 | I27: =O27+T27+Y27+AD27+AI27 -> 116739 | J27: 116739 | N27: 116739 | O27: =SUM(K27:N27) -> 116739 | T27: =SUM(P27:S27) -> 0 | Y27: =SUM(U27:X27) -> 0 | AD27: =SUM(Z27:AC27) -> 0 | AI27: =SUM(AE27:AH27) -> 0
B28: 1.4.7 | C28: Gafas de seguridad | D28: 3 | E28: und | F28: 3678.5 | G28: =+D28*F28 -> 11035.5 | I28: =O28+T28+Y28+AD28+AI28 -> 14756 | J28: 14756 | N28: 14756 | O28: =SUM(K28:N28) -> 14756 | T28: =SUM(P28:S28) -> 0 | Y28: =SUM(U28:X28) -> 0 | AD28: =SUM(Z28:AC28) -> 0 | AI28: =SUM(AE28:AH28) -> 0
B29: 1.4.8 | C29: Chalecos reflectivos | D29: 1 | E29: und | F29: 78825 | G29: =+D29*F29 -> 78825 | I29: =O29+T29+Y29+AD29+AI29 -> 81037 | J29: 81037 | N29: 81037 | O29: =SUM(K29:N29) -> 81037 | T29: =SUM(P29:S29) -> 0 | Y29: =SUM(U29:X29) -> 0 | AD29: =SUM(Z29:AC29) -> 0 | AI29: =SUM(AE29:AH29) -> 0
B30: 1.4.9 | C30: Overoles | D30: 1 | E30: und | F30: 50448 | G30: =+D30*F30 -> 50448 | I30: =O30+T30+Y30+AD30+AI30 -> 186870 | J30: 186870 | N30: 186870 | O30: =SUM(K30:N30) -> 186870 | T30: =SUM(P30:S30) -> 0 | Y30: =SUM(U30:X30) -> 0 | AD30: =SUM(Z30:AC30) -> 0 | AI30: =SUM(AE30:AH30) -> 0
B31: 1.5 | C31: G.C. | D31: =SUM(D32) -> 1 | E31: =SUM(E32) -> 0 | F31: =SUM(F32) -> 58546503 | G31: =SUM(G32) -> 58546503 | I31: =SUM(I32) -> 58546503 | J31: =SUM(J32) -> 58546503 | K31: =SUM(K32) -> 0 | L31: =SUM(L32) -> 0 | M31: =SUM(M32) -> 58546503 | N31: =SUM(N32) -> 0 | O31: =SUM(O32) -> 58546503 | P31: =SUM(P32) -> 0 | ... AI31: =SUM(AI32) -> 0
B32: 1.5.1 | C32: TRANSPORTES | D32: 1 | E32: glb | F32: 58546503 | G32: =+D32*F32 -> 58546503 | I32: =O32+T32+Y32+AD32+AI32 -> 58546503 | J32: 58546503 | M32: 58546503 | O32: =SUM(K32:N32) -> 58546503 | T32: =SUM(P32:S32) -> 0 | Y32: =SUM(U32:X32) -> 0 | AD32: =SUM(Z32:AC32) -> 0 | AI32: =SUM(AE32:AH32) -> 0
B33: 3 | C33: Viaticos | G33: =G34 -> 0 | I33: =I34 -> 4200000 | J33: =J34 -> 4200000 | K33: =K34 -> 0 | L33: =L34 -> 0 | M33: =M34 -> 0 | N33: =N34 -> 0 | O33: =O34 -> 0 | P33: =P34 -> 1850000 | ... AI33: =AI34 -> 0
B34: 3.1 | C34: Viaticos | G34: =SUM(G35:G38) -> 0 | I34: =SUM(I35:I38) -> 4200000 | J34: =SUM(J35:J38) -> 4200000 | K34: =SUM(K35:K38) -> 0 | L34: =SUM(L35:L38) -> 0 | M34: =SUM(M35:M38) -> 0 | N34: =SUM(N35:N38) -> 0 | O34: =SUM(O35:O38) -> 0 | P34: =SUM(P35:P38) -> 1850000 | ... AI34: =SUM(AI35:AI38) -> 0
B35: 3.1.1 | C35: Hospedaje | I35: =O35+T35+Y35+AD35+AI35 -> 1237600 | J35: 1237600 | O35: =SUM(K35:N35) -> 0 | P35: 618800 | T35: =SUM(P35:S35) -> 618800 | Y35: =SUM(U35:X35) -> 0 | AB35: 618800 | AD35: =SUM(Z35:AC35) -> 618800 | AI35: =SUM(AE35:AH35) -> 0
B36: 3.1.2 | C36: Transportes | I36: =O36+T36+Y36+AD36+AI36 -> 292400 | J36: 292400 | O36: =SUM(K36:N36) -> 0 | P36: 146200 | T36: =SUM(P36:S36) -> 146200 | Y36: =SUM(U36:X36) -> 0 | AB36: 146200 | AD36: =SUM(Z36:AC36) -> 146200 | AI36: =SUM(AE36:AH36) -> 0
B37: 3.1.3 | C37: Pasajes | I37: =O37+T37+Y37+AD37+AI37 -> 2190000 | J37: 2190000 | O37: =SUM(K37:N37) -> 0 | P37: 845000 | T37: =SUM(P37:S37) -> 845000 | V37: 500000 | Y37: =SUM(U37:X37) -> 500000 | AB37: 845000 | AD37: =SUM(Z37:AC37) -> 845000 | AI37: =SUM(AE37:AH37) -> 0
B38: 3.1.4 | C38: Alimentacion | I38: =O38+T38+Y38+AD38+AI38 -> 480000 | J38: 480000 | O38: =SUM(K38:N38) -> 0 | P38: 240000 | T38: =SUM(P38:S38) -> 240000 | Y38: =SUM(U38:X38) -> 0 | AB38: 240000 | AD38: =SUM(Z38:AC38) -> 240000 | AI38: =SUM(AE38:AH38) -> 0
B39: 4 | C39: INGENIERÍA | G39: =G40 -> 0 | I39: =I40 -> 11448636 | J39: =J40 -> 11448635 | K39: =K40 -> 0 | L39: =L40 -> 0 | M39: =M40 -> 0 | N39: =N40 -> 0 | O39: =O40 -> 0 | P39: =P40 -> 0 | ... AI39: =AI40 -> 0
B40: 4.1 | C40: Ingenieria de taller | G40: =G41 -> 0 | I40: =I41 -> 11448636 | J40: =J41 -> 11448635 | K40: =K41 -> 0 | L40: =L41 -> 0 | M40: =M41 -> 0 | N40: =N41 -> 0 | O40: =O41 -> 0 | P40: =P41 -> 0 | ... AI40: =AI41 -> 0
B41: 4.1.1 | C41: Ingenieria de taller | I41: =O41+T41+Y41+AD41+AI41 -> 11448636 | J41: 11448635 | O41: =SUM(K41:N41) -> 0 | Q41: 5724317.5 | S41: 5724318 | T41: =SUM(P41:S41) -> 11448636 | Y41: =SUM(U41:X41) -> 0 | AD41: =SUM(Z41:AC41) -> 0 | AI41: =SUM(AE41:AH41) -> 0
B42: 5 | C42: Suministros | G42: =SUM(G43) -> 0 | I42: =SUM(I43) -> 2.4344444e+08 | J42: =SUM(J43) -> 2045743.3 | K42: =SUM(K43) -> 0 | L42: =SUM(L43) -> 0 | M42: =SUM(M43) -> 0 | N42: =SUM(N43) -> 0 | O42: =SUM(O43) -> 0 | P42: =SUM(P43) -> 0 | ... AI42: =SUM(AI43) -> 0
B43: 5.1 | C43: PINTURA | G43: =G45 -> 0 | I43: =I44+I48 -> 2.4344444e+08 | J43: =J44+J48 -> 2045743.3 | K43: =K44+K48 -> 0 | L43: =L44+L48 -> 0 | M43: =M44+M48 -> 0 | N43: =N44+N48 -> 0 | O43: =O44+O48 -> 0 | P43: =P44+P48 -> 0 | ... AI43: =AI44+AI48 -> 0
B44: 5.1.1 | C44: Epoxico | I44: =SUM(I45:I47) -> 93907565 | J44: =SUM(J45:J47) -> 866096.28 | K44: =SUM(K45:K47) -> 0 | L44: =SUM(L45:L47) -> 0 | M44: =SUM(M45:M47) -> 0 | N44: =SUM(N45:N47) -> 0 | O44: =SUM(O45:O47) -> 0 | P44: =SUM(P45:P47) -> 0 | ... AI44: =SUM(AI45:AI47) -> 0
B45: 5.1.1.1 | C45: Anticorrosivo epoxico x cuñete | D45: 136 | E45: Cuñetes | I45: =(O45+T45+Y45+AD45+AI45)*J45 -> 91167061 | J45: =563316*1.19 -> 670346.04 | O45: =SUM(K45:N45) -> 0 | Q45: 43 | S45: 93 | T45: =SUM(P45:S45) -> 136 | Y45: =SUM(U45:X45) -> 0 | AD45: =SUM(Z45:AC45) -> 0 | AI45: =SUM(AE45:AH45) -> 0
B46: 5.1.1.2 | C46: Catalizador | I46: =(O46+T46+Y46+AD46+AI46)*J46 -> 0 | O46: =SUM(K46:N46) -> 0 | T46: =SUM(P46:S46) -> 0 | Y46: =SUM(U46:X46) -> 0 | AD46: =SUM(Z46:AC46) -> 0 | AI46: =SUM(AE46:AH46) -> 0
B47: 5.1.1.3 | C47: Disolvente epoxicco cuñete | D47: 13 | E47: Cuñetes | I47: =(O47+T47+Y47+AD47+AI47)*J47 -> 2740503.4 | J47: =164496*1.19 -> 195750.24 | O47: =SUM(K47:N47) -> 0 | Q47: 5 | S47: 9 | T47: =SUM(P47:S47) -> 14 | Y47: =SUM(U47:X47) -> 0 | AD47: =SUM(Z47:AC47) -> 0 | AI47: =SUM(AE47:AH47) -> 0
B48: 5.1.2 | C48: Pintura | I48: =SUM(I49:I51) -> 1.4953687e+08 | J48: =SUM(J49:J51) -> 1179647 | K48: =SUM(K49:K51) -> 0 | L48: =SUM(L49:L51) -> 0 | M48: =SUM(M49:M51) -> 0 | N48: =SUM(N49:N51) -> 0 | O48: =SUM(O49:O51) -> 0 | P48: =SUM(P49:P51) -> 0 | ... AI48: =SUM(AI49:AI51) -> 0
B49: 5.1.2.1 | C49: Esmalte Urretano | D49: 149 | E49: Cuñetes | I49: =(O49+T49+Y49+AD49+AI49)*J49 -> 1.4660062e+08 | J49: =826804*1.19 -> 983896.76 | O49: =SUM(K49:N49) -> 0 | T49: =SUM(P49:S49) -> 0 | V49: 149 | Y49: =SUM(U49:X49) -> 149 | AD49: =SUM(Z49:AC49) -> 0 | AI49: =SUM(AE49:AH49) -> 0
B50: 5.1.2.2 | C50: Catalizador Urretano | I50: =(O50+T50+Y50+AD50+AI50)*J50 -> 0 | O50: =SUM(K50:N50) -> 0 | T50: =SUM(P50:S50) -> 0 | Y50: =SUM(U50:X50) -> 0 | AD50: =SUM(Z50:AC50) -> 0 | AI50: =SUM(AE50:AH50) -> 0
B51: 5.1.2.3 | C51: Solvente Uretano | D51: 15 | E51: Cuñetes | I51: =(O51+T51+Y51+AD51+AI51)*J51 -> 2936253.6 | J51: =164496*1.19 -> 195750.24 | O51: =SUM(K51:N51) -> 0 | T51: =SUM(P51:S51) -> 0 | V51: 15 | Y51: =SUM(U51:X51) -> 15 | AD51: =SUM(Z51:AC51) -> 0 | AI51: =SUM(AE51:AH51) -> 0
B52: 6 | C52: Mano de obra | G52: =SUM(G53) -> 2519593500 | I52: =SUM(I53) -> 2.3182446e+09 | J52: =SUM(J53) -> 4374.0463 | K52: =SUM(K53) -> 0 | L52: =SUM(L53) -> 0 | M52: =SUM(M53) -> 0 | N52: =SUM(N53) -> 0 | O52: =SUM(O53) -> 0 | P52: =SUM(P53) -> 0 | ... AI52: =SUM(AI53) -> 150000
B53: 6.1 | C53: Fabricación de EEMM | G53: =G54 -> 2519593500 | I53: =I54 -> 2.3182446e+09 | J53: =J54 -> 4374.0463 | K53: =K54 -> 0 | L53: =L54 -> 0 | M53: =M54 -> 0 | N53: =N54 -> 0 | O53: =O54 -> 0 | P53: =P54 -> 0 | ... AI53: =AI54 -> 150000
B54: 6.1.1 | C54: Lámina ARMADO | D54: 530000 | E54: Kg | F54: 4753.95 | G54: =+D54*F54 -> 2519593500 | I54: =(O54+T54+Y54+AD54+AI54)*J54 -> 2.3182446e+09 | J54: =SUM(C69:C73) -> 4374.0463 | L54: =J54*K54 -> 0 | O54: =SUM(K54:N54) -> 0 | P54: =O54*J54 -> 0 | V54: 80000 | X54: 100000 | Y54: =SUM(U54:X54) -> 180000 | AA54: 100000 | AC54: 100000 | AD54: =SUM(Z54:AC54) -> 200000 | AE54: 100000 | AG54: 50000 | AI54: =SUM(AE54:AH54) -> 150000
B55: 6.1.1.p | C55: Proveedor | I55: =(O55+T55+Y55+AD55+AI55)*J55 -> 2.3182446e+09 | J55: =SUM(C69:C73) -> 4374.0463 | O55: =SUM(K55:N55) -> 0 | Q55: 10600 | R55: 15900 | S55: 37100 | T55: =SUM(P55:S55) -> 63600 | U55: 37100 | V55: 53000 | W55: 47700 | X55: 53000 | Y55: =SUM(U55:X55) -> 190800 | Z55: 53000 | AA55: 63600 | AB55: 58300 | AC55: 42400 | AD55: =SUM(Z55:AC55) -> 217300 | AE55: 58300 | AI55: =SUM(AE55:AH55) -> 58300
C59: Totales | F59: =F45*D45 -> 0 | G59: =G52+G42+G39+G33+G7 -> 2.6701275e+09 | I59: =I52+I42+I39+I33+I7 -> 2.7283957e+09 | K59: =(K52*$J$54)+(K45*$J$45)+(K46*$J$46)+(K47*$J$47)+(K49*$J$49)+(K50*$J$50)+(K51*$J$51)+K39+K33+K7 -> 0 | L59: =(L52*$J$54)+(L45*$J$45)+(L46*$J$46)+(L47*$J$47)+(L49*$J$49)+(L50*$J$50)+(L51*$J$51)+L39+L33+L7 -> 0 | M59: =(M52*$J$54)+(M45*$J$45)+(M46*$J$46)+(M47*$J$47)+(M49*$J$49)+(M50*$J$50)+(M51*$J$51)+M39+M33+M7 -> 64463869 | N59: =(N52*$J$54)+(N45*$J$45)+(N46*$J$46)+(N47*$J$47)+(N49*$J$49)+(N50*$J$50)+(N51*$J$51)+N39+N33+N7 -> 3097443 | O59: =(O52*$J$54)+(O45*$J$45)+(O46*$J$46)+(O47*$J$47)+(O49*$J$49)+(O50*$J$50)+(O51*$J$51)+O39+O33+O7 -> 67561312 | P59: =(P52*$J$54)+(P45*$J$45)+(P46*$J$46)+(P47*$J$47)+(P49*$J$49)+(P50*$J$50)+(P51*$J$51)+P39+P33+P7 -> 1850000 | Q59: =(Q52*$J$54)+(Q45*$J$45)+(Q46*$J$46)+(Q47*$J$47)+(Q49*$J$49)+(Q50*$J$50)+(Q51*$J$51)+Q39+Q33+Q7 -> 35527948 | R59: =(R52*$J$54)+(R45*$J$45)+(R46*$J$46)+(R47*$J$47)+(R49*$J$49)+(R50*$J$50)+(R51*$J$51)+R39+R33+R7 -> 0 | ... AI59: =(AI52*$J$54)+(AI45*$J$45)+(AI46*$J$46)+(AI47*$J$47)+(AI49*$J$49)+(AI50*$J$50)+(AI51*$J$51)+AI39+AI33+AI7 -> 6.7055672e+08
H61: PINTURA | I61: =I42 -> 2.4344444e+08 | J61: =I42/D54 -> 459.32912
I62: =SUM(I63) -> 2.4344444e+08 | J62: =SUM(J63) -> 459.32912 | K62: =SUM(K63) -> 0 | L62: =SUM(L63) -> 0 | M62: =SUM(M63) -> 0 | N62: =SUM(N63) -> 0 | O62: =SUM(O63) -> 0 | P62: =SUM(P63) -> 0 | ... AI62: =SUM(AI63) -> 0
I63: =I64 -> 2.4344444e+08 | J63: =J64 -> 459.32912 | K63: =K64 -> 0 | L63: =L64 -> 0 | M63: =M64 -> 0 | N63: =N64 -> 0 | O63: =O64 -> 0 | P63: =P64 -> 0 | ... AI63: =AI64 -> 0
I64: =SUM(K64:AI64)*J64 -> 2.4344444e+08 | J64: =J61 -> 459.32912 | L64: =J64*K64 -> 0 | P64: =O64*J64 -> 0 | V64: 80000 | X64: 100000 | AA64: 100000 | AC64: 100000 | AE64: 100000 | AG64: 50000
I66: 2902704000
B68: OPC 1
B69: Costo | C69: 3824.47 | I69: Margen
B70: A | C70: =C69*6.42% -> 245.53097 | G70: =SUM(C70:C72)/C69 -> 0.1342 | I70: =I66-I59 -> 1.7430828e+08
B71: I | C71: =C69*2% -> 76.4894 | I71: =I70/I66 -> 0.060050311
B72: U | C72: =C69*5% -> 191.2235
B73: IVA | C73: =C72*19% -> 36.332465
B74: Total | C74: =SUM(C69:C73) -> 4374.0463 | D74: 530000 | E74: =C74*D74 -> 2.3182446e+09
B76: Costo | C76: 3970.41
B77: A | C77: 254.9
B78: I | C78: 79.41
B79: U | C79: 198.52
B80: IVA | C80: =C79*19% -> 37.7188
B81: Total | C81: =SUM(C76:C80) -> 4540.9588 | D81: 530000 | E81: =C81*D81 -> 2.4067082e+09
L97: Anticipo | P97: Corte avance (2 semanas) 50 ton pago en 30 días | R97: Corte avance (2 semanas) 50 ton pago en 30 días | U97: Corte avance (2 semanas) 50 ton pago en 30 días | W97: Corte avance (2 semanas) 50 ton pago en 30 días | Z97: Corte avance (2 semanas) 50 ton pago en 30 días | AB97: Corte avance entrega final 30 ton pago en 30 días
J98: 530000 | L98: 151169.52 | P98: 50000 | S98: 50000 | U98: 88000 | W98: 88000 | Z98: 88000 | AB98: 14830.48 | AE98: 64869261
J99: =J98*J54 -> 2.3182446e+09 | L99: =L98*J54 -> 6.6122249e+08 | P99: =P98*J54 -> 2.1870232e+08 | S99: =S98*J54 -> 2.1870232e+08 | U99: =U98*J54 -> 3.8491608e+08 | W99: =W98*J54 -> 3.8491608e+08 | Z99: =W99 -> 3.8491608e+08 | AB99: =AB98*J54 -> 64869207

Sheet Resumen
B2: Cuadro de Control
B4: =+C6 -> NORTON EDIFICIOS INDUSTRIALES COLOMBIA SAS
B6: EMPRESA: | C6: NORTON EDIFICIOS INDUSTRIALES COLOMBIA SAS
B7: DOMICILIO: | C7: Calle 93 # 12 - 14, Edificio Tempo 93, Oficina 704
B9: OBRA: | C9: 16-16 | F9: CÓDIGO:
B10: UBICACIÓN: | C10: Bogota | F10: FECHA: | G10: =TODAY() -> 46275
B14: Resumen consolidado | F14: 2927325150
B15: GRUPO | C15: TOTAL | D15: Porcentaje | F15: COSTO | G15: MARGEN
B16: Presupuesto | C16: ='FLUJO DE CAJA PRESU'!D18+'FLUJO DE CAJA PRESU'!D30 -> 2670127485 | D16: 1 | F16: =C16/$F$14 -> 0.91213902 | G16: =1-F16 -> 0.087860983
B17: Proyectado | C17: ='FLUJO DE CAJA PROYECTADO '!I66 -> 2.791884e+09 | D17: =C17/C16 -> 1.0455995 | F17: =C17/$F$14 -> 0.95373212 | G17: =1-F17 -> 0.04626788
B18: Avance de Obra | D18: ='CURVA S'!L21 -> 0.42502835 | F18: =SUM('CURVA S'!I4:I37) -> 2.4714021
B20: Ingresos Real | C20: ='Control Flujo de caja'!V88 -> 1.1021602e+09 | D20: =C20/F14 -> 0.3765076 | F20: =C20/$F$14 -> 0.3765076
B21: Egresos real | C21: ='Control Flujo de caja'!V90 -> 1.1496763e+09 | D21: =C21/C17 -> 0.41179227 | F21: =C21/$F$14 -> 0.39273951 | G21: =1-F21 -> 0.60726049
B22: Avance Contabilidad | C22: =Contabilidad!D53 -> 62862623 | D22: =C22/C17 -> 0.022516202 | F22: =C22/$F$14 -> 0.021474425 | G22: =1-F22 -> 0.97852558
B24: Costo de punto de margen | C24: =F14*0.01 -> 29273252
B25: Margen acumulado a hoy | C25: =C20-C21 -> -47516098
C28: =F14-C17 -> 1.3544113e+08

Sheet Control Flujo de caja
B7: =+C9 -> NORTON EDIFICIOS INDUSTRIALES COLOMBIA SAS
B9: EMPRESA: | C9: NORTON EDIFICIOS INDUSTRIALES COLOMBIA SAS
B10: DOMICILIO: | C10: Calle 93 # 12 - 14, Edificio Tempo 93, Oficina 704
B12: OBRA: | C12: 16-16 | E12: CÓDIGO:
B13: UBICACIÓN: | C13: Bogota | E13: FECHA:
X16: ='FLUJO DE CAJA PROYECTADO '!O12 -> 14 | Y16: =REAL!O12 -> 14 | AA16: ='FLUJO DE CAJA PROYECTADO '!T12 -> 19 | AB16: =AA16 -> 19 | AC16: 2 | AD16: ='FLUJO DE CAJA PROYECTADO '!Y12 -> 24 | AE16: =AD16 -> 24 | AG16: =AD16+5 -> 29 | AH16: =AG16 -> 29 | AJ16: =AG16+5 -> 34 | AK16: =AJ16 -> 34 | AM16: =AJ16+5 -> 39 | AN16: =AM16 -> 39 | AP16: 44 | AQ16: 44
C17: DATOS DE EXPLOTACIÓN | D17: Meses o costo/u | E17: Detalles | X17: ABRIL | AA17: MAYO | AD17: JUNIO | AG17: JULIO | AJ17: AGOSTO | AM17: SEPTIEMBRE | AP17: OCTUBRE
X18: Proyectado | Y18: ="Real"&Z17 -> Real | Z18: Diferencia | AA18: Proyectado | AB18: ="Real"&AC17 -> Real | AC18: Diferencia | AD18: Proyectado | AE18: ="Real"&AF17 -> Real | AF18: Diferencia | AG18: Proyectado | AH18: ="Real"&AI17 -> Real | AI18: Diferencia | AJ18: Proyectado | AK18: ="Real"&AL17 -> Real | AL18: Diferencia | AM18: Proyectado | AN18: ="Real"&AO17 -> Real | AO18: Diferencia | AP18: Proyectado | AQ18: ="Real"&AR17 -> Real | AR18: Diferencia
AE19: =AE76 -> 1.5515135e+08
C20: % DE FACTURACIÓN | W20: % DE FACTURACIÓN
C21: FACTURACION PROYECTO | D21: 2927325150 | W21: FACTURACION PROYECTO | AA21: =HLOOKUP(AA16,'FLUJO DE CAJA PROYECTADO '!$I$5:$AN$8,4,FALSE) -> 0 | AB21: =HLOOKUP(AB16,REAL!$H$5:$AN$8,4,FALSE) -> 0 | AD21: =HLOOKUP(AD16,'FLUJO DE CAJA PROYECTADO '!$I$5:$AN$8,4,FALSE) -> 3.016487e+08 | AE21: =HLOOKUP(AE16,REAL!$H$5:$AN$8,4,FALSE) -> 3.016487e+08 | AG21: =HLOOKUP(AG16,'FLUJO DE CAJA PROYECTADO '!$I$5:$AN$8,4,FALSE) -> 2.732718e+08 | AH21: =HLOOKUP(AH16,REAL!$H$5:$AN$8,4,FALSE) -> 3.0440545e+08 | AJ21: =HLOOKUP(AJ16,'FLUJO DE CAJA PROYECTADO '!$I$5:$AN$8,4,FALSE) -> 994140000 | AK21: =HLOOKUP(AK16,REAL!$H$5:$AN$8,4,FALSE) -> 3.2349017e+08 | AM21: =HLOOKUP(AM16,'FLUJO DE CAJA PROYECTADO '!$I$5:$AN$8,4,FALSE) -> 552300000 | AN21: =HLOOKUP(AN16,REAL!$H$5:$AN$8,4,FALSE) -> 172615842 | AP21: =HLOOKUP(AP16,'FLUJO DE CAJA PROYECTADO '!$I$5:$AZ$8,4,FALSE) -> 805833315 | AQ21: =HLOOKUP(AQ16,REAL!$H$5:$AZ$8,4,FALSE) -> 0
C22: VALOR FACTURADO | W22: VALOR FACTURADO
C23: ANTICIPO | W23: ANTICIPO | X23: 870811200 | Y23: 870811200
W24: Total | X24: =X21+X23 -> 870811200 | Y24: =Y21+Y23 -> 870811200 | Z24: =Z21+Z23 -> 0 | AA24: =AA21+AA23 -> 0 | AB24: =AB21+AB23 -> 0 | AC24: =AC21+AC23 -> 0 | AD24: =AD21+AD23 -> 3.016487e+08 | AE24: =AE21+AE23 -> 3.016487e+08 | ... AR24: =AR21+AR23 -> 0
D26: Presupuesto | E26: Proyectado | J26: Asegurado | P26: Real | U26: Contabilidad | X26: ABRIL | AA26: MAYO | AD26: JUNIO | AG26: JULIO | AJ26: AGOSTO | AM26: SEPTIEMBRE | AP26: octubre
B27: Código | C27: ITEM | D27: Valor Unitario | E27: Cantidad | F27: Valor Unitario | G27: Total proyectado | H27: Desviacion | J27: Cantidad | K27: Valor Unitario | L27: Total proyectado | M27: Desviacion | P27: Cantidad | Q27: Valor Unitario | R27: Total proyectado | S27: Desviacion | U27: Proyectado | V27: Desviacion | X27: Proyectado | Y27: ="Real"&Z26 -> Real | Z27: Desviacion | AA27: Proyectado | AB27: ="Real"&AC26 -> Real | AC27: Desviacion | AD27: Proyectado | AE27: ="Real"&AF26 -> Real | AF27: Desviacion | AG27: Proyectado | AH27: ="Real"&AI26 -> Real | AI27: Desviacion | AJ27: Proyectado | AK27: ="Real"&AL26 -> Real | AL27: Desviacion | AM27: Proyectado | AN27: ="Real"&AO26 -> Real | AO27: Desviacion | AP27: Proyectado | AQ27: ="Real"&AR26 -> Real | AR27: Desviacion
B28: 1 | C28: Indirectos | D28: =SUM(D29,D36,D40,D43,D53) -> 150533984 | E28: =SUM(E29,E36,E40,E43,E53) -> 31 | F28: =SUM(F29,F36,F40,F43,F53) -> 120426289 | G28: =SUM(G29,G36,G40,G43,G53) -> 99465371 | H28: =D28-G28 -> 51068613 | J28: =SUM(J29,J36,J40,J43,J53) -> 31 | K28: =SUM(K29,K36,K40,K43,K53) -> 120426289 | L28: =SUM(L29,L36,L40,L43,L53) -> 66899755 | M28: =SUM(M29,M36,M40,M43,M53) -> 15315616 | P28: =SUM(P29,P36,P40,P43,P53) -> 35 | Q28: =SUM(Q29,Q36,Q40,Q43,Q53) -> 123876289 | R28: =SUM(R29,R36,R40,R43,R53) -> 88200771 | S28: =G28-R28 -> 11264600 | U28: =SUM(#REF!,U29,U37,U43,#REF!,#REF!,#REF!,#REF!,#REF!,U46) -> #REF! | V28: =SUM(V29,V36,V40,V43,V53) -> 62987523 | X28: =SUM(X29,X36,X40,X43,X53) -> 67561312 | Y28: =SUM(Y29,Y36,Y40,Y43,Y53) -> 66899755 | Z28: =SUM(Z29,Z36,Z40,Z43,Z53) -> 661557 | AA28: =SUM(AA29,AA36,AA40,AA43,AA53) -> 10365382 | AB28: =SUM(AB29,AB36,AB40,AB43,AB53) -> 10362570 | AC28: =SUM(AC29,AC36,AC40,AC43,AC53) -> 2812 | AD28: =SUM(AD29,AD36,AD40,AD43,AD53) -> 10365382 | AE28: =SUM(AE29,AE36,AE40,AE43,AE53) -> 7315258 | ... AR28: =SUM(AR29,AR36,AR40,AR43,AR53) -> 60108545
B29: 1.1 | C29: Polizas talleres | D29: 18295782 | E29: =SUM(E30:E35) -> 6 | F29: =SUM(F30:F35) -> 5917366 | G29: =SUM(G30:G35) -> 5917366 | H29: =D29-G29 -> 12378416 | J29: =SUM(J30:J35) -> 6 | K29: =SUM(K30:K35) -> 5917366 | L29: =SUM(L30:L35) -> 5917366 | M29: =SUM(M30:M35) -> 0 | P29: =SUM(P30:P35) -> 6 | Q29: =SUM(Q30:Q35) -> 5917366 | R29: =SUM(R30:R35) -> 5917366 | S29: =G29-R29 -> 0 | U29: =VLOOKUP(B29,Contabilidad!$B$3:$D$51,3,FALSE) -> 5917366.9 | V29: =SUM(V30:V35) -> -0.86 | X29: =SUM(X30:X35) -> 5917366 | Y29: =SUM(Y30:Y35) -> 5917366 | Z29: =SUM(Z30:Z35) -> 0 | AA29: =SUM(AA30:AA35) -> 0 | AB29: =SUM(AB30:AB35) -> 0 | AC29: =SUM(AC30:AC35) -> 0 | AD29: =SUM(AD30:AD35) -> 0 | AE29: =SUM(AE30:AE35) -> 0 | ... AR29: =SUM(AR30:AR35) -> 7534385
B30: 1.1.1 | C30: Buen manejo de anticipo | E30: =VLOOKUP(B30,'FLUJO DE CAJA PROYECTADO '!$B$13:$J$61,3,FALSE) -> 1 | F30: =VLOOKUP(B30,'FLUJO DE CAJA PROYECTADO '!$B$13:$J$61,9,FALSE) -> 516713.12 | G30: =VLOOKUP(B30,'FLUJO DE CAJA PROYECTADO '!$B$13:$J$61,8,FALSE) -> 516713.12 | H30: =D30-G30 -> -516713.12 | J30: =VLOOKUP($B30,ASEGURADO!$B$3:$J$51,3,FALSE) -> 1 | K30: =VLOOKUP(B30,ASEGURADO!$B$3:$J$52,9,FALSE) -> 516713.12 | L30: =VLOOKUP($B30,ASEGURADO!$B$3:$J$52,8,FALSE) -> 516713.12 | M30: =G30-L30 -> 0 | P30: =VLOOKUP(B30,REAL!$B$13:$J$61,3,FALSE) -> 1 | Q30: =VLOOKUP(B30,REAL!$B$13:$J$61,9,FALSE) -> 516713.12 | R30: =VLOOKUP(B30,REAL!$B$13:$J$61,8,FALSE) -> 516713.12 | S30: =G30-R30 -> 0 | U30: =VLOOKUP(B30,Contabilidad!$B$3:$D$51,3,FALSE) -> 0 | V30: =R30-U30 -> 516713.12 | X30: =VLOOKUP($B30,'FLUJO DE CAJA PROYECTADO '!$B$13:$AI$66,'Control Flujo de caja'!X$16,FALSE) -> 516713.12 | Y30: =VLOOKUP($B30,REAL!$B$13:$AI$61,'Control Flujo de caja'!Y$16,FALSE) -> 516713.12 | Z30: =X30-Y30 -> 0 | AA30: =VLOOKUP($B30,'FLUJO DE CAJA PROYECTADO '!$B$13:$AI$66,'Control Flujo de caja'!AA$16,FALSE) -> 0 | AB30: =VLOOKUP($B30,REAL!$B$13:$AI$61,'Control Flujo de caja'!AB$16,FALSE) -> 0 | AC30: =AA30-AB30 -> 0 | AD30: =VLOOKUP($B30,'FLUJO DE CAJA PROYECTADO '!$B$13:$AI$66,'Control Flujo de caja'!AD$16,FALSE) -> 0 | AE30: =VLOOKUP($B30,REAL!$B$13:$AI$61,'Control Flujo de caja'!AE$16,FALSE) -> 0 | AF30: =AD30-AE30 -> 0 | AG30: =VLOOKUP($B30,'FLUJO DE CAJA PROYECTADO '!$B$13:$AI$66,'Control Flujo de caja'!AG$16,FALSE) -> 0 | AH30: =VLOOKUP($B30,REAL!$B$13:$AI$61,'Control Flujo de caja'!AH$16,FALSE) -> 0 | AI30: =AG30-AH30 -> 0 | AJ30: =VLOOKUP($B30,'FLUJO DE CAJA PROYECTADO '!$B$13:$AI$66,'Control Flujo de caja'!AJ$16,FALSE) -> 0 | AK30: =VLOOKUP($B30,REAL!$B$13:$AI$61,'Control Flujo de caja'!AK$16,FALSE) -> 0 | AL30: =AJ30-AK30 -> 0 | AM30: =VLOOKUP($B30,'FLUJO DE CAJA PROYECTADO '!$B$13:$AN$66,'Control Flujo de caja'!AM$16,FALSE) -> 0 | AN30: =VLOOKUP($B30,REAL!$B$13:$AN$61,'Control Flujo de caja'!AN$16,FALSE) -> 0 | AO30: =AM30-AN30 -> 0 | AP30: =VLOOKUP($B30,'FLUJO DE CAJA PROYECTADO '!$B$13:$AS$66,'Control Flujo de caja'!AP$16,FALSE) -> 1328123 | AQ30: =VLOOKUP($B30,REAL!$B$13:$AS$61,'Control Flujo de caja'!AQ$16,FALSE) -> 0 | AR30: =AP30-AQ30 -> 1328123
B31: 1.1.2 | C31: Cumplimiento | E31: =VLOOKUP(B31,'FLUJO DE CAJA PROYECTADO '!$B$13:$J$61,3,FALSE) -> 1 | F31: =VLOOKUP(B31,'FLUJO DE CAJA PROYECTADO '!$B$13:$J$61,9,FALSE) -> 465741.43 | G31: =VLOOKUP(B31,'FLUJO DE CAJA PROYECTADO '!$B$13:$J$61,8,FALSE) -> 465741.43 | H31: =D31-G31 -> -465741.43 | J31: =VLOOKUP($B31,ASEGURADO!$B$3:$J$51,3,FALSE) -> 1 | K31: =VLOOKUP(B31,ASEGURADO!$B$3:$J$52,9,FALSE) -> 465741.43 | L31: =VLOOKUP($B31,ASEGURADO!$B$3:$J$52,8,FALSE) -> 465741.43 | M31: =G31-L31 -> 0 | P31: =VLOOKUP(B31,REAL!$B$13:$J$61,3,FALSE) -> 1 | Q31: =VLOOKUP(B31,REAL!$B$13:$J$61,9,FALSE) -> 465741.43 | R31: =VLOOKUP(B31,REAL!$B$13:$J$61,8,FALSE) -> 465741.43 | S31: =G31-R31 -> 0 | U31: =VLOOKUP(B31,Contabilidad!$B$3:$D$51,3,FALSE) -> 5917366.9 | V31: =R31-U31 -> -5451625.4 | X31: =VLOOKUP($B31,'FLUJO DE CAJA PROYECTADO '!$B$13:$AI$66,'Control Flujo de caja'!X$16,FALSE) -> 465741.43 | Y31: =VLOOKUP($B31,REAL!$B$13:$AI$61,'Control Flujo de caja'!Y$16,FALSE) -> 465741.43 | Z31: =X31-Y31 -> 0 | AA31: =VLOOKUP($B31,'FLUJO DE CAJA PROYECTADO '!$B$13:$AI$66,'Control Flujo de caja'!AA$16,FALSE) -> 0 | AB31: =VLOOKUP($B31,REAL!$B$13:$AI$61,'Control Flujo de caja'!AB$16,FALSE) -> 0 | AC31: =AA31-AB31 -> 0 | AD31: =VLOOKUP($B31,'FLUJO DE CAJA PROYECTADO '!$B$13:$AI$66,'Control Flujo de caja'!AD$16,FALSE) -> 0 | AE31: =VLOOKUP($B31,REAL!$B$13:$AI$61,'Control Flujo de caja'!AE$16,FALSE) -> 0 | AF31: =AD31-AE31 -> 0 | AG31: =VLOOKUP($B31,'FLUJO DE CAJA PROYECTADO '!$B$13:$AI$66,'Control Flujo de caja'!AG$16,FALSE) -> 0 | AH31: =VLOOKUP($B31,REAL!$B$13:$AI$61,'Control Flujo de caja'!AH$16,FALSE) -> 0 | AI31: =AG31-AH31 -> 0 | AJ31: =VLOOKUP($B31,'FLUJO DE CAJA PROYECTADO '!$B$13:$AI$66,'Control Flujo de caja'!AJ$16,FALSE) -> 0 | AK31: =VLOOKUP($B31,REAL!$B$13:$AI$61,'Control Flujo de caja'!AK$16,FALSE) -> 0 | AL31: =AJ31-AK31 -> 0 | AM31: =VLOOKUP($B31,'FLUJO DE CAJA PROYECTADO '!$B$13:$AN$66,'Control Flujo de caja'!AM$16,FALSE) -> 0 | AN31: =VLOOKUP($B31,REAL!$B$13:$AN$61,'Control Flujo de caja'!AN$16,FALSE) -> 0 | AO31: =AM31-AN31 -> 0 | AP31: =VLOOKUP($B31,'FLUJO DE CAJA PROYECTADO '!$B$13:$AS$66,'Control Flujo de caja'!AP$16,FALSE) -> 444632 | AQ31: =VLOOKUP($B31,REAL!$B$13:$AS$61,'Control Flujo de caja'!AQ$16,FALSE) -> 0 | AR31: =AP31-AQ31 -> 444632
B32: 1.1.3 | C32: Salarios y prestaciones sociales | E32: =VLOOKUP(B32,'FLUJO DE CAJA PROYECTADO '!$B$13:$J$61,3,FALSE) -> 1 | F32: =VLOOKUP(B32,'FLUJO DE CAJA PROYECTADO '!$B$13:$J$61,9,FALSE) -> 349306.07 | G32: =VLOOKUP(B32,'FLUJO DE CAJA PROYECTADO '!$B$13:$J$61,8,FALSE) -> 349306.07 | H32: =D32-G32 -> -349306.07 | J32: =VLOOKUP($B32,ASEGURADO!$B$3:$J$51,3,FALSE) -> 1 | K32: =VLOOKUP(B32,ASEGURADO!$B$3:$J$52,9,FALSE) -> 349306.07 | L32: =VLOOKUP($B32,ASEGURADO!$B$3:$J$52,8,FALSE) -> 349306.07 | M32: =G32-L32 -> 0 | P32: =VLOOKUP(B32,REAL!$B$13:$J$61,3,FALSE) -> 1 | Q32: =VLOOKUP(B32,REAL!$B$13:$J$61,9,FALSE) -> 349306.07 | R32: =VLOOKUP(B32,REAL!$B$13:$J$61,8,FALSE) -> 349306.07 | S32: =G32-R32 -> 0 | U32: =VLOOKUP(B32,Contabilidad!$B$3:$D$51,3,FALSE) -> 0 | V32: =R32-U32 -> 349306.07 | X32: =VLOOKUP($B32,'FLUJO DE CAJA PROYECTADO '!$B$13:$AI$66,'Control Flujo de caja'!X$16,FALSE) -> 349306.07 | Y32: =VLOOKUP($B32,REAL!$B$13:$AI$61,'Control Flujo de caja'!Y$16,FALSE) -> 349306.07 | Z32: =X32-Y32 -> 0 | AA32: =VLOOKUP($B32,'FLUJO DE CAJA PROYECTADO '!$B$13:$AI$66,'Control Flujo de caja'!AA$16,FALSE) -> 0 | AB32: =VLOOKUP($B32,REAL!$B$13:$AI$61,'Control Flujo de caja'!AB$16,FALSE) -> 0 | AC32: =AA32-AB32 -> 0 | AD32: =VLOOKUP($B32,'FLUJO DE CAJA PROYECTADO '!$B$13:$AI$66,'Control Flujo de caja'!AD$16,FALSE) -> 0 | AE32: =VLOOKUP($B32,REAL!$B$13:$AI$61,'Control Flujo de caja'!AE$16,FALSE) -> 0 | AF32: =AD32-AE32 -> 0 | AG32: =VLOOKUP($B32,'FLUJO DE CAJA PROYECTADO '!$B$13:$AI$66,'Control Flujo de caja'!AG$16,FALSE) -> 0 | AH32: =VLOOKUP($B32,REAL!$B$13:$AI$61,'Control Flujo de caja'!AH$16,FALSE) -> 0 | AI32: =AG32-AH32 -> 0 | AJ32: =VLOOKUP($B32,'FLUJO DE CAJA PROYECTADO '!$B$13:$AI$66,'Control Flujo de caja'!AJ$16,FALSE) -> 0 | AK32: =VLOOKUP($B32,REAL!$B$13:$AI$61,'Control Flujo de caja'!AK$16,FALSE) -> 0 | AL32: =AJ32-AK32 -> 0 | AM32: =VLOOKUP($B32,'FLUJO DE CAJA PROYECTADO '!$B$13:$AN$66,'Control Flujo de caja'!AM$16,FALSE) -> 0 | AN32: =VLOOKUP($B32,REAL!$B$13:$AN$61,'Control Flujo de caja'!AN$16,FALSE) -> 0 | AO32: =AM32-AN32 -> 0 | AP32: =VLOOKUP($B32,'FLUJO DE CAJA PROYECTADO '!$B$13:$AS$66,'Control Flujo de caja'!AP$16,FALSE) -> 262737 | AQ32: =VLOOKUP($B32,REAL!$B$13:$AS$61,'Control Flujo de caja'!AQ$16,FALSE) -> 0 | AR32: =AP32-AQ32 -> 262737
B33: 1.1.4 | C33: Estabilidad de obra | E33: =VLOOKUP(B33,'FLUJO DE CAJA PROYECTADO '!$B$13:$J$61,3,FALSE) -> 1 | F33: =VLOOKUP(B33,'FLUJO DE CAJA PROYECTADO '!$B$13:$J$61,9,FALSE) -> 4184037.9 | G33: =VLOOKUP(B33,'FLUJO DE CAJA PROYECTADO '!$B$13:$J$61,8,FALSE) -> 4184037.9 | H33: =D33-G33 -> -4184037.9 | J33: =VLOOKUP($B33,ASEGURADO!$B$3:$J$51,3,FALSE) -> 1 | K33: =VLOOKUP(B33,ASEGURADO!$B$3:$J$52,9,FALSE) -> 4184037.9 | L33: =VLOOKUP($B33,ASEGURADO!$B$3:$J$52,8,FALSE) -> 4184037.9 | M33: =G33-L33 -> 0 | P33: =VLOOKUP(B33,REAL!$B$13:$J$61,3,FALSE) -> 1 | Q33: =VLOOKUP(B33,REAL!$B$13:$J$61,9,FALSE) -> 4184037.9 | R33: =VLOOKUP(B33,REAL!$B$13:$J$61,8,FALSE) -> 4184037.9 | S33: =G33-R33 -> 0 | U33: =VLOOKUP(B33,Contabilidad!$B$3:$D$51,3,FALSE) -> 0 | V33: =R33-U33 -> 4184037.9 | X33: =VLOOKUP($B33,'FLUJO DE CAJA PROYECTADO '!$B$13:$AI$66,'Control Flujo de caja'!X$16,FALSE) -> 4184037.9 | Y33: =VLOOKUP($B33,REAL!$B$13:$AI$61,'Control Flujo de caja'!Y$16,FALSE) -> 4184037.9 | Z33: =X33-Y33 -> 0 | AA33: =VLOOKUP($B33,'FLUJO DE CAJA PROYECTADO '!$B$13:$AI$66,'Control Flujo de caja'!AA$16,FALSE) -> 0 | AB33: =VLOOKUP($B33,REAL!$B$13:$AI$61,'Control Flujo de caja'!AB$16,FALSE) -> 0 | AC33: =AA33-AB33 -> 0 | AD33: =VLOOKUP($B33,'FLUJO DE CAJA PROYECTADO '!$B$13:$AI$66,'Control Flujo de caja'!AD$16,FALSE) -> 0 | AE33: =VLOOKUP($B33,REAL!$B$13:$AI$61,'Control Flujo de caja'!AE$16,FALSE) -> 0 | AF33: =AD33-AE33 -> 0 | AG33: =VLOOKUP($B33,'FLUJO DE CAJA PROYECTADO '!$B$13:$AI$66,'Control Flujo de caja'!AG$16,FALSE) -> 0 | AH33: =VLOOKUP($B33,REAL!$B$13:$AI$61,'Control Flujo de caja'!AH$16,FALSE) -> 0 | AI33: =AG33-AH33 -> 0 | AJ33: =VLOOKUP($B33,'FLUJO DE CAJA PROYECTADO '!$B$13:$AI$66,'Control Flujo de caja'!AJ$16,FALSE) -> 0 | AK33: =VLOOKUP($B33,REAL!$B$13:$AI$61,'Control Flujo de caja'!AK$16,FALSE) -> 0 | AL33: =AJ33-AK33 -> 0 | AM33: =VLOOKUP($B33,'FLUJO DE CAJA PROYECTADO '!$B$13:$AN$66,'Control Flujo de caja'!AM$16,FALSE) -> 0 | AN33: =VLOOKUP($B33,REAL!$B$13:$AN$61,'Control Flujo de caja'!AN$16,FALSE) -> 0 | AO33: =AM33-AN33 -> 0 | AP33: =VLOOKUP($B33,'FLUJO DE CAJA PROYECTADO '!$B$13:$AS$66,'Control Flujo de caja'!AP$16,FALSE) -> 3695647 | AQ33: =VLOOKUP($B33,REAL!$B$13:$AS$61,'Control Flujo de caja'!AQ$16,FALSE) -> 0 | AR33: =AP33-AQ33 -> 3695647
B34: 1.1.5 | C34: Calidad de obra | E34: =VLOOKUP(B34,'FLUJO DE CAJA PROYECTADO '!$B$13:$J$61,3,FALSE) -> 1 | F34: =VLOOKUP(B34,'FLUJO DE CAJA PROYECTADO '!$B$13:$J$61,9,FALSE) -> 9282 | G34: =VLOOKUP(B34,'FLUJO DE CAJA PROYECTADO '!$B$13:$J$61,8,FALSE) -> 9282 | H34: =D34-G34 -> -9282 | J34: =VLOOKUP($B34,ASEGURADO!$B$3:$J$51,3,FALSE) -> 1 | K34: =VLOOKUP(B34,ASEGURADO!$B$3:$J$52,9,FALSE) -> 9282 | L34: =VLOOKUP($B34,ASEGURADO!$B$3:$J$52,8,FALSE) -> 9282 | M34: =G34-L34 -> 0 | P34: =VLOOKUP(B34,REAL!$B$13:$J$61,3,FALSE) -> 1 | Q34: =VLOOKUP(B34,REAL!$B$13:$J$61,9,FALSE) -> 9282 | R34: =VLOOKUP(B34,REAL!$B$13:$J$61,8,FALSE) -> 9282 | S34: =G34-R34 -> 0 | U34: =VLOOKUP(B34,Contabilidad!$B$3:$D$51,3,FALSE) -> 0 | V34: =R34-U34 -> 9282 | X34: =VLOOKUP($B34,'FLUJO DE CAJA PROYECTADO '!$B$13:$AI$66,'Control Flujo de caja'!X$16,FALSE) -> 9282 | Y34: =VLOOKUP($B34,REAL!$B$13:$AI$61,'Control Flujo de caja'!Y$16,FALSE) -> 9282 | Z34: =X34-Y34 -> 0 | AA34: =VLOOKUP($B34,'FLUJO DE CAJA PROYECTADO '!$B$13:$AI$66,'Control Flujo de caja'!AA$16,FALSE) -> 0 | AB34: =VLOOKUP($B34,REAL!$B$13:$AI$61,'Control Flujo de caja'!AB$16,FALSE) -> 0 | AC34: =AA34-AB34 -> 0 | AD34: =VLOOKUP($B34,'FLUJO DE CAJA PROYECTADO '!$B$13:$AI$66,'Control Flujo de caja'!AD$16,FALSE) -> 0 | AE34: =VLOOKUP($B34,REAL!$B$13:$AI$61,'Control Flujo de caja'!AE$16,FALSE) -> 0 | AF34: =AD34-AE34 -> 0 | AG34: =VLOOKUP($B34,'FLUJO DE CAJA PROYECTADO '!$B$13:$AI$66,'Control Flujo de caja'!AG$16,FALSE) -> 0 | AH34: =VLOOKUP($B34,REAL!$B$13:$AI$61,'Control Flujo de caja'!AH$16,FALSE) -> 0 | AI34: =AG34-AH34 -> 0 | AJ34: =VLOOKUP($B34,'FLUJO DE CAJA PROYECTADO '!$B$13:$AI$66,'Control Flujo de caja'!AJ$16,FALSE) -> 0 | AK34: =VLOOKUP($B34,REAL!$B$13:$AI$61,'Control Flujo de caja'!AK$16,FALSE) -> 0 | AL34: =AJ34-AK34 -> 0 | AM34: =VLOOKUP($B34,'FLUJO DE CAJA PROYECTADO '!$B$13:$AN$66,'Control Flujo de caja'!AM$16,FALSE) -> 0 | AN34: =VLOOKUP($B34,REAL!$B$13:$AN$61,'Control Flujo de caja'!AN$16,FALSE) -> 0 | AO34: =AM34-AN34 -> 0 | AP34: =VLOOKUP($B34,'FLUJO DE CAJA PROYECTADO '!$B$13:$AS$66,'Control Flujo de caja'!AP$16,FALSE) -> 1212969 | AQ34: =VLOOKUP($B34,REAL!$B$13:$AS$61,'Control Flujo de caja'!AQ$16,FALSE) -> 0 | AR34: =AP34-AQ34 -> 1212969
B35: 1.1.6 | C35: Responsabilidad civil extracontractural | E35: =VLOOKUP(B35,'FLUJO DE CAJA PROYECTADO '!$B$13:$J$61,3,FALSE) -> 1 | F35: =VLOOKUP(B35,'FLUJO DE CAJA PROYECTADO '!$B$13:$J$61,9,FALSE) -> 392285.52 | G35: =VLOOKUP(B35,'FLUJO DE CAJA PROYECTADO '!$B$13:$J$61,8,FALSE) -> 392285.52 | H35: =D35-G35 -> -392285.52 | J35: =VLOOKUP($B35,ASEGURADO!$B$3:$J$51,3,FALSE) -> 1 | K35: =VLOOKUP(B35,ASEGURADO!$B$3:$J$52,9,FALSE) -> 392285.52 | L35: =VLOOKUP($B35,ASEGURADO!$B$3:$J$52,8,FALSE) -> 392285.52 | M35: =G35-L35 -> 0 | P35: =VLOOKUP(B35,REAL!$B$13:$J$61,3,FALSE) -> 1 | Q35: =VLOOKUP(B35,REAL!$B$13:$J$61,9,FALSE) -> 392285.52 | R35: =VLOOKUP(B35,REAL!$B$13:$J$61,8,FALSE) -> 392285.52 | S35: =G35-R35 -> 0 | U35: =VLOOKUP(B35,Contabilidad!$B$3:$D$51,3,FALSE) -> 0 | V35: =R35-U35 -> 392285.52 | X35: =VLOOKUP($B35,'FLUJO DE CAJA PROYECTADO '!$B$13:$AI$66,'Control Flujo de caja'!X$16,FALSE) -> 392285.52 | Y35: =VLOOKUP($B35,REAL!$B$13:$AI$61,'Control Flujo de caja'!Y$16,FALSE) -> 392285.52 | Z35: =X35-Y35 -> 0 | AA35: =VLOOKUP($B35,'FLUJO DE CAJA PROYECTADO '!$B$13:$AI$66,'Control Flujo de caja'!AA$16,FALSE) -> 0 | AB35: =VLOOKUP($B35,REAL!$B$13:$AI$61,'Control Flujo de caja'!AB$16,FALSE) -> 0 | AC35: =AA35-AB35 -> 0 | AD35: =VLOOKUP($B35,'FLUJO DE CAJA PROYECTADO '!$B$13:$AI$66,'Control Flujo de caja'!AD$16,FALSE) -> 0 | AE35: =VLOOKUP($B35,REAL!$B$13:$AI$61,'Control Flujo de caja'!AE$16,FALSE) -> 0 | AF35: =AD35-AE35 -> 0 | AG35: =VLOOKUP($B35,'FLUJO DE CAJA PROYECTADO '!$B$13:$AI$66,'Control Flujo de caja'!AG$16,FALSE) -> 0 | AH35: =VLOOKUP($B35,REAL!$B$13:$AI$61,'Control Flujo de caja'!AH$16,FALSE) -> 0 | AI35: =AG35-AH35 -> 0 | AJ35: =VLOOKUP($B35,'FLUJO DE CAJA PROYECTADO '!$B$13:$AI$66,'Control Flujo de caja'!AJ$16,FALSE) -> 0 | AK35: =VLOOKUP($B35,REAL!$B$13:$AI$61,'Control Flujo de caja'!AK$16,FALSE) -> 0 | AL35: =AJ35-AK35 -> 0 | AM35: =VLOOKUP($B35,'FLUJO DE CAJA PROYECTADO '!$B$13:$AN$66,'Control Flujo de caja'!AM$16,FALSE) -> 0 | AN35: =VLOOKUP($B35,REAL!$B$13:$AN$61,'Control Flujo de caja'!AN$16,FALSE) -> 0 | AO35: =AM35-AN35 -> 0 | AP35: =VLOOKUP($B35,'FLUJO DE CAJA PROYECTADO '!$B$13:$AS$66,'Control Flujo de caja'!AP$16,FALSE) -> 590277 | AQ35: =VLOOKUP($B35,REAL!$B$13:$AS$61,'Control Flujo de caja'!AQ$16,FALSE) -> 0 | AR35: =AP35-AQ35 -> 590277
B36: 1.2. | C36: Impuestos | D36: 48300865 | E36: =SUM(E37:E39) -> 3 | F36: =SUM(F37:F39) -> 48300863 | G36: =SUM(G37:G39) -> 0 | H36: =D36-G36 -> 48300865 | J36: =SUM(J37:J39) -> 3 | K36: =SUM(K37:K39) -> 48300863 | L36: =SUM(L37:L39) -> 0 | M36: =SUM(M37:M39) -> 0 | P36: =SUM(P37:P39) -> 3 | Q36: =SUM(Q37:Q39) -> 48300863 | R36: =SUM(R37:R39) -> 0 | S36: =G36-R36 -> 0 | U36: =VLOOKUP(B36,Contabilidad!$B$3:$D$51,3,FALSE) -> 0 | V36: =SUM(V37:V39) -> 0 | X36: =SUM(X37:X39) -> 0 | Y36: =SUM(Y37:Y39) -> 0 | Z36: =SUM(Z37:Z39) -> 0 | AA36: =SUM(AA37:AA39) -> 0 | AB36: =SUM(AB37:AB39) -> 0 | AC36: =SUM(AC37:AC39) -> 0 | AD36: =SUM(AD37:AD39) -> 0 | AE36: =SUM(AE37:AE39) -> 0 | ... AR36: =SUM(AR37:AR39) -> 48300865
B37: 1.2.1 | C37: FIC | E37: =VLOOKUP(B37,'FLUJO DE CAJA PROYECTADO '!$B$13:$J$61,3,FALSE) -> 1 | F37: =VLOOKUP(B37,'FLUJO DE CAJA PROYECTADO '!$B$13:$J$61,9,FALSE) -> 7318312 | G37: =VLOOKUP(B37,'FLUJO DE CAJA PROYECTADO '!$B$13:$J$61,8,FALSE) -> 0 | H37: =D37-G37 -> 0 | J37: =VLOOKUP($B37,ASEGURADO!$B$3:$J$51,3,FALSE) -> 1 | K37: =VLOOKUP(B37,ASEGURADO!$B$3:$J$52,9,FALSE) -> 7318312 | L37: =VLOOKUP($B37,ASEGURADO!$B$3:$J$52,8,FALSE) -> 0 | M37: =G37-L37 -> 0 | P37: =VLOOKUP(B37,REAL!$B$13:$J$61,3,FALSE) -> 1 | Q37: =VLOOKUP(B37,REAL!$B$13:$J$61,9,FALSE) -> 7318312 | R37: =VLOOKUP(B37,REAL!$B$13:$J$61,8,FALSE) -> 0 | S37: =G37-R37 -> 0 | U37: =VLOOKUP(B37,Contabilidad!$B$3:$D$51,3,FALSE) -> 0 | V37: =R37-U37 -> 0 | X37: =VLOOKUP($B37,'FLUJO DE CAJA PROYECTADO '!$B$13:$AI$66,'Control Flujo de caja'!X$16,FALSE) -> 0 | Y37: =VLOOKUP($B37,REAL!$B$13:$AI$61,'Control Flujo de caja'!Y$16,FALSE) -> 0 | Z37: =X37-Y37 -> 0 | AA37: =VLOOKUP($B37,'FLUJO DE CAJA PROYECTADO '!$B$13:$AI$66,'Control Flujo de caja'!AA$16,FALSE) -> 0 | AB37: =VLOOKUP($B37,REAL!$B$13:$AI$61,'Control Flujo de caja'!AB$16,FALSE) -> 0 | AC37: =AA37-AB37 -> 0 | AD37: =VLOOKUP($B37,'FLUJO DE CAJA PROYECTADO '!$B$13:$AI$66,'Control Flujo de caja'!AD$16,FALSE) -> 0 | AE37: =VLOOKUP($B37,REAL!$B$13:$AI$61,'Control Flujo de caja'!AE$16,FALSE) -> 0 | AF37: =AD37-AE37 -> 0 | AG37: =VLOOKUP($B37,'FLUJO DE CAJA PROYECTADO '!$B$13:$AI$66,'Control Flujo de caja'!AG$16,FALSE) -> 0 | AH37: =VLOOKUP($B37,REAL!$B$13:$AI$61,'Control Flujo de caja'!AH$16,FALSE) -> 0 | AI37: =AG37-AH37 -> 0 | AJ37: =VLOOKUP($B37,'FLUJO DE CAJA PROYECTADO '!$B$13:$AI$66,'Control Flujo de caja'!AJ$16,FALSE) -> 0 | AK37: =VLOOKUP($B37,REAL!$B$13:$AI$61,'Control Flujo de caja'!AK$16,FALSE) -> 0 | AL37: =AJ37-AK37 -> 0 | AM37: =VLOOKUP($B37,'FLUJO DE CAJA PROYECTADO '!$B$13:$AN$66,'Control Flujo de caja'!AM$16,FALSE) -> 0 | AN37: =VLOOKUP($B37,REAL!$B$13:$AN$61,'Control Flujo de caja'!AN$16,FALSE) -> 0 | AO37: =AM37-AN37 -> 0 | AP37: =VLOOKUP($B37,'FLUJO DE CAJA PROYECTADO '!$B$13:$AS$66,'Control Flujo de caja'!AP$16,FALSE) -> 7318312.9 | AQ37: =VLOOKUP($B37,REAL!$B$13:$AS$61,'Control Flujo de caja'!AQ$16,FALSE) -> 0 | AR37: =AP37-AQ37 -> 7318312.9
B38: 1.2.2 | C38: ICA | E38: =VLOOKUP(B38,'FLUJO DE CAJA PROYECTADO '!$B$13:$J$61,3,FALSE) -> 1 | F38: =VLOOKUP(B38,'FLUJO DE CAJA PROYECTADO '!$B$13:$J$61,9,FALSE) -> 29273251 | G38: =VLOOKUP(B38,'FLUJO DE CAJA PROYECTADO '!$B$13:$J$61,8,FALSE) -> 0 | H38: =D38-G38 -> 0 | J38: =VLOOKUP($B38,ASEGURADO!$B$3:$J$51,3,FALSE) -> 1 | K38: =VLOOKUP(B38,ASEGURADO!$B$3:$J$52,9,FALSE) -> 29273251 | L38: =VLOOKUP($B38,ASEGURADO!$B$3:$J$52,8,FALSE) -> 0 | M38: =G38-L38 -> 0 | P38: =VLOOKUP(B38,REAL!$B$13:$J$61,3,FALSE) -> 1 | Q38: =VLOOKUP(B38,REAL!$B$13:$J$61,9,FALSE) -> 29273251 | R38: =VLOOKUP(B38,REAL!$B$13:$J$61,8,FALSE) -> 0 | S38: =G38-R38 -> 0 | U38: =VLOOKUP(B38,Contabilidad!$B$3:$D$51,3,FALSE) -> 0 | V38: =R38-U38 -> 0 | X38: =VLOOKUP($B38,'FLUJO DE CAJA PROYECTADO '!$B$13:$AI$66,'Control Flujo de caja'!X$16,FALSE) -> 0 | Y38: =VLOOKUP($B38,REAL!$B$13:$AI$61,'Control Flujo de caja'!Y$16,FALSE) -> 0 | Z38: =X38-Y38 -> 0 | AA38: =VLOOKUP($B38,'FLUJO DE CAJA PROYECTADO '!$B$13:$AI$66,'Control Flujo de caja'!AA$16,FALSE) -> 0 | AB38: =VLOOKUP($B38,REAL!$B$13:$AI$61,'Control Flujo de caja'!AB$16,FALSE) -> 0 | AC38: =AA38-AB38 -> 0 | AD38: =VLOOKUP($B38,'FLUJO DE CAJA PROYECTADO '!$B$13:$AI$66,'Control Flujo de caja'!AD$16,FALSE) -> 0 | AE38: =VLOOKUP($B38,REAL!$B$13:$AI$61,'Control Flujo de caja'!AE$16,FALSE) -> 0 | AF38: =AD38-AE38 -> 0 | AG38: =VLOOKUP($B38,'FLUJO DE CAJA PROYECTADO '!$B$13:$AI$66,'Control Flujo de caja'!AG$16,FALSE) -> 0 | AH38: =VLOOKUP($B38,REAL!$B$13:$AI$61,'Control Flujo de caja'!AH$16,FALSE) -> 0 | AI38: =AG38-AH38 -> 0 | AJ38: =VLOOKUP($B38,'FLUJO DE CAJA PROYECTADO '!$B$13:$AI$66,'Control Flujo de caja'!AJ$16,FALSE) -> 0 | AK38: =VLOOKUP($B38,REAL!$B$13:$AI$61,'Control Flujo de caja'!AK$16,FALSE) -> 0 | AL38: =AJ38-AK38 -> 0 | AM38: =VLOOKUP($B38,'FLUJO DE CAJA PROYECTADO '!$B$13:$AN$66,'Control Flujo de caja'!AM$16,FALSE) -> 0 | AN38: =VLOOKUP($B38,REAL!$B$13:$AN$61,'Control Flujo de caja'!AN$16,FALSE) -> 0 | AO38: =AM38-AN38 -> 0 | AP38: =VLOOKUP($B38,'FLUJO DE CAJA PROYECTADO '!$B$13:$AS$66,'Control Flujo de caja'!AP$16,FALSE) -> 29273252 | AQ38: =VLOOKUP($B38,REAL!$B$13:$AS$61,'Control Flujo de caja'!AQ$16,FALSE) -> 0 | AR38: =AP38-AQ38 -> 29273252
B39: 1.2.3 | C39: Cuatro por 1000 | E39: =VLOOKUP(B39,'FLUJO DE CAJA PROYECTADO '!$B$13:$J$61,3,FALSE) -> 1 | F39: =VLOOKUP(B39,'FLUJO DE CAJA PROYECTADO '!$B$13:$J$61,9,FALSE) -> 11709300 | G39: =VLOOKUP(B39,'FLUJO DE CAJA PROYECTADO '!$B$13:$J$61,8,FALSE) -> 0 | H39: =D39-G39 -> 0 | J39: =VLOOKUP($B39,ASEGURADO!$B$3:$J$51,3,FALSE) -> 1 | K39: =VLOOKUP(B39,ASEGURADO!$B$3:$J$52,9,FALSE) -> 11709300 | L39: =VLOOKUP($B39,ASEGURADO!$B$3:$J$52,8,FALSE) -> 0 | M39: =G39-L39 -> 0 | P39: =VLOOKUP(B39,REAL!$B$13:$J$61,3,FALSE) -> 1 | Q39: =VLOOKUP(B39,REAL!$B$13:$J$61,9,FALSE) -> 11709300 | R39: =VLOOKUP(B39,REAL!$B$13:$J$61,8,FALSE) -> 0 | S39: =G39-R39 -> 0 | U39: =VLOOKUP(B39,Contabilidad!$B$3:$D$51,3,FALSE) -> 0 | V39: =R39-U39 -> 0 | X39: =VLOOKUP($B39,'FLUJO DE CAJA PROYECTADO '!$B$13:$AI$66,'Control Flujo de caja'!X$16,FALSE) -> 0 | Y39: =VLOOKUP($B39,REAL!$B$13:$AI$61,'Control Flujo de caja'!Y$16,FALSE) -> 0 | Z39: =X39-Y39 -> 0 | AA39: =VLOOKUP($B39,'FLUJO DE CAJA PROYECTADO '!$B$13:$AI$66,'Control Flujo de caja'!AA$16,FALSE) -> 0 | AB39: =VLOOKUP($B39,REAL!$B$13:$AI$61,'Control Flujo de caja'!AB$16,FALSE) -> 0 | AC39: =AA39-AB39 -> 0 | AD39: =VLOOKUP($B39,'FLUJO DE CAJA PROYECTADO '!$B$13:$AI$66,'Control Flujo de caja'!AD$16,FALSE) -> 0 | AE39: =VLOOKUP($B39,REAL!$B$13:$AI$61,'Control Flujo de caja'!AE$16,FALSE) -> 0 | AF39: =AD39-AE39 -> 0 | AG39: =VLOOKUP($B39,'FLUJO DE CAJA PROYECTADO '!$B$13:$AI$66,'Control Flujo de caja'!AG$16,FALSE) -> 0 | AH39: =VLOOKUP($B39,REAL!$B$13:$AI$61,'Control Flujo de caja'!AH$16,FALSE) -> 0 | AI39: =AG39-AH39 -> 0 | AJ39: =VLOOKUP($B39,'FLUJO DE CAJA PROYECTADO '!$B$13:$AI$66,'Control Flujo de caja'!AJ$16,FALSE) -> 0 | AK39: =VLOOKUP($B39,REAL!$B$13:$AI$61,'Control Flujo de caja'!AK$16,FALSE) -> 0 | AL39: =AJ39-AK39 -> 0 | AM39: =VLOOKUP($B39,'FLUJO DE CAJA PROYECTADO '!$B$13:$AN$66,'Control Flujo de caja'!AM$16,FALSE) -> 0 | AN39: =VLOOKUP($B39,REAL!$B$13:$AN$61,'Control Flujo de caja'!AN$16,FALSE) -> 0 | AO39: =AM39-AN39 -> 0 | AP39: =VLOOKUP($B39,'FLUJO DE CAJA PROYECTADO '!$B$13:$AS$66,'Control Flujo de caja'!AP$16,FALSE) -> 11709301 | AQ39: =VLOOKUP($B39,REAL!$B$13:$AS$61,'Control Flujo de caja'!AQ$16,FALSE) -> 0 | AR39: =AP39-AQ39 -> 11709301
B40: 1.3 | C40: Personal administración | D40: 24640000 | E40: =E41 -> 4 | F40: =F41 -> 7000000 | G40: =SUM(G41:G42) -> 34339945 | H40: =D40-G40 -> -9699945 | J40: =J41 -> 4 | K40: =K41 -> 7000000 | L40: =L41 -> 2435886 | M40: =M41 -> 14654059 | P40: =SUM(P41:P42) -> 8 | Q40: =SUM(Q41:Q42) -> 10450000 | R40: =SUM(R41:R42) -> 23736902 | S40: =G40-R40 -> 10603043 | U40: =SUM(U41:U42) -> 8202317 | V40: =V41 -> 4441021 | X40: =SUM(X41:X42) -> 2435886 | Y40: =SUM(Y41:Y42) -> 2435886 | Z40: =SUM(Z41:Z42) -> 0 | AA40: =SUM(AA41:AA42) -> 10365382 | AB40: =SUM(AB41:AB42) -> 10362570 | AC40: =SUM(AC41:AC42) -> 2812 | AD40: =SUM(AD41:AD42) -> 10365382 | AE40: =SUM(AE41:AE42) -> 7315258 | ... AR40: =SUM(AR41:AR42) -> 4273295
B41: 1.3.1 | C41: Profesional de calidad 100% | E41: =VLOOKUP(B41,'FLUJO DE CAJA PROYECTADO '!$B$13:$J$61,3,FALSE) -> 4 | F41: =VLOOKUP(B41,'FLUJO DE CAJA PROYECTADO '!$B$13:$J$61,9,FALSE) -> 7000000 | G41: =VLOOKUP(B41,'FLUJO DE CAJA PROYECTADO '!$B$13:$J$61,8,FALSE) -> 17089945 | H41: =D41-G41 -> -17089945 | J41: =VLOOKUP($B41,ASEGURADO!$B$3:$J$51,3,FALSE) -> 4 | K41: =VLOOKUP(B41,ASEGURADO!$B$3:$J$52,9,FALSE) -> 7000000 | L41: =VLOOKUP($B41,ASEGURADO!$B$3:$J$52,8,FALSE) -> 2435886 | M41: =G41-L41 -> 14654059 | P41: =VLOOKUP(B41,REAL!$B$13:$J$61,3,FALSE) -> 4 | Q41: =VLOOKUP(B41,REAL!$B$13:$J$61,9,FALSE) -> 7000000 | R41: =VLOOKUP(B41,REAL!$B$13:$J$61,8,FALSE) -> 12643338 | S41: =G41-R41 -> 4446607 | U41: =VLOOKUP(B41,Contabilidad!$B$3:$D$51,3,FALSE) -> 8202317 | V41: =R41-U41 -> 4441021 | X41: =VLOOKUP($B41,'FLUJO DE CAJA PROYECTADO '!$B$13:$AI$66,'Control Flujo de caja'!X$16,FALSE) -> 2435886 | Y41: =VLOOKUP($B41,REAL!$B$13:$AI$61,'Control Flujo de caja'!Y$16,FALSE) -> 2435886 | Z41: =X41-Y41 -> 0 | AA41: =VLOOKUP($B41,'FLUJO DE CAJA PROYECTADO '!$B$13:$AI$66,'Control Flujo de caja'!AA$16,FALSE) -> 6915382 | AB41: =VLOOKUP($B41,REAL!$B$13:$AI$61,'Control Flujo de caja'!AB$16,FALSE) -> 6515382 | AC41: =AA41-AB41 -> 400000 | AD41: =VLOOKUP($B41,'FLUJO DE CAJA PROYECTADO '!$B$13:$AI$66,'Control Flujo de caja'!AD$16,FALSE) -> 6915382 | AE41: =VLOOKUP($B41,REAL!$B$13:$AI$61,'Control Flujo de caja'!AE$16,FALSE) -> 3692070 | AF41: =AD41-AE41 -> 3223312 | AG41: =VLOOKUP($B41,'FLUJO DE CAJA PROYECTADO '!$B$13:$AI$66,'Control Flujo de caja'!AG$16,FALSE) -> 0 | AH41: =VLOOKUP($B41,REAL!$B$13:$AI$61,'Control Flujo de caja'!AH$16,FALSE) -> 0 | AI41: =AG41-AH41 -> 0 | AJ41: =VLOOKUP($B41,'FLUJO DE CAJA PROYECTADO '!$B$13:$AI$66,'Control Flujo de caja'!AJ$16,FALSE) -> 0 | AK41: =VLOOKUP($B41,REAL!$B$13:$AI$61,'Control Flujo de caja'!AK$16,FALSE) -> 0 | AL41: =AJ41-AK41 -> 0 | AM41: =VLOOKUP($B41,'FLUJO DE CAJA PROYECTADO '!$B$13:$AN$66,'Control Flujo de caja'!AM$16,FALSE) -> 823295 | AN41: =VLOOKUP($B41,REAL!$B$13:$AN$61,'Control Flujo de caja'!AN$16,FALSE) -> 0 | AO41: =AM41-AN41 -> 823295 | AP41: =VLOOKUP($B41,'FLUJO DE CAJA PROYECTADO '!$B$13:$AS$66,'Control Flujo de caja'!AP$16,FALSE) -> 823295 | AQ41: =VLOOKUP($B41,REAL!$B$13:$AS$61,'Control Flujo de caja'!AQ$16,FALSE) -> 0 | AR41: =AP41-AQ41 -> 823295
B42: 1.3.2 | C42: Residente administrativo | E42: 0 | F42: =VLOOKUP(B42,'FLUJO DE CAJA PROYECTADO '!$B$13:$J$61,9,FALSE) -> 3450000 | G42: =VLOOKUP(B42,'FLUJO DE CAJA PROYECTADO '!$B$13:$J$61,8,FALSE) -> 17250000 | H42: =D42-G42 -> -17250000 | J42: =VLOOKUP($B42,ASEGURADO!$B$3:$J$51,3,FALSE) -> 0 | K42: =VLOOKUP(B42,ASEGURADO!$B$3:$J$52,9,FALSE) -> 4000000 | L42: =VLOOKUP($B42,ASEGURADO!$B$3:$J$52,8,FALSE) -> 20000000 | M42: =G42-L42 -> -2750000 | P42: =VLOOKUP(B42,REAL!$B$13:$J$61,3,FALSE) -> 4 | Q42: =VLOOKUP(B42,REAL!$B$13:$J$61,9,FALSE) -> 3450000 | R42: =VLOOKUP(B42,REAL!$B$13:$J$61,8,FALSE) -> 11093564 | S42: =G42-R42 -> 6156436 | X42: =IFERROR(VLOOKUP($B42,'FLUJO DE CAJA PROYECTADO '!$B$13:$AI$597,'Control Flujo de caja'!X$16,FALSE),0) -> 0 | Y42: =VLOOKUP($B42,REAL!$B$13:$AI$61,'Control Flujo de caja'!Y$16,FALSE) -> 0 | Z42: =X42-Y42 -> 0 | AA42: =IFERROR(VLOOKUP($B42,'FLUJO DE CAJA PROYECTADO '!$B$13:$AI$597,'Control Flujo de caja'!AA$16,FALSE),0) -> 3450000 | AB42: =VLOOKUP($B42,REAL!$B$13:$AI$61,'Control Flujo de caja'!AB$16,FALSE) -> 3847188 | AC42: =AA42-AB42 -> -397188 | AD42: =IFERROR(VLOOKUP($B42,'FLUJO DE CAJA PROYECTADO '!$B$13:$AI$597,'Control Flujo de caja'!AD$16,FALSE),0) -> 3450000 | AE42: =VLOOKUP($B42,REAL!$B$13:$AI$61,'Control Flujo de caja'!AE$16,FALSE) -> 3623188 | AF42: =AD42-AE42 -> -173188 | AG42: =IFERROR(VLOOKUP($B42,'FLUJO DE CAJA PROYECTADO '!$B$13:$AI$597,'Control Flujo de caja'!AG$16,FALSE),0) -> 3450000 | AH42: =VLOOKUP($B42,REAL!$B$13:$AI$61,'Control Flujo de caja'!AH$16,FALSE) -> 3623188 | AI42: =AG42-AH42 -> -173188 | AJ42: =IFERROR(VLOOKUP($B42,'FLUJO DE CAJA PROYECTADO '!$B$13:$AI$597,'Control Flujo de caja'!AJ$16,FALSE),0) -> 3450000 | AK42: =VLOOKUP($B42,REAL!$B$13:$AI$61,'Control Flujo de caja'!AK$16,FALSE) -> 0 | AL42: =AJ42-AK42 -> 3450000 | AM42: =VLOOKUP($B42,'FLUJO DE CAJA PROYECTADO '!$B$13:$AN$66,'Control Flujo de caja'!AM$16,FALSE) -> 3450000 | AN42: =VLOOKUP($B42,REAL!$B$13:$AN$61,'Control Flujo de caja'!AN$16,FALSE) -> 0 | AO42: =AM42-AN42 -> 3450000 | AP42: =VLOOKUP($B42,'FLUJO DE CAJA PROYECTADO '!$B$13:$AS$66,'Control Flujo de caja'!AP$16,FALSE) -> 3450000 | AQ42: =VLOOKUP($B42,REAL!$B$13:$AS$61,'Control Flujo de caja'!AQ$16,FALSE) -> 0 | AR42: =AP42-AQ42 -> 3450000
B43: 1.4 | C43: Campamentos, protecciones e insumos de obra | D43: 750834 | E43: =SUM(E44:E52) -> 17 | F43: =SUM(F44:F52) -> 661557 | G43: =SUM(G44:G52) -> 661557 | H43: =D43-G43 -> 89277 | J43: =SUM(J44:J52) -> 17 | K43: =SUM(K44:K52) -> 661557 | L43: =SUM(L44:L52) -> 0 | M43: =SUM(M44:M52) -> 661557 | P43: =SUM(P44:P52) -> 17 | Q43: =SUM(Q44:Q52) -> 661557 | R43: =SUM(R44:R52) -> 0 | S43: =G43-R43 -> 661557 | U43: =VLOOKUP(B43,Contabilidad!$B$3:$D$51,3,FALSE) -> 0 | V43: =SUM(V44:V52) -> 0 | X43: =SUM(X44:X52) -> 661557 | Y43: =SUM(Y44:Y52) -> 0 | Z43: =SUM(Z44:Z52) -> 661557 | AA43: =SUM(AA44:AA52) -> 0 | AB43: =SUM(AB44:AB52) -> 0 | AC43: =SUM(AC44:AC52) -> 0 | AD43: =SUM(AD44:AD52) -> 0 | AE43: =SUM(AE44:AE52) -> 0 | ... AR43: =SUM(AR44:AR52) -> 0
B44: 1.4.1 | C44: Kit señalización para campamentos (hasta 120 m2) | E44: =VLOOKUP(B44,'FLUJO DE CAJA PROYECTADO '!$B$13:$J$61,3,FALSE) -> 3 | F44: =VLOOKUP(B44,'FLUJO DE CAJA PROYECTADO '!$B$13:$J$61,9,FALSE) -> 150000 | G44: =VLOOKUP(B44,'FLUJO DE CAJA PROYECTADO '!$B$13:$J$61,8,FALSE) -> 150000 | H44: =D44-G44 -> -150000 | J44: =VLOOKUP($B44,ASEGURADO!$B$3:$J$51,3,FALSE) -> 3 | K44: =VLOOKUP(B44,ASEGURADO!$B$3:$J$52,9,FALSE) -> 150000 | L44: =VLOOKUP($B44,ASEGURADO!$B$3:$J$52,8,FALSE) -> 0 | M44: =G44-L44 -> 150000 | P44: =VLOOKUP(B44,REAL!$B$13:$J$61,3,FALSE) -> 3 | Q44: =VLOOKUP(B44,REAL!$B$13:$J$61,9,FALSE) -> 150000 | R44: =VLOOKUP(B44,REAL!$B$13:$J$61,8,FALSE) -> 0 | S44: =G44-R44 -> 150000 | U44: =VLOOKUP(B44,Contabilidad!$B$3:$D$51,3,FALSE) -> 0 | V44: =R44-U44 -> 0 | X44: =VLOOKUP($B44,'FLUJO DE CAJA PROYECTADO '!$B$13:$AI$66,'Control Flujo de caja'!X$16,FALSE) -> 150000 | Y44: =VLOOKUP($B44,REAL!$B$13:$AI$61,'Control Flujo de caja'!Y$16,FALSE) -> 0 | Z44: =X44-Y44 -> 150000 | AA44: =VLOOKUP($B44,'FLUJO DE CAJA PROYECTADO '!$B$13:$AI$66,'Control Flujo de caja'!AA$16,FALSE) -> 0 | AB44: =VLOOKUP($B44,REAL!$B$13:$AI$61,'Control Flujo de caja'!AB$16,FALSE) -> 0 | AC44: =AA44-AB44 -> 0 | AD44: =VLOOKUP($B44,'FLUJO DE CAJA PROYECTADO '!$B$13:$AI$66,'Control Flujo de caja'!AD$16,FALSE) -> 0 | AE44: =VLOOKUP($B44,REAL!$B$13:$AI$61,'Control Flujo de caja'!AE$16,FALSE) -> 0 | AF44: =AD44-AE44 -> 0 | AG44: =VLOOKUP($B44,'FLUJO DE CAJA PROYECTADO '!$B$13:$AI$66,'Control Flujo de caja'!AG$16,FALSE) -> 0 | AH44: =VLOOKUP($B44,REAL!$B$13:$AI$61,'Control Flujo de caja'!AH$16,FALSE) -> 0 | AI44: =AG44-AH44 -> 0 | AJ44: =VLOOKUP($B44,'FLUJO DE CAJA PROYECTADO '!$B$13:$AI$66,'Control Flujo de caja'!AJ$16,FALSE) -> 0 | AK44: =VLOOKUP($B44,REAL!$B$13:$AI$61,'Control Flujo de caja'!AK$16,FALSE) -> 0 | AL44: =AJ44-AK44 -> 0 | AM44: =VLOOKUP($B44,'FLUJO DE CAJA PROYECTADO '!$B$13:$AN$66,'Control Flujo de caja'!AM$16,FALSE) -> 0 | AN44: =VLOOKUP($B44,REAL!$B$13:$AN$61,'Control Flujo de caja'!AN$16,FALSE) -> 0 | AO44: =AM44-AN44 -> 0 | AP44: =VLOOKUP($B44,'FLUJO DE CAJA PROYECTADO '!$B$13:$AS$66,'Control Flujo de caja'!AP$16,FALSE) -> 0 | AQ44: =VLOOKUP($B44,REAL!$B$13:$AS$61,'Control Flujo de caja'!AQ$16,FALSE) -> 0 | AR44: =AP44-AQ44 -> 0
B45: 1.4.2 | C45: Cascos de seguridad | E45: =VLOOKUP(B45,'FLUJO DE CAJA PROYECTADO '!$B$13:$J$61,3,FALSE) -> 1 | F45: =VLOOKUP(B45,'FLUJO DE CAJA PROYECTADO '!$B$13:$J$61,9,FALSE) -> 17850 | G45: =VLOOKUP(B45,'FLUJO DE CAJA PROYECTADO '!$B$13:$J$61,8,FALSE) -> 17850 | H45: =D45-G45 -> -17850 | J45: =VLOOKUP($B45,ASEGURADO!$B$3:$J$51,3,FALSE) -> 1 | K45: =VLOOKUP(B45,ASEGURADO!$B$3:$J$52,9,FALSE) -> 17850 | L45: =VLOOKUP($B45,ASEGURADO!$B$3:$J$52,8,FALSE) -> 0 | M45: =G45-L45 -> 17850 | P45: =VLOOKUP(B45,REAL!$B$13:$J$61,3,FALSE) -> 1 | Q45: =VLOOKUP(B45,REAL!$B$13:$J$61,9,FALSE) -> 17850 | R45: =VLOOKUP(B45,REAL!$B$13:$J$61,8,FALSE) -> 0 | S45: =G45-R45 -> 17850 | U45: =VLOOKUP(B45,Contabilidad!$B$3:$D$51,3,FALSE) -> 0 | V45: =R45-U45 -> 0 | X45: =VLOOKUP($B45,'FLUJO DE CAJA PROYECTADO '!$B$13:$AI$66,'Control Flujo de caja'!X$16,FALSE) -> 17850 | Y45: =VLOOKUP($B45,REAL!$B$13:$AI$61,'Control Flujo de caja'!Y$16,FALSE) -> 0 | Z45: =X45-Y45 -> 17850 | AA45: =VLOOKUP($B45,'FLUJO DE CAJA PROYECTADO '!$B$13:$AI$66,'Control Flujo de caja'!AA$16,FALSE) -> 0 | AB45: =VLOOKUP($B45,REAL!$B$13:$AI$61,'Control Flujo de caja'!AB$16,FALSE) -> 0 | AC45: =AA45-AB45 -> 0 | AD45: =VLOOKUP($B45,'FLUJO DE CAJA PROYECTADO '!$B$13:$AI$66,'Control Flujo de caja'!AD$16,FALSE) -> 0 | AE45: =VLOOKUP($B45,REAL!$B$13:$AI$61,'Control Flujo de caja'!AE$16,FALSE) -> 0 | AF45: =AD45-AE45 -> 0 | AG45: =VLOOKUP($B45,'FLUJO DE CAJA PROYECTADO '!$B$13:$AI$66,'Control Flujo de caja'!AG$16,FALSE) -> 0 | AH45: =VLOOKUP($B45,REAL!$B$13:$AI$61,'Control Flujo de caja'!AH$16,FALSE) -> 0 | AI45: =AG45-AH45 -> 0 | AJ45: =VLOOKUP($B45,'FLUJO DE CAJA PROYECTADO '!$B$13:$AI$66,'Control Flujo de caja'!AJ$16,FALSE) -> 0 | AK45: =VLOOKUP($B45,REAL!$B$13:$AI$61,'Control Flujo de caja'!AK$16,FALSE) -> 0 | AL45: =AJ45-AK45 -> 0 | AM45: =VLOOKUP($B45,'FLUJO DE CAJA PROYECTADO '!$B$13:$AN$66,'Control Flujo de caja'!AM$16,FALSE) -> 0 | AN45: =VLOOKUP($B45,REAL!$B$13:$AN$61,'Control Flujo de caja'!AN$16,FALSE) -> 0 | AO45: =AM45-AN45 -> 0 | AP45: =VLOOKUP($B45,'FLUJO DE CAJA PROYECTADO '!$B$13:$AS$66,'Control Flujo de caja'!AP$16,FALSE) -> 0 | AQ45: =VLOOKUP($B45,REAL!$B$13:$AS$61,'Control Flujo de caja'!AQ$16,FALSE) -> 0 | AR45: =AP45-AQ45 -> 0
B46: 1.4.3 | C46: Protección auditiva | E46: =VLOOKUP(B46,'FLUJO DE CAJA PROYECTADO '!$B$13:$J$61,3,FALSE) -> 3 | F46: =VLOOKUP(B46,'FLUJO DE CAJA PROYECTADO '!$B$13:$J$61,9,FALSE) -> 4341 | G46: =VLOOKUP(B46,'FLUJO DE CAJA PROYECTADO '!$B$13:$J$61,8,FALSE) -> 4341 | H46: =D46-G46 -> -4341 | J46: =VLOOKUP($B46,ASEGURADO!$B$3:$J$51,3,FALSE) -> 3 | K46: =VLOOKUP(B46,ASEGURADO!$B$3:$J$52,9,FALSE) -> 4341 | L46: =VLOOKUP($B46,ASEGURADO!$B$3:$J$52,8,FALSE) -> 0 | M46: =G46-L46 -> 4341 | P46: =VLOOKUP(B46,REAL!$B$13:$J$61,3,FALSE) -> 3 | Q46: =VLOOKUP(B46,REAL!$B$13:$J$61,9,FALSE) -> 4341 | R46: =VLOOKUP(B46,REAL!$B$13:$J$61,8,FALSE) -> 0 | S46: =G46-R46 -> 4341 | U46: =VLOOKUP(B46,Contabilidad!$B$3:$D$51,3,FALSE) -> 0 | V46: =R46-U46 -> 0 | X46: =VLOOKUP($B46,'FLUJO DE CAJA PROYECTADO '!$B$13:$AI$66,'Control Flujo de caja'!X$16,FALSE) -> 4341 | Y46: =VLOOKUP($B46,REAL!$B$13:$AI$61,'Control Flujo de caja'!Y$16,FALSE) -> 0 | Z46: =X46-Y46 -> 4341 | AA46: =VLOOKUP($B46,'FLUJO DE CAJA PROYECTADO '!$B$13:$AI$66,'Control Flujo de caja'!AA$16,FALSE) -> 0 | AB46: =VLOOKUP($B46,REAL!$B$13:$AI$61,'Control Flujo de caja'!AB$16,FALSE) -> 0 | AC46: =AA46-AB46 -> 0 | AD46: =VLOOKUP($B46,'FLUJO DE CAJA PROYECTADO '!$B$13:$AI$66,'Control Flujo de caja'!AD$16,FALSE) -> 0 | AE46: =VLOOKUP($B46,REAL!$B$13:$AI$61,'Control Flujo de caja'!AE$16,FALSE) -> 0 | AF46: =AD46-AE46 -> 0 | AG46: =VLOOKUP($B46,'FLUJO DE CAJA PROYECTADO '!$B$13:$AI$66,'Control Flujo de caja'!AG$16,FALSE) -> 0 | AH46: =VLOOKUP($B46,REAL!$B$13:$AI$61,'Control Flujo de caja'!AH$16,FALSE) -> 0 | AI46: =AG46-AH46 -> 0 | AJ46: =VLOOKUP($B46,'FLUJO DE CAJA PROYECTADO '!$B$13:$AI$66,'Control Flujo de caja'!AJ$16,FALSE) -> 0 | AK46: =VLOOKUP($B46,REAL!$B$13:$AI$61,'Control Flujo de caja'!AK$16,FALSE) -> 0 | AL46: =AJ46-AK46 -> 0 | AM46: =VLOOKUP($B46,'FLUJO DE CAJA PROYECTADO '!$B$13:$AN$66,'Control Flujo de caja'!AM$16,FALSE) -> 0 | AN46: =VLOOKUP($B46,REAL!$B$13:$AN$61,'Control Flujo de caja'!AN$16,FALSE) -> 0 | AO46: =AM46-AN46 -> 0 | AP46: =VLOOKUP($B46,'FLUJO DE CAJA PROYECTADO '!$B$13:$AS$66,'Control Flujo de caja'!AP$16,FALSE) -> 0 | AQ46: =VLOOKUP($B46,REAL!$B$13:$AS$61,'Control Flujo de caja'!AQ$16,FALSE) -> 0 | AR46: =AP46-AQ46 -> 0
B47: 1.4.4 | C47: Guantes de nitrilo | E47: =VLOOKUP(B47,'FLUJO DE CAJA PROYECTADO '!$B$13:$J$61,3,FALSE) -> 3 | F47: =VLOOKUP(B47,'FLUJO DE CAJA PROYECTADO '!$B$13:$J$61,9,FALSE) -> 23324 | G47: =VLOOKUP(B47,'FLUJO DE CAJA PROYECTADO '!$B$13:$J$61,8,FALSE) -> 23324 | H47: =D47-G47 -> -23324 | J47: =VLOOKUP($B47,ASEGURADO!$B$3:$J$51,3,FALSE) -> 3 | K47: =VLOOKUP(B47,ASEGURADO!$B$3:$J$52,9,FALSE) -> 23324 | L47: =VLOOKUP($B47,ASEGURADO!$B$3:$J$52,8,FALSE) -> 0 | M47: =G47-L47 -> 23324 | P47: =VLOOKUP(B47,REAL!$B$13:$J$61,3,FALSE) -> 3 | Q47: =VLOOKUP(B47,REAL!$B$13:$J$61,9,FALSE) -> 23324 | R47: =VLOOKUP(B47,REAL!$B$13:$J$61,8,FALSE) -> 0 | S47: =G47-R47 -> 23324 | U47: =VLOOKUP(B47,Contabilidad!$B$3:$D$51,3,FALSE) -> 0 | V47: =R47-U47 -> 0 | X47: =VLOOKUP($B47,'FLUJO DE CAJA PROYECTADO '!$B$13:$AI$66,'Control Flujo de caja'!X$16,FALSE) -> 23324 | Y47: =VLOOKUP($B47,REAL!$B$13:$AI$61,'Control Flujo de caja'!Y$16,FALSE) -> 0 | Z47: =X47-Y47 -> 23324 | AA47: =VLOOKUP($B47,'FLUJO DE CAJA PROYECTADO '!$B$13:$AI$66,'Control Flujo de caja'!AA$16,FALSE) -> 0 | AB47: =VLOOKUP($B47,REAL!$B$13:$AI$61,'Control Flujo de caja'!AB$16,FALSE) -> 0 | AC47: =AA47-AB47 -> 0 | AD47: =VLOOKUP($B47,'FLUJO DE CAJA PROYECTADO '!$B$13:$AI$66,'Control Flujo de caja'!AD$16,FALSE) -> 0 | AE47: =VLOOKUP($B47,REAL!$B$13:$AI$61,'Control Flujo de caja'!AE$16,FALSE) -> 0 | AF47: =AD47-AE47 -> 0 | AG47: =VLOOKUP($B47,'FLUJO DE CAJA PROYECTADO '!$B$13:$AI$66,'Control Flujo de caja'!AG$16,FALSE) -> 0 | AH47: =VLOOKUP($B47,REAL!$B$13:$AI$61,'Control Flujo de caja'!AH$16,FALSE) -> 0 | AI47: =AG47-AH47 -> 0 | AJ47: =VLOOKUP($B47,'FLUJO DE CAJA PROYECTADO '!$B$13:$AI$66,'Control Flujo de caja'!AJ$16,FALSE) -> 0 | AK47: =VLOOKUP($B47,REAL!$B$13:$AI$61,'Control Flujo de caja'!AK$16,FALSE) -> 0 | AL47: =AJ47-AK47 -> 0 | AM47: =VLOOKUP($B47,'FLUJO DE CAJA PROYECTADO '!$B$13:$AN$66,'Control Flujo de caja'!AM$16,FALSE) -> 0 | AN47: =VLOOKUP($B47,REAL!$B$13:$AN$61,'Control Flujo de caja'!AN$16,FALSE) -> 0 | AO47: =AM47-AN47 -> 0 | AP47: =VLOOKUP($B47,'FLUJO DE CAJA PROYECTADO '!$B$13:$AS$66,'Control Flujo de caja'!AP$16,FALSE) -> 0 | AQ47: =VLOOKUP($B47,REAL!$B$13:$AS$61,'Control Flujo de caja'!AQ$16,FALSE) -> 0 | AR47: =AP47-AQ47 -> 0
B48: 1.4.5 | C48: Par de botas de agua | E48: =VLOOKUP(B48,'FLUJO DE CAJA PROYECTADO '!$B$13:$J$61,3,FALSE) -> 1 | F48: =VLOOKUP(B48,'FLUJO DE CAJA PROYECTADO '!$B$13:$J$61,9,FALSE) -> 66640 | G48: =VLOOKUP(B48,'FLUJO DE CAJA PROYECTADO '!$B$13:$J$61,8,FALSE) -> 66640 | H48: =D48-G48 -> -66640 | J48: =VLOOKUP($B48,ASEGURADO!$B$3:$J$51,3,FALSE) -> 1 | K48: =VLOOKUP(B48,ASEGURADO!$B$3:$J$52,9,FALSE) -> 66640 | L48: =VLOOKUP($B48,ASEGURADO!$B$3:$J$52,8,FALSE) -> 0 | M48: =G48-L48 -> 66640 | P48: =VLOOKUP(B48,REAL!$B$13:$J$61,3,FALSE) -> 1 | Q48: =VLOOKUP(B48,REAL!$B$13:$J$61,9,FALSE) -> 66640 | R48: =VLOOKUP(B48,REAL!$B$13:$J$61,8,FALSE) -> 0 | S48: =G48-R48 -> 66640 | U48: =VLOOKUP(B48,Contabilidad!$B$3:$D$51,3,FALSE) -> 0 | V48: =R48-U48 -> 0 | X48: =VLOOKUP($B48,'FLUJO DE CAJA PROYECTADO '!$B$13:$AI$66,'Control Flujo de caja'!X$16,FALSE) -> 66640 | Y48: =VLOOKUP($B48,REAL!$B$13:$AI$61,'Control Flujo de caja'!Y$16,FALSE) -> 0 | Z48: =X48-Y48 -> 66640 | AA48: =VLOOKUP($B48,'FLUJO DE CAJA PROYECTADO '!$B$13:$AI$66,'Control Flujo de caja'!AA$16,FALSE) -> 0 | AB48: =VLOOKUP($B48,REAL!$B$13:$AI$61,'Control Flujo de caja'!AB$16,FALSE) -> 0 | AC48: =AA48-AB48 -> 0 | AD48: =VLOOKUP($B48,'FLUJO DE CAJA PROYECTADO '!$B$13:$AI$66,'Control Flujo de caja'!AD$16,FALSE) -> 0 | AE48: =VLOOKUP($B48,REAL!$B$13:$AI$61,'Control Flujo de caja'!AE$16,FALSE) -> 0 | AF48: =AD48-AE48 -> 0 | AG48: =VLOOKUP($B48,'FLUJO DE CAJA PROYECTADO '!$B$13:$AI$66,'Control Flujo de caja'!AG$16,FALSE) -> 0 | AH48: =VLOOKUP($B48,REAL!$B$13:$AI$61,'Control Flujo de caja'!AH$16,FALSE) -> 0 | AI48: =AG48-AH48 -> 0 | AJ48: =VLOOKUP($B48,'FLUJO DE CAJA PROYECTADO '!$B$13:$AI$66,'Control Flujo de caja'!AJ$16,FALSE) -> 0 | AK48: =VLOOKUP($B48,REAL!$B$13:$AI$61,'Control Flujo de caja'!AK$16,FALSE) -> 0 | AL48: =AJ48-AK48 -> 0 | AM48: =VLOOKUP($B48,'FLUJO DE CAJA PROYECTADO '!$B$13:$AN$66,'Control Flujo de caja'!AM$16,FALSE) -> 0 | AN48: =VLOOKUP($B48,REAL!$B$13:$AN$61,'Control Flujo de caja'!AN$16,FALSE) -> 0 | AO48: =AM48-AN48 -> 0 | AP48: =VLOOKUP($B48,'FLUJO DE CAJA PROYECTADO '!$B$13:$AS$66,'Control Flujo de caja'!AP$16,FALSE) -> 0 | AQ48: =VLOOKUP($B48,REAL!$B$13:$AS$61,'Control Flujo de caja'!AQ$16,FALSE) -> 0 | AR48: =AP48-AQ48 -> 0
B49: 1.4.6 | C49: Par de botas de seguridad | E49: =VLOOKUP(B49,'FLUJO DE CAJA PROYECTADO '!$B$13:$J$61,3,FALSE) -> 1 | F49: =VLOOKUP(B49,'FLUJO DE CAJA PROYECTADO '!$B$13:$J$61,9,FALSE) -> 116739 | G49: =VLOOKUP(B49,'FLUJO DE CAJA PROYECTADO '!$B$13:$J$61,8,FALSE) -> 116739 | H49: =D49-G49 -> -116739 | J49: =VLOOKUP($B49,ASEGURADO!$B$3:$J$51,3,FALSE) -> 1 | K49: =VLOOKUP(B49,ASEGURADO!$B$3:$J$52,9,FALSE) -> 116739 | L49: =VLOOKUP($B49,ASEGURADO!$B$3:$J$52,8,FALSE) -> 0 | M49: =G49-L49 -> 116739 | P49: =VLOOKUP(B49,REAL!$B$13:$J$61,3,FALSE) -> 1 | Q49: =VLOOKUP(B49,REAL!$B$13:$J$61,9,FALSE) -> 116739 | R49: =VLOOKUP(B49,REAL!$B$13:$J$61,8,FALSE) -> 0 | S49: =G49-R49 -> 116739 | U49: =VLOOKUP(B49,Contabilidad!$B$3:$D$51,3,FALSE) -> 0 | V49: =R49-U49 -> 0 | X49: =VLOOKUP($B49,'FLUJO DE CAJA PROYECTADO '!$B$13:$AI$66,'Control Flujo de caja'!X$16,FALSE) -> 116739 | Y49: =VLOOKUP($B49,REAL!$B$13:$AI$61,'Control Flujo de caja'!Y$16,FALSE) -> 0 | Z49: =X49-Y49 -> 116739 | AA49: =VLOOKUP($B49,'FLUJO DE CAJA PROYECTADO '!$B$13:$AI$66,'Control Flujo de caja'!AA$16,FALSE) -> 0 | AB49: =VLOOKUP($B49,REAL!$B$13:$AI$61,'Control Flujo de caja'!AB$16,FALSE) -> 0 | AC49: =AA49-AB49 -> 0 | AD49: =VLOOKUP($B49,'FLUJO DE CAJA PROYECTADO '!$B$13:$AI$66,'Control Flujo de caja'!AD$16,FALSE) -> 0 | AE49: =VLOOKUP($B49,REAL!$B$13:$AI$61,'Control Flujo de caja'!AE$16,FALSE) -> 0 | AF49: =AD49-AE49 -> 0 | AG49: =VLOOKUP($B49,'FLUJO DE CAJA PROYECTADO '!$B$13:$AI$66,'Control Flujo de caja'!AG$16,FALSE) -> 0 | AH49: =VLOOKUP($B49,REAL!$B$13:$AI$61,'Control Flujo de caja'!AH$16,FALSE) -> 0 | AI49: =AG49-AH49 -> 0 | AJ49: =VLOOKUP($B49,'FLUJO DE CAJA PROYECTADO '!$B$13:$AI$66,'Control Flujo de caja'!AJ$16,FALSE) -> 0 | AK49: =VLOOKUP($B49,REAL!$B$13:$AI$61,'Control Flujo de caja'!AK$16,FALSE) -> 0 | AL49: =AJ49-AK49 -> 0 | AM49: =VLOOKUP($B49,'FLUJO DE CAJA PROYECTADO '!$B$13:$AN$66,'Control Flujo de caja'!AM$16,FALSE) -> 0 | AN49: =VLOOKUP($B49,REAL!$B$13:$AN$61,'Control Flujo de caja'!AN$16,FALSE) -> 0 | AO49: =AM49-AN49 -> 0 | AP49: =VLOOKUP($B49,'FLUJO DE CAJA PROYECTADO '!$B$13:$AS$66,'Control Flujo de caja'!AP$16,FALSE) -> 0 | AQ49: =VLOOKUP($B49,REAL!$B$13:$AS$61,'Control Flujo de caja'!AQ$16,FALSE) -> 0 | AR49: =AP49-AQ49 -> 0
B50: 1.4.7 | C50: Gafas de seguridad | E50: =VLOOKUP(B50,'FLUJO DE CAJA PROYECTADO '!$B$13:$J$61,3,FALSE) -> 3 | F50: =VLOOKUP(B50,'FLUJO DE CAJA PROYECTADO '!$B$13:$J$61,9,FALSE) -> 14756 | G50: =VLOOKUP(B50,'FLUJO DE CAJA PROYECTADO '!$B$13:$J$61,8,FALSE) -> 14756 | H50: =D50-G50 -> -14756 | J50: =VLOOKUP($B50,ASEGURADO!$B$3:$J$51,3,FALSE) -> 3 | K50: =VLOOKUP(B50,ASEGURADO!$B$3:$J$52,9,FALSE) -> 14756 | L50: =VLOOKUP($B50,ASEGURADO!$B$3:$J$52,8,FALSE) -> 0 | M50: =G50-L50 -> 14756 | P50: =VLOOKUP(B50,REAL!$B$13:$J$61,3,FALSE) -> 3 | Q50: =VLOOKUP(B50,REAL!$B$13:$J$61,9,FALSE) -> 14756 | R50: =VLOOKUP(B50,REAL!$B$13:$J$61,8,FALSE) -> 0 | S50: =G50-R50 -> 14756 | U50: =VLOOKUP(B50,Contabilidad!$B$3:$D$51,3,FALSE) -> 0 | V50: =R50-U50 -> 0 | X50: =VLOOKUP($B50,'FLUJO DE CAJA PROYECTADO '!$B$13:$AI$66,'Control Flujo de caja'!X$16,FALSE) -> 14756 | Y50: =VLOOKUP($B50,REAL!$B$13:$AI$61,'Control Flujo de caja'!Y$16,FALSE) -> 0 | Z50: =X50-Y50 -> 14756 | AA50: =VLOOKUP($B50,'FLUJO DE CAJA PROYECTADO '!$B$13:$AI$66,'Control Flujo de caja'!AA$16,FALSE) -> 0 | AB50: =VLOOKUP($B50,REAL!$B$13:$AI$61,'Control Flujo de caja'!AB$16,FALSE) -> 0 | AC50: =AA50-AB50 -> 0 | AD50: =VLOOKUP($B50,'FLUJO DE CAJA PROYECTADO '!$B$13:$AI$66,'Control Flujo de caja'!AD$16,FALSE) -> 0 | AE50: =VLOOKUP($B50,REAL!$B$13:$AI$61,'Control Flujo de caja'!AE$16,FALSE) -> 0 | AF50: =AD50-AE50 -> 0 | AG50: =VLOOKUP($B50,'FLUJO DE CAJA PROYECTADO '!$B$13:$AI$66,'Control Flujo de caja'!AG$16,FALSE) -> 0 | AH50: =VLOOKUP($B50,REAL!$B$13:$AI$61,'Control Flujo de caja'!AH$16,FALSE) -> 0 | AI50: =AG50-AH50 -> 0 | AJ50: =VLOOKUP($B50,'FLUJO DE CAJA PROYECTADO '!$B$13:$AI$66,'Control Flujo de caja'!AJ$16,FALSE) -> 0 | AK50: =VLOOKUP($B50,REAL!$B$13:$AI$61,'Control Flujo de caja'!AK$16,FALSE) -> 0 | AL50: =AJ50-AK50 -> 0 | AM50: =VLOOKUP($B50,'FLUJO DE CAJA PROYECTADO '!$B$13:$AN$66,'Control Flujo de caja'!AM$16,FALSE) -> 0 | AN50: =VLOOKUP($B50,REAL!$B$13:$AN$61,'Control Flujo de caja'!AN$16,FALSE) -> 0 | AO50: =AM50-AN50 -> 0 | AP50: =VLOOKUP($B50,'FLUJO DE CAJA PROYECTADO '!$B$13:$AS$66,'Control Flujo de caja'!AP$16,FALSE) -> 0 | AQ50: =VLOOKUP($B50,REAL!$B$13:$AS$61,'Control Flujo de caja'!AQ$16,FALSE) -> 0 | AR50: =AP50-AQ50 -> 0
B51: 1.4.8 | C51: Chalecos reflectivos | E51: =VLOOKUP(B51,'FLUJO DE CAJA PROYECTADO '!$B$13:$J$61,3,FALSE) -> 1 | F51: =VLOOKUP(B51,'FLUJO DE CAJA PROYECTADO '!$B$13:$J$61,9,FALSE) -> 81037 | G51: =VLOOKUP(B51,'FLUJO DE CAJA PROYECTADO '!$B$13:$J$61,8,FALSE) -> 81037 | H51: =D51-G51 -> -81037 | J51: =VLOOKUP($B51,ASEGURADO!$B$3:$J$51,3,FALSE) -> 1 | K51: =VLOOKUP(B51,ASEGURADO!$B$3:$J$52,9,FALSE) -> 81037 | L51: =VLOOKUP($B51,ASEGURADO!$B$3:$J$52,8,FALSE) -> 0 | M51: =G51-L51 -> 81037 | P51: =VLOOKUP(B51,REAL!$B$13:$J$61,3,FALSE) -> 1 | Q51: =VLOOKUP(B51,REAL!$B$13:$J$61,9,FALSE) -> 81037 | R51: =VLOOKUP(B51,REAL!$B$13:$J$61,8,FALSE) -> 0 | S51: =G51-R51 -> 81037 | U51: =VLOOKUP(B51,Contabilidad!$B$3:$D$51,3,FALSE) -> 0 | V51: =R51-U51 -> 0 | X51: =VLOOKUP($B51,'FLUJO DE CAJA PROYECTADO '!$B$13:$AI$66,'Control Flujo de caja'!X$16,FALSE) -> 81037 | Y51: =VLOOKUP($B51,REAL!$B$13:$AI$61,'Control Flujo de caja'!Y$16,FALSE) -> 0 | Z51: =X51-Y51 -> 81037 | AA51: =VLOOKUP($B51,'FLUJO DE CAJA PROYECTADO '!$B$13:$AI$66,'Control Flujo de caja'!AA$16,FALSE) -> 0 | AB51: =VLOOKUP($B51,REAL!$B$13:$AI$61,'Control Flujo de caja'!AB$16,FALSE) -> 0 | AC51: =AA51-AB51 -> 0 | AD51: =VLOOKUP($B51,'FLUJO DE CAJA PROYECTADO '!$B$13:$AI$66,'Control Flujo de caja'!AD$16,FALSE) -> 0 | AE51: =VLOOKUP($B51,REAL!$B$13:$AI$61,'Control Flujo de caja'!AE$16,FALSE) -> 0 | AF51: =AD51-AE51 -> 0 | AG51: =VLOOKUP($B51,'FLUJO DE CAJA PROYECTADO '!$B$13:$AI$66,'Control Flujo de caja'!AG$16,FALSE) -> 0 | AH51: =VLOOKUP($B51,REAL!$B$13:$AI$61,'Control Flujo de caja'!AH$16,FALSE) -> 0 | AI51: =AG51-AH51 -> 0 | AJ51: =VLOOKUP($B51,'FLUJO DE CAJA PROYECTADO '!$B$13:$AI$66,'Control Flujo de caja'!AJ$16,FALSE) -> 0 | AK51: =VLOOKUP($B51,REAL!$B$13:$AI$61,'Control Flujo de caja'!AK$16,FALSE) -> 0 | AL51: =AJ51-AK51 -> 0 | AM51: =VLOOKUP($B51,'FLUJO DE CAJA PROYECTADO '!$B$13:$AN$66,'Control Flujo de caja'!AM$16,FALSE) -> 0 | AN51: =VLOOKUP($B51,REAL!$B$13:$AN$61,'Control Flujo de caja'!AN$16,FALSE) -> 0 | AO51: =AM51-AN51 -> 0 | AP51: =VLOOKUP($B51,'FLUJO DE CAJA PROYECTADO '!$B$13:$AS$66,'Control Flujo de caja'!AP$16,FALSE) -> 0 | AQ51: =VLOOKUP($B51,REAL!$B$13:$AS$61,'Control Flujo de caja'!AQ$16,FALSE) -> 0 | AR51: =AP51-AQ51 -> 0
B52: 1.4.9 | C52: Overoles | E52: =VLOOKUP(B52,'FLUJO DE CAJA PROYECTADO '!$B$13:$J$61,3,FALSE) -> 1 | F52: =VLOOKUP(B52,'FLUJO DE CAJA PROYECTADO '!$B$13:$J$61,9,FALSE) -> 186870 | G52: =VLOOKUP(B52,'FLUJO DE CAJA PROYECTADO '!$B$13:$J$61,8,FALSE) -> 186870 | H52: =D52-G52 -> -186870 | J52: =VLOOKUP($B52,ASEGURADO!$B$3:$J$51,3,FALSE) -> 1 | K52: =VLOOKUP(B52,ASEGURADO!$B$3:$J$52,9,FALSE) -> 186870 | L52: =VLOOKUP($B52,ASEGURADO!$B$3:$J$52,8,FALSE) -> 0 | M52: =G52-L52 -> 186870 | P52: =VLOOKUP(B52,REAL!$B$13:$J$61,3,FALSE) -> 1 | Q52: =VLOOKUP(B52,REAL!$B$13:$J$61,9,FALSE) -> 186870 | R52: =VLOOKUP(B52,REAL!$B$13:$J$61,8,FALSE) -> 0 | S52: =G52-R52 -> 186870 | U52: =VLOOKUP(B52,Contabilidad!$B$3:$D$51,3,FALSE) -> 0 | V52: =R52-U52 -> 0 | X52: =VLOOKUP($B52,'FLUJO DE CAJA PROYECTADO '!$B$13:$AI$66,'Control Flujo de caja'!X$16,FALSE) -> 186870 | Y52: =VLOOKUP($B52,REAL!$B$13:$AI$61,'Control Flujo de caja'!Y$16,FALSE) -> 0 | Z52: =X52-Y52 -> 186870 | AA52: =VLOOKUP($B52,'FLUJO DE CAJA PROYECTADO '!$B$13:$AI$66,'Control Flujo de caja'!AA$16,FALSE) -> 0 | AB52: =VLOOKUP($B52,REAL!$B$13:$AI$61,'Control Flujo de caja'!AB$16,FALSE) -> 0 | AC52: =AA52-AB52 -> 0 | AD52: =VLOOKUP($B52,'FLUJO DE CAJA PROYECTADO '!$B$13:$AI$66,'Control Flujo de caja'!AD$16,FALSE) -> 0 | AE52: =VLOOKUP($B52,REAL!$B$13:$AI$61,'Control Flujo de caja'!AE$16,FALSE) -> 0 | AF52: =AD52-AE52 -> 0 | AG52: =VLOOKUP($B52,'FLUJO DE CAJA PROYECTADO '!$B$13:$AI$66,'Control Flujo de caja'!AG$16,FALSE) -> 0 | AH52: =VLOOKUP($B52,REAL!$B$13:$AI$61,'Control Flujo de caja'!AH$16,FALSE) -> 0 | AI52: =AG52-AH52 -> 0 | AJ52: =VLOOKUP($B52,'FLUJO DE CAJA PROYECTADO '!$B$13:$AI$66,'Control Flujo de caja'!AJ$16,FALSE) -> 0 | AK52: =VLOOKUP($B52,REAL!$B$13:$AI$61,'Control Flujo de caja'!AK$16,FALSE) -> 0 | AL52: =AJ52-AK52 -> 0 | AM52: =VLOOKUP($B52,'FLUJO DE CAJA PROYECTADO '!$B$13:$AN$66,'Control Flujo de caja'!AM$16,FALSE) -> 0 | AN52: =VLOOKUP($B52,REAL!$B$13:$AN$61,'Control Flujo de caja'!AN$16,FALSE) -> 0 | AO52: =AM52-AN52 -> 0 | AP52: =VLOOKUP($B52,'FLUJO DE CAJA PROYECTADO '!$B$13:$AS$66,'Control Flujo de caja'!AP$16,FALSE) -> 0 | AQ52: =VLOOKUP($B52,REAL!$B$13:$AS$61,'Control Flujo de caja'!AQ$16,FALSE) -> 0 | AR52: =AP52-AQ52 -> 0
B53: 1.5 | C53: G.C. | D53: 58546503 | E53: =SUM(E54) -> 1 | F53: =SUM(F54) -> 58546503 | G53: =SUM(G54) -> 58546503 | H53: =D53-G53 -> 0 | J53: =SUM(J54) -> 1 | K53: =VLOOKUP(B53,ASEGURADO!$B$3:$J$52,9,FALSE) -> 58546503 | L53: =VLOOKUP($B53,ASEGURADO!$B$3:$J$52,8,FALSE) -> 58546503 | M53: =SUM(M54) -> 0 | P53: =SUM(P54) -> 1 | Q53: =SUM(Q54) -> 58546503 | R53: =SUM(R54) -> 58546503 | S53: =G53-R53 -> 0 | U53: =VLOOKUP(B53,Contabilidad!$B$3:$D$51,3,FALSE) -> 0 | V53: =SUM(V54) -> 58546503 | X53: =SUM(X54) -> 58546503 | Y53: =SUM(Y54) -> 58546503 | Z53: =SUM(Z54) -> 0 | AA53: =SUM(AA54) -> 0 | AB53: =SUM(AB54) -> 0 | AC53: =SUM(AC54) -> 0 | AD53: =SUM(AD54) -> 0 | AE53: =SUM(AE54) -> 0 | ... AR53: =SUM(AR54) -> 0
B54: 1.5.1 | C54: TRANSPORTES | D54: 58546503 | E54: =VLOOKUP(B54,'FLUJO DE CAJA PROYECTADO '!$B$13:$J$61,3,FALSE) -> 1 | F54: =VLOOKUP(B54,'FLUJO DE CAJA PROYECTADO '!$B$13:$J$61,9,FALSE) -> 58546503 | G54: =VLOOKUP(B54,'FLUJO DE CAJA PROYECTADO '!$B$13:$J$61,8,FALSE) -> 58546503 | H54: =D54-G54 -> 0 | J54: =VLOOKUP($B54,ASEGURADO!$B$3:$J$51,3,FALSE) -> 1 | K54: =VLOOKUP(B54,ASEGURADO!$B$3:$J$52,9,FALSE) -> 58546503 | L54: =VLOOKUP($B54,ASEGURADO!$B$3:$J$52,8,FALSE) -> 58546503 | M54: =G54-L54 -> 0 | P54: =VLOOKUP(B54,REAL!$B$13:$J$61,3,FALSE) -> 1 | Q54: =VLOOKUP(B54,REAL!$B$13:$J$61,9,FALSE) -> 58546503 | R54: =VLOOKUP(B54,REAL!$B$13:$J$61,8,FALSE) -> 58546503 | S54: =G54-R54 -> 0 | U54: =VLOOKUP(B54,Contabilidad!$B$3:$D$51,3,FALSE) -> 0 | V54: =R54-U54 -> 58546503 | X54: =VLOOKUP($B54,'FLUJO DE CAJA PROYECTADO '!$B$13:$AI$66,'Control Flujo de caja'!X$16,FALSE) -> 58546503 | Y54: =VLOOKUP($B54,REAL!$B$13:$AI$61,'Control Flujo de caja'!Y$16,FALSE) -> 58546503 | Z54: =X54-Y54 -> 0 | AA54: =VLOOKUP($B54,'FLUJO DE CAJA PROYECTADO '!$B$13:$AI$66,'Control Flujo de caja'!AA$16,FALSE) -> 0 | AB54: =VLOOKUP($B54,REAL!$B$13:$AI$61,'Control Flujo de caja'!AB$16,FALSE) -> 0 | AC54: =AA54-AB54 -> 0 | AD54: =VLOOKUP($B54,'FLUJO DE CAJA PROYECTADO '!$B$13:$AI$66,'Control Flujo de caja'!AD$16,FALSE) -> 0 | AE54: =VLOOKUP($B54,REAL!$B$13:$AI$61,'Control Flujo de caja'!AE$16,FALSE) -> 0 | AF54: =AD54-AE54 -> 0 | AG54: =VLOOKUP($B54,'FLUJO DE CAJA PROYECTADO '!$B$13:$AI$66,'Control Flujo de caja'!AG$16,FALSE) -> 0 | AH54: =VLOOKUP($B54,REAL!$B$13:$AI$61,'Control Flujo de caja'!AH$16,FALSE) -> 0 | AI54: =AG54-AH54 -> 0 | AJ54: =VLOOKUP($B54,'FLUJO DE CAJA PROYECTADO '!$B$13:$AI$66,'Control Flujo de caja'!AJ$16,FALSE) -> 0 | AK54: =VLOOKUP($B54,REAL!$B$13:$AI$61,'Control Flujo de caja'!AK$16,FALSE) -> 0 | AL54: =AJ54-AK54 -> 0 | AM54: =VLOOKUP($B54,'FLUJO DE CAJA PROYECTADO '!$B$13:$AN$66,'Control Flujo de caja'!AM$16,FALSE) -> 0 | AN54: =VLOOKUP($B54,REAL!$B$13:$AN$61,'Control Flujo de caja'!AN$16,FALSE) -> 0 | AO54: =AM54-AN54 -> 0 | AP54: =VLOOKUP($B54,'FLUJO DE CAJA PROYECTADO '!$B$13:$AS$66,'Control Flujo de caja'!AP$16,FALSE) -> 0 | AQ54: =VLOOKUP($B54,REAL!$B$13:$AS$61,'Control Flujo de caja'!AQ$16,FALSE) -> 0 | AR54: =AP54-AQ54 -> 0
B55: 3 | C55: Viaticos | D55: =D56 -> 0 | E55: =E56 -> 0 | F55: =F56 -> 4200000 | G55: =G56 -> 17881010 | H55: =D55-G55 -> -17881010 | J55: =J56 -> 0 | K55: =K56 -> 4200000 | L55: =L56 -> 1497410 | M55: =M56 -> 16383600 | P55: =P56 -> 0 | Q55: =Q56 -> 4200000 | R55: =R56 -> 0 | S55: =G55-R55 -> 17881010 | U55: =VLOOKUP(B55,Contabilidad!$B$3:$D$51,3,FALSE) -> 609510 | V55: =V56 -> -609510 | X55: =X56 -> 0 | Y55: =Y56 -> 0 | Z55: =Z56 -> 0 | AA55: =AA56 -> 1497410 | AB55: =AB56 -> 1497410 | AC55: =AC56 -> 0 | AD55: =AD56 -> 2235000 | AE55: =AE56 -> 2235000 | ... AR55: =AR56 -> 4716200
B56: 3.1 | C56: Viaticos | D56: =SUM(D57:D60) -> 0 | E56: =SUM(E57:E60) -> 0 | F56: =SUM(F57:F60) -> 4200000 | G56: =SUM(G57:G60) -> 17881010 | H56: =D56-G56 -> -17881010 | J56: =SUM(J57:J60) -> 0 | K56: =SUM(K57:K60) -> 4200000 | L56: =SUM(L57:L60) -> 1497410 | M56: =SUM(M57:M60) -> 16383600 | P56: =SUM(P57:P60) -> 0 | Q56: =SUM(Q57:Q60) -> 4200000 | R56: =SUM(R57:R60) -> 0 | S56: =G56-R56 -> 17881010 | U56: =VLOOKUP(B56,Contabilidad!$B$3:$D$51,3,FALSE) -> 609510 | V56: =SUM(V57:V60) -> -609510 | X56: =SUM(X57:X60) -> 0 | Y56: =SUM(Y57:Y60) -> 0 | Z56: =SUM(Z57:Z60) -> 0 | AA56: =SUM(AA57:AA60) -> 1497410 | AB56: =SUM(AB57:AB60) -> 1497410 | AC56: =SUM(AC57:AC60) -> 0 | AD56: =SUM(AD57:AD60) -> 2235000 | AE56: =SUM(AE57:AE60) -> 2235000 | ... AR56: =SUM(AR57:AR60) -> 4716200
B57: 3.1.1 | C57: Hospedaje | E57: =VLOOKUP(B57,'FLUJO DE CAJA PROYECTADO '!$B$13:$J$61,3,FALSE) -> 0 | F57: =VLOOKUP(B57,'FLUJO DE CAJA PROYECTADO '!$B$13:$J$61,9,FALSE) -> 1237600 | G57: =VLOOKUP(B57,'FLUJO DE CAJA PROYECTADO '!$B$13:$J$61,8,FALSE) -> 9048000 | H57: =D57-G57 -> -9048000 | J57: =VLOOKUP($B57,ASEGURADO!$B$3:$J$51,3,FALSE) -> 0 | K57: =VLOOKUP(B57,ASEGURADO!$B$3:$J$52,9,FALSE) -> 1237600 | L57: =VLOOKUP($B57,ASEGURADO!$B$3:$J$52,8,FALSE) -> 500000 | M57: =G57-L57 -> 8548000 | P57: =VLOOKUP(B57,REAL!$B$13:$J$61,3,FALSE) -> 0 | Q57: =VLOOKUP(B57,REAL!$B$13:$J$61,9,FALSE) -> 1237600 | R57: =VLOOKUP(B57,REAL!$B$13:$J$61,6,FALSE) -> 0 | S57: =G57-R57 -> 9048000 | U57: =VLOOKUP(B57,Contabilidad!$B$3:$D$51,3,FALSE) -> 0 | V57: =R57-U57 -> 0 | X57: =VLOOKUP($B57,'FLUJO DE CAJA PROYECTADO '!$B$13:$AI$66,'Control Flujo de caja'!X$16,FALSE) -> 0 | Y57: =VLOOKUP($B57,REAL!$B$13:$AI$61,'Control Flujo de caja'!Y$16,FALSE) -> 0 | Z57: =X57-Y57 -> 0 | AA57: =VLOOKUP($B57,'FLUJO DE CAJA PROYECTADO '!$B$13:$AI$66,'Control Flujo de caja'!AA$16,FALSE) -> 500000 | AB57: =VLOOKUP($B57,REAL!$B$13:$AI$61,'Control Flujo de caja'!AB$16,FALSE) -> 500000 | AC57: =AA57-AB57 -> 0 | AD57: =VLOOKUP($B57,'FLUJO DE CAJA PROYECTADO '!$B$13:$AI$66,'Control Flujo de caja'!AD$16,FALSE) -> 1348000 | AE57: =VLOOKUP($B57,REAL!$B$13:$AI$61,'Control Flujo de caja'!AE$16,FALSE) -> 1348000 | AF57: =AD57-AE57 -> 0 | AG57: =VLOOKUP($B57,'FLUJO DE CAJA PROYECTADO '!$B$13:$AI$66,'Control Flujo de caja'!AG$16,FALSE) -> 2400000 | AH57: =VLOOKUP($B57,REAL!$B$13:$AI$61,'Control Flujo de caja'!AH$16,FALSE) -> 2400000 | AI57: =AG57-AH57 -> 0 | AJ57: =VLOOKUP($B57,'FLUJO DE CAJA PROYECTADO '!$B$13:$AI$66,'Control Flujo de caja'!AJ$16,FALSE) -> 2400000 | AK57: =VLOOKUP($B57,REAL!$B$13:$AI$61,'Control Flujo de caja'!AK$16,FALSE) -> 0 | AL57: =AJ57-AK57 -> 2400000 | AM57: =VLOOKUP($B57,'FLUJO DE CAJA PROYECTADO '!$B$13:$AN$66,'Control Flujo de caja'!AM$16,FALSE) -> 2400000 | AN57: =VLOOKUP($B57,REAL!$B$13:$AN$61,'Control Flujo de caja'!AN$16,FALSE) -> 2093495 | AO57: =AM57-AN57 -> 306505 | AP57: =VLOOKUP($B57,'FLUJO DE CAJA PROYECTADO '!$B$13:$AS$66,'Control Flujo de caja'!AP$16,FALSE) -> 2400000 | AQ57: =VLOOKUP($B57,REAL!$B$13:$AS$61,'Control Flujo de caja'!AQ$16,FALSE) -> 0 | AR57: =AP57-AQ57 -> 2400000
B58: 3.1.2 | C58: Transportes | E58: =VLOOKUP(B58,'FLUJO DE CAJA PROYECTADO '!$B$13:$J$61,3,FALSE) -> 0 | F58: =VLOOKUP(B58,'FLUJO DE CAJA PROYECTADO '!$B$13:$J$61,9,FALSE) -> 292400 | G58: =VLOOKUP(B58,'FLUJO DE CAJA PROYECTADO '!$B$13:$J$61,8,FALSE) -> 586500 | H58: =D58-G58 -> -586500 | J58: =VLOOKUP($B58,ASEGURADO!$B$3:$J$51,3,FALSE) -> 0 | K58: =VLOOKUP(B58,ASEGURADO!$B$3:$J$52,9,FALSE) -> 292400 | L58: =VLOOKUP($B58,ASEGURADO!$B$3:$J$52,8,FALSE) -> 147900 | M58: =G58-L58 -> 438600 | P58: =VLOOKUP(B58,REAL!$B$13:$J$61,3,FALSE) -> 0 | Q58: =VLOOKUP(B58,REAL!$B$13:$J$61,9,FALSE) -> 292400 | R58: =VLOOKUP(B58,REAL!$B$13:$J$61,6,FALSE) -> 0 | S58: =G58-R58 -> 586500 | U58: =VLOOKUP(B58,Contabilidad!$B$3:$D$51,3,FALSE) -> 0 | V58: =R58-U58 -> 0 | X58: =VLOOKUP($B58,'FLUJO DE CAJA PROYECTADO '!$B$13:$AI$66,'Control Flujo de caja'!X$16,FALSE) -> 0 | Y58: =VLOOKUP($B58,REAL!$B$13:$AI$61,'Control Flujo de caja'!Y$16,FALSE) -> 0 | Z58: =X58-Y58 -> 0 | AA58: =VLOOKUP($B58,'FLUJO DE CAJA PROYECTADO '!$B$13:$AI$66,'Control Flujo de caja'!AA$16,FALSE) -> 147900 | AB58: =VLOOKUP($B58,REAL!$B$13:$AI$61,'Control Flujo de caja'!AB$16,FALSE) -> 147900 | AC58: =AA58-AB58 -> 0 | AD58: =VLOOKUP($B58,'FLUJO DE CAJA PROYECTADO '!$B$13:$AI$66,'Control Flujo de caja'!AD$16,FALSE) -> 0 | AE58: =VLOOKUP($B58,REAL!$B$13:$AI$61,'Control Flujo de caja'!AE$16,FALSE) -> 0 | AF58: =AD58-AE58 -> 0 | AG58: =VLOOKUP($B58,'FLUJO DE CAJA PROYECTADO '!$B$13:$AI$66,'Control Flujo de caja'!AG$16,FALSE) -> 146200 | AH58: =VLOOKUP($B58,REAL!$B$13:$AI$61,'Control Flujo de caja'!AH$16,FALSE) -> 248000 | AI58: =AG58-AH58 -> -101800 | AJ58: =VLOOKUP($B58,'FLUJO DE CAJA PROYECTADO '!$B$13:$AI$66,'Control Flujo de caja'!AJ$16,FALSE) -> 146200 | AK58: =VLOOKUP($B58,REAL!$B$13:$AI$61,'Control Flujo de caja'!AK$16,FALSE) -> 426000 | AL58: =AJ58-AK58 -> -279800 | AM58: =VLOOKUP($B58,'FLUJO DE CAJA PROYECTADO '!$B$13:$AN$66,'Control Flujo de caja'!AM$16,FALSE) -> 146200 | AN58: =VLOOKUP($B58,REAL!$B$13:$AN$61,'Control Flujo de caja'!AN$16,FALSE) -> 0 | AO58: =AM58-AN58 -> 146200 | AP58: =VLOOKUP($B58,'FLUJO DE CAJA PROYECTADO '!$B$13:$AS$66,'Control Flujo de caja'!AP$16,FALSE) -> 146200 | AQ58: =VLOOKUP($B58,REAL!$B$13:$AS$61,'Control Flujo de caja'!AQ$16,FALSE) -> 0 | AR58: =AP58-AQ58 -> 146200
B59: 3.1.3 | C59: Pasajes | E59: =VLOOKUP(B59,'FLUJO DE CAJA PROYECTADO '!$B$13:$J$61,3,FALSE) -> 0 | F59: =VLOOKUP(B59,'FLUJO DE CAJA PROYECTADO '!$B$13:$J$61,9,FALSE) -> 2190000 | G59: =VLOOKUP(B59,'FLUJO DE CAJA PROYECTADO '!$B$13:$J$61,8,FALSE) -> 1539510 | H59: =D59-G59 -> -1539510 | J59: =VLOOKUP($B59,ASEGURADO!$B$3:$J$51,3,FALSE) -> 0 | K59: =VLOOKUP(B59,ASEGURADO!$B$3:$J$52,9,FALSE) -> 2190000 | L59: =VLOOKUP($B59,ASEGURADO!$B$3:$J$52,8,FALSE) -> 609510 | M59: =G59-L59 -> 930000 | P59: =VLOOKUP(B59,REAL!$B$13:$J$61,3,FALSE) -> 0 | Q59: =VLOOKUP(B59,REAL!$B$13:$J$61,9,FALSE) -> 2190000 | R59: =VLOOKUP(B59,REAL!$B$13:$J$61,6,FALSE) -> 0 | S59: =G59-R59 -> 1539510 | U59: =VLOOKUP(B59,Contabilidad!$B$3:$D$51,3,FALSE) -> 609510 | V59: =R59-U59 -> -609510 | X59: =VLOOKUP($B59,'FLUJO DE CAJA PROYECTADO '!$B$13:$AI$66,'Control Flujo de caja'!X$16,FALSE) -> 0 | Y59: =VLOOKUP($B59,REAL!$B$13:$AI$61,'Control Flujo de caja'!Y$16,FALSE) -> 0 | Z59: =X59-Y59 -> 0 | AA59: =VLOOKUP($B59,'FLUJO DE CAJA PROYECTADO '!$B$13:$AI$66,'Control Flujo de caja'!AA$16,FALSE) -> 609510 | AB59: =VLOOKUP($B59,REAL!$B$13:$AI$61,'Control Flujo de caja'!AB$16,FALSE) -> 609510 | AC59: =AA59-AB59 -> 0 | AD59: =VLOOKUP($B59,'FLUJO DE CAJA PROYECTADO '!$B$13:$AI$66,'Control Flujo de caja'!AD$16,FALSE) -> 0 | AE59: =VLOOKUP($B59,REAL!$B$13:$AI$61,'Control Flujo de caja'!AE$16,FALSE) -> 0 | AF59: =AD59-AE59 -> 0 | AG59: =VLOOKUP($B59,'FLUJO DE CAJA PROYECTADO '!$B$13:$AI$66,'Control Flujo de caja'!AG$16,FALSE) -> 310000 | AH59: =VLOOKUP($B59,REAL!$B$13:$AI$61,'Control Flujo de caja'!AH$16,FALSE) -> 0 | AI59: =AG59-AH59 -> 310000 | AJ59: =VLOOKUP($B59,'FLUJO DE CAJA PROYECTADO '!$B$13:$AI$66,'Control Flujo de caja'!AJ$16,FALSE) -> 310000 | AK59: =VLOOKUP($B59,REAL!$B$13:$AI$61,'Control Flujo de caja'!AK$16,FALSE) -> 0 | AL59: =AJ59-AK59 -> 310000 | AM59: =VLOOKUP($B59,'FLUJO DE CAJA PROYECTADO '!$B$13:$AN$66,'Control Flujo de caja'!AM$16,FALSE) -> 310000 | AN59: =VLOOKUP($B59,REAL!$B$13:$AN$61,'Control Flujo de caja'!AN$16,FALSE) -> 0 | AO59: =AM59-AN59 -> 310000 | AP59: =VLOOKUP($B59,'FLUJO DE CAJA PROYECTADO '!$B$13:$AS$66,'Control Flujo de caja'!AP$16,FALSE) -> 310000 | AQ59: =VLOOKUP($B59,REAL!$B$13:$AS$61,'Control Flujo de caja'!AQ$16,FALSE) -> 0 | AR59: =AP59-AQ59 -> 310000
B60: 3.1.4 | C60: Alimentacion | E60: =VLOOKUP(B60,'FLUJO DE CAJA PROYECTADO '!$B$13:$J$61,3,FALSE) -> 0 | F60: =VLOOKUP(B60,'FLUJO DE CAJA PROYECTADO '!$B$13:$J$61,9,FALSE) -> 480000 | G60: =VLOOKUP(B60,'FLUJO DE CAJA PROYECTADO '!$B$13:$J$61,8,FALSE) -> 6707000 | H60: =D60-G60 -> -6707000 | J60: =VLOOKUP($B60,ASEGURADO!$B$3:$J$51,3,FALSE) -> 0 | K60: =VLOOKUP(B60,ASEGURADO!$B$3:$J$52,9,FALSE) -> 480000 | L60: =VLOOKUP($B60,ASEGURADO!$B$3:$J$52,8,FALSE) -> 240000 | M60: =G60-L60 -> 6467000 | P60: =VLOOKUP(B60,REAL!$B$13:$J$61,3,FALSE) -> 0 | Q60: =VLOOKUP(B60,REAL!$B$13:$J$61,9,FALSE) -> 480000 | R60: =VLOOKUP(B60,REAL!$B$13:$J$61,6,FALSE) -> 0 | S60: =G60-R60 -> 6707000 | U60: =VLOOKUP(B60,Contabilidad!$B$3:$D$51,3,FALSE) -> 0 | V60: =R60-U60 -> 0 | X60: =VLOOKUP($B60,'FLUJO DE CAJA PROYECTADO '!$B$13:$AI$66,'Control Flujo de caja'!X$16,FALSE) -> 0 | Y60: =VLOOKUP($B60,REAL!$B$13:$AI$61,'Control Flujo de caja'!Y$16,FALSE) -> 0 | Z60: =X60-Y60 -> 0 | AA60: =VLOOKUP($B60,'FLUJO DE CAJA PROYECTADO '!$B$13:$AI$66,'Control Flujo de caja'!AA$16,FALSE) -> 240000 | AB60: =VLOOKUP($B60,REAL!$B$13:$AI$61,'Control Flujo de caja'!AB$16,FALSE) -> 240000 | AC60: =AA60-AB60 -> 0 | AD60: =VLOOKUP($B60,'FLUJO DE CAJA PROYECTADO '!$B$13:$AI$66,'Control Flujo de caja'!AD$16,FALSE) -> 887000 | AE60: =VLOOKUP($B60,REAL!$B$13:$AI$61,'Control Flujo de caja'!AE$16,FALSE) -> 887000 | AF60: =AD60-AE60 -> 0 | AG60: =VLOOKUP($B60,'FLUJO DE CAJA PROYECTADO '!$B$13:$AI$66,'Control Flujo de caja'!AG$16,FALSE) -> 1860000 | AH60: =VLOOKUP($B60,REAL!$B$13:$AI$61,'Control Flujo de caja'!AH$16,FALSE) -> 1860000 | AI60: =AG60-AH60 -> 0 | AJ60: =VLOOKUP($B60,'FLUJO DE CAJA PROYECTADO '!$B$13:$AI$66,'Control Flujo de caja'!AJ$16,FALSE) -> 1860000 | AK60: =VLOOKUP($B60,REAL!$B$13:$AI$61,'Control Flujo de caja'!AK$16,FALSE) -> 1874000 | AL60: =AJ60-AK60 -> -14000 | AM60: =VLOOKUP($B60,'FLUJO DE CAJA PROYECTADO '!$B$13:$AN$66,'Control Flujo de caja'!AM$16,FALSE) -> 1860000 | AN60: =VLOOKUP($B60,REAL!$B$13:$AN$61,'Control Flujo de caja'!AN$16,FALSE) -> 0 | AO60: =AM60-AN60 -> 1860000 | AP60: =VLOOKUP($B60,'FLUJO DE CAJA PROYECTADO '!$B$13:$AS$66,'Control Flujo de caja'!AP$16,FALSE) -> 1860000 | AQ60: =VLOOKUP($B60,REAL!$B$13:$AS$61,'Control Flujo de caja'!AQ$16,FALSE) -> 0 | AR60: =AP60-AQ60 -> 1860000
B61: 4 | C61: INGENIERÍA | D61: =D62 -> 0 | E61: =E62 -> 0 | F61: =F62 -> 11448635 | G61: =G62 -> 11448636 | H61: =D61-G61 -> -11448636 | J61: =J62 -> 0 | K61: =K62 -> 11448635 | L61: =L62 -> 0 | M61: =M62 -> 11448636 | P61: =P62 -> 0 | Q61: =Q62 -> 11448635 | R61: =R62 -> 0 | S61: =G61-R61 -> 11448636 | U61: =VLOOKUP(B61,Contabilidad!$B$3:$D$51,3,FALSE) -> 0 | V61: =V62 -> 0 | X61: =X62 -> 0 | Y61: =Y62 -> 0 | Z61: =Z62 -> 0 | AA61: =AA62 -> 0 | AB61: =AB62 -> 0 | AC61: =AC62 -> 0 | AD61: =AD62 -> 0 | AE61: =AE62 -> 0 | ... AR61: =AR62 -> 0
B62: 4.1 | C62: Ingenieria de taller | D62: =D63 -> 0 | E62: =E63 -> 0 | F62: =F63 -> 11448635 | G62: =G63 -> 11448636 | H62: =D62-G62 -> -11448636 | J62: =J63 -> 0 | K62: =K63 -> 11448635 | L62: =L63 -> 0 | M62: =M63 -> 11448636 | P62: =P63 -> 0 | Q62: =Q63 -> 11448635 | R62: =R63 -> 0 | S62: =G62-R62 -> 11448636 | U62: =VLOOKUP(B62,Contabilidad!$B$3:$D$51,3,FALSE) -> 0 | V62: =V63 -> 0 | X62: =X63 -> 0 | Y62: =Y63 -> 0 | Z62: =Z63 -> 0 | AA62: =AA63 -> 0 | AB62: =AB63 -> 0 | AC62: =AC63 -> 0 | AD62: =AD63 -> 0 | AE62: =AE63 -> 0 | ... AR62: =AR63 -> 0
B63: 4.1.1 | C63: Ingenieria de taller | E63: =VLOOKUP(B63,'FLUJO DE CAJA PROYECTADO '!$B$13:$J$61,3,FALSE) -> 0 | F63: =VLOOKUP(B63,'FLUJO DE CAJA PROYECTADO '!$B$13:$J$61,9,FALSE) -> 11448635 | G63: =VLOOKUP(B63,'FLUJO DE CAJA PROYECTADO '!$B$13:$J$61,8,FALSE) -> 11448636 | H63: =D63-G63 -> -11448636 | J63: =VLOOKUP($B63,ASEGURADO!$B$3:$J$51,3,FALSE) -> 0 | K63: =VLOOKUP(B63,ASEGURADO!$B$3:$J$52,9,FALSE) -> 11448635 | L63: =VLOOKUP($B63,ASEGURADO!$B$3:$J$52,8,FALSE) -> 0 | M63: =G63-L63 -> 11448636 | P63: =VLOOKUP(B63,REAL!$B$13:$J$61,3,FALSE) -> 0 | Q63: =VLOOKUP(B63,REAL!$B$13:$J$61,9,FALSE) -> 11448635 | R63: =VLOOKUP(B63,REAL!$B$13:$J$61,6,FALSE) -> 0 | S63: =G63-R63 -> 11448636 | U63: =VLOOKUP(B63,Contabilidad!$B$3:$D$51,3,FALSE) -> 0 | V63: =R63-U63 -> 0 | X63: =VLOOKUP($B63,'FLUJO DE CAJA PROYECTADO '!$B$13:$AI$66,'Control Flujo de caja'!X$16,FALSE) -> 0 | Y63: =VLOOKUP($B63,REAL!$B$13:$AI$61,'Control Flujo de caja'!Y$16,FALSE) -> 0 | Z63: =X63-Y63 -> 0 | AA63: =VLOOKUP($B63,'FLUJO DE CAJA PROYECTADO '!$B$13:$AI$66,'Control Flujo de caja'!AA$16,FALSE) -> 0 | AB63: =VLOOKUP($B63,REAL!$B$13:$AI$61,'Control Flujo de caja'!AB$16,FALSE) -> 0 | AC63: =AA63-AB63 -> 0 | AD63: =VLOOKUP($B63,'FLUJO DE CAJA PROYECTADO '!$B$13:$AI$66,'Control Flujo de caja'!AD$16,FALSE) -> 0 | AE63: =VLOOKUP($B63,REAL!$B$13:$AI$61,'Control Flujo de caja'!AE$16,FALSE) -> 0 | AF63: =AD63-AE63 -> 0 | AG63: =VLOOKUP($B63,'FLUJO DE CAJA PROYECTADO '!$B$13:$AI$66,'Control Flujo de caja'!AG$16,FALSE) -> 0 | AH63: =VLOOKUP($B63,REAL!$B$13:$AI$61,'Control Flujo de caja'!AH$16,FALSE) -> 0 | AI63: =AG63-AH63 -> 0 | AJ63: =VLOOKUP($B63,'FLUJO DE CAJA PROYECTADO '!$B$13:$AI$66,'Control Flujo de caja'!AJ$16,FALSE) -> 11448636 | AK63: =VLOOKUP($B63,REAL!$B$13:$AI$61,'Control Flujo de caja'!AK$16,FALSE) -> 0 | AL63: =AJ63-AK63 -> 11448636 | AM63: =VLOOKUP($B63,'FLUJO DE CAJA PROYECTADO '!$B$13:$AN$66,'Control Flujo de caja'!AM$16,FALSE) -> 0 | AN63: =VLOOKUP($B63,REAL!$B$13:$AN$61,'Control Flujo de caja'!AN$16,FALSE) -> 0 | AO63: =AM63-AN63 -> 0 | AP63: =VLOOKUP($B63,'FLUJO DE CAJA PROYECTADO '!$B$13:$AS$66,'Control Flujo de caja'!AP$16,FALSE) -> 0 | AQ63: =VLOOKUP($B63,REAL!$B$13:$AS$61,'Control Flujo de caja'!AQ$16,FALSE) -> 0 | AR63: =AP63-AQ63 -> 0
B64: 5 | C64: Suministros | D64: =SUM(D65) -> 0 | E64: =SUM(E65) -> 313 | F64: =SUM(F65) -> 2045743.3 | G64: =SUM(G65) -> 2.4344444e+08 | H64: =D64-G64 -> -2.4344444e+08 | J64: =SUM(J65) -> 313 | K64: =SUM(K65) -> 2045743.3 | L64: =SUM(L65) -> 2.4324869e+08 | M64: =SUM(M65) -> 195750.24 | P64: =SUM(P65) -> 313 | Q64: =SUM(Q65) -> 2045743.3 | R64: =SUM(R65) -> 71708196 | S64: =G64-R64 -> 1.7173624e+08 | U64: =VLOOKUP(B64,Contabilidad!$B$3:$D$51,3,FALSE) -> 48133429 | V64: =SUM(V65) -> 23574766 | X64: =SUM(X65) -> 0 | Y64: =SUM(Y65) -> 0 | Z64: =SUM(Z65) -> 0 | AA64: =SUM(AA65) -> 93907565 | AB64: =SUM(AB65) -> 0 | AC64: =SUM(AC65) -> 93907565 | AD64: =SUM(AD65) -> 0 | AE64: =SUM(AE65) -> 48329180 | ... AR64: =SUM(AR65) -> -1.7154049e+08
B65: 5.1 | C65: PINTURA | D65: =D66+D70 -> 0 | E65: =E66+E70 -> 313 | F65: =F66+F70 -> 2045743.3 | G65: =G66+G70 -> 2.4344444e+08 | H65: =D65-G65 -> -2.4344444e+08 | J65: =J66+J70 -> 313 | K65: =K66+K70 -> 2045743.3 | L65: =L66+L70 -> 2.4324869e+08 | M65: =M66+M70 -> 195750.24 | P65: =P66+P70 -> 313 | Q65: =Q66+Q70 -> 2045743.3 | R65: =R66+R70 -> 71708196 | S65: =G65-R65 -> 1.7173624e+08 | U65: =VLOOKUP(B65,Contabilidad!$B$3:$D$51,3,FALSE) -> 48133429 | V65: =V66+V70 -> 23574766 | X65: =X66+X70 -> 0 | Y65: =Y66+Y70 -> 0 | Z65: =Z66+Z70 -> 0 | AA65: =AA66+AA70 -> 93907565 | AB65: =AB66+AB70 -> 0 | AC65: =AC66+AC70 -> 93907565 | AD65: =AD66+AD70 -> 0 | AE65: =AE66+AE70 -> 48329180 | ... AR65: =AR66+AR70 -> -1.7154049e+08
B66: 5.1.1 | C66: Epoxico | D66: =SUM(D67:D69) -> 0 | E66: =SUM(E67:E69) -> 149 | F66: =SUM(F67:F69) -> 866096.28 | G66: =SUM(G67:G69) -> 93907565 | H66: =D66-G66 -> -93907565 | J66: =SUM(J67:J69) -> 149 | K66: =SUM(K67:K69) -> 866096.28 | L66: =SUM(L67:L69) -> 93711815 | M66: =SUM(M67:M69) -> 195750.24 | P66: =SUM(P67:P69) -> 149 | Q66: =SUM(Q67:Q69) -> 866096.28 | R66: =SUM(R67:R69) -> 70528549 | S66: =G66-R66 -> 23379016 | U66: =VLOOKUP(B66,Contabilidad!$B$3:$D$51,3,FALSE) -> 0 | V66: =SUM(V67:V69) -> 22395119 | X66: =SUM(X67:X69) -> 0 | Y66: =SUM(Y67:Y69) -> 0 | Z66: =SUM(Z67:Z69) -> 0 | AA66: =SUM(AA67:AA69) -> 93907565 | AB66: =SUM(AB67:AB69) -> 0 | AC66: =SUM(AC67:AC69) -> 93907565 | AD66: =SUM(AD67:AD69) -> 0 | AE66: =SUM(AE67:AE69) -> 47149533 | ... AR66: =SUM(AR67:AR69) -> -23183266
B67: 5.1.1.1 | C67: Anticorrosivo epoxico x cuñete | E67: =VLOOKUP(B67,'FLUJO DE CAJA PROYECTADO '!$B$13:$J$61,3,FALSE) -> 136 | F67: =VLOOKUP(B67,'FLUJO DE CAJA PROYECTADO '!$B$13:$J$61,9,FALSE) -> 670346.04 | G67: =VLOOKUP(B67,'FLUJO DE CAJA PROYECTADO '!$B$13:$J$61,8,FALSE) -> 91167061 | H67: =D67-G67 -> -91167061 | J67: =VLOOKUP($B67,ASEGURADO!$B$3:$J$51,3,FALSE) -> 136 | K67: =VLOOKUP(B67,ASEGURADO!$B$3:$J$52,9,FALSE) -> 670346.04 | L67: =VLOOKUP($B67,ASEGURADO!$B$3:$J$52,8,FALSE) -> 91167061 | M67: =G67-L67 -> 0 | P67: =VLOOKUP(B67,REAL!$B$13:$J$61,3,FALSE) -> 136 | Q67: =VLOOKUP(B67,REAL!$B$13:$J$61,9,FALSE) -> 670346.04 | R67: =VLOOKUP(B67,REAL!$B$13:$J$61,8,FALSE) -> 68375296 | S67: =G67-R67 -> 22791765 | U67: =VLOOKUP(B67,Contabilidad!$B$3:$D$51,3,FALSE) -> 48133429 | V67: =R67-U67 -> 20241867 | X67: =VLOOKUP($B67,'FLUJO DE CAJA PROYECTADO '!$B$13:$AI$66,'Control Flujo de caja'!X$16,FALSE)*VLOOKUP($B67,'FLUJO DE CAJA PROYECTADO '!$B$13:$AI$66,9,FALSE) -> 0 | Y67: =VLOOKUP($B67,REAL!$B$13:$AI$61,'Control Flujo de caja'!Y$16,FALSE)*VLOOKUP($B67,REAL!$B$13:$AI$61,9,FALSE) -> 0 | Z67: =X67-Y67 -> 0 | AA67: =VLOOKUP($B67,'FLUJO DE CAJA PROYECTADO '!$B$13:$AI$66,'Control Flujo de caja'!AA$16,FALSE)*VLOOKUP($B67,'FLUJO DE CAJA PROYECTADO '!$B$13:$AI$66,9,FALSE) -> 91167061 | AB67: =VLOOKUP($B67,REAL!$B$13:$AI$61,'Control Flujo de caja'!AB$16,FALSE)*VLOOKUP($B67,REAL!$B$13:$AI$61,9,FALSE) -> 0 | AC67: =AA67-AB67 -> 91167061 | AD67: =VLOOKUP($B67,'FLUJO DE CAJA PROYECTADO '!$B$13:$AI$66,'Control Flujo de caja'!AD$16,FALSE)*VLOOKUP($B67,'FLUJO DE CAJA PROYECTADO '!$B$13:$AI$66,9,FALSE) -> 0 | AE67: =VLOOKUP($B67,REAL!$B$13:$AI$61,'Control Flujo de caja'!AE$16,FALSE)*VLOOKUP($B67,REAL!$B$13:$AI$61,9,FALSE) -> 45583531 | AF67: =AD67-AE67 -> -45583531 | AG67: =VLOOKUP($B67,'FLUJO DE CAJA PROYECTADO '!$B$13:$AI$66,'Control Flujo de caja'!AG$16,FALSE)*VLOOKUP($B67,'FLUJO DE CAJA PROYECTADO '!$B$13:$AI$66,9,FALSE) -> 0 | AH67: =VLOOKUP($B67,REAL!$B$13:$AI$61,'Control Flujo de caja'!AH$16,FALSE)*VLOOKUP($B67,REAL!$B$13:$AI$61,9,FALSE) -> 0 | AI67: =AG67-AH67 -> 0 | AJ67: =VLOOKUP($B67,'FLUJO DE CAJA PROYECTADO '!$B$13:$AI$66,'Control Flujo de caja'!AJ$16,FALSE)*VLOOKUP($B67,'FLUJO DE CAJA PROYECTADO '!$B$13:$AI$66,9,FALSE) -> 0 | AK67: =VLOOKUP($B67,REAL!$B$13:$AI$61,'Control Flujo de caja'!AK$16,FALSE)*VLOOKUP($B67,REAL!$B$13:$AI$61,9,FALSE) -> 0 | AL67: =AJ67-AK67 -> 0 | AM67: =VLOOKUP($B67,'FLUJO DE CAJA PROYECTADO '!$B$13:$AN$66,'Control Flujo de caja'!AM$16,FALSE) -> 0 | AN67: =VLOOKUP($B67,REAL!$B$13:$AS$610,'Control Flujo de caja'!AN$16,FALSE)*REAL!$J53 -> 22791765 | AO67: =AM67-AN67 -> -22791765 | AP67: =VLOOKUP($B67,'FLUJO DE CAJA PROYECTADO '!$B$13:$AS$66,'Control Flujo de caja'!AP$16,FALSE) -> 0 | AQ67: =VLOOKUP($B67,REAL!$B$13:$AS$610,'Control Flujo de caja'!AQ$16,FALSE)*REAL!$J53 -> 22791765 | AR67: =AP67-AQ67 -> -22791765
B68: 5.1.1.2 | C68: Catalizador | E68: =VLOOKUP(B68,'FLUJO DE CAJA PROYECTADO '!$B$13:$J$61,3,FALSE) -> 0 | F68: =VLOOKUP(B68,'FLUJO DE CAJA PROYECTADO '!$B$13:$J$61,9,FALSE) -> 0 | G68: =VLOOKUP(B68,'FLUJO DE CAJA PROYECTADO '!$B$13:$J$61,8,FALSE) -> 0 | H68: =D68-G68 -> 0 | J68: =VLOOKUP($B68,ASEGURADO!$B$3:$J$51,3,FALSE) -> 0 | K68: =VLOOKUP(B68,ASEGURADO!$B$3:$J$52,9,FALSE) -> 0 | L68: =VLOOKUP($B68,ASEGURADO!$B$3:$J$52,8,FALSE) -> 0 | M68: =G68-L68 -> 0 | P68: =VLOOKUP(B68,REAL!$B$13:$J$61,3,FALSE) -> 0 | Q68: =VLOOKUP(B68,REAL!$B$13:$J$61,9,FALSE) -> 0 | R68: =VLOOKUP(B68,REAL!$B$13:$J$61,8,FALSE) -> 0 | S68: =G68-R68 -> 0 | U68: =VLOOKUP(B68,Contabilidad!$B$3:$D$51,3,FALSE) -> 0 | V68: =R68-U68 -> 0 | X68: =VLOOKUP($B68,'FLUJO DE CAJA PROYECTADO '!$B$13:$AI$66,'Control Flujo de caja'!X$16,FALSE)*VLOOKUP($B68,'FLUJO DE CAJA PROYECTADO '!$B$13:$AI$66,9,FALSE) -> 0 | Y68: =VLOOKUP($B68,REAL!$B$13:$AI$61,'Control Flujo de caja'!Y$16,FALSE)*VLOOKUP($B68,REAL!$B$13:$AI$61,9,FALSE) -> 0 | Z68: =X68-Y68 -> 0 | AA68: =VLOOKUP($B68,'FLUJO DE CAJA PROYECTADO '!$B$13:$AI$66,'Control Flujo de caja'!AA$16,FALSE)*VLOOKUP($B68,'FLUJO DE CAJA PROYECTADO '!$B$13:$AI$66,9,FALSE) -> 0 | AB68: =VLOOKUP($B68,REAL!$B$13:$AI$61,'Control Flujo de caja'!AB$16,FALSE)*VLOOKUP($B68,REAL!$B$13:$AI$61,9,FALSE) -> 0 | AC68: =AA68-AB68 -> 0 | AD68: =VLOOKUP($B68,'FLUJO DE CAJA PROYECTADO '!$B$13:$AI$66,'Control Flujo de caja'!AD$16,FALSE)*VLOOKUP($B68,'FLUJO DE CAJA PROYECTADO '!$B$13:$AI$66,9,FALSE) -> 0 | AE68: =VLOOKUP($B68,REAL!$B$13:$AI$61,'Control Flujo de caja'!AE$16,FALSE)*VLOOKUP($B68,REAL!$B$13:$AI$61,9,FALSE) -> 0 | AF68: =AD68-AE68 -> 0 | AG68: =VLOOKUP($B68,'FLUJO DE CAJA PROYECTADO '!$B$13:$AI$66,'Control Flujo de caja'!AG$16,FALSE)*VLOOKUP($B68,'FLUJO DE CAJA PROYECTADO '!$B$13:$AI$66,9,FALSE) -> 0 | AH68: =VLOOKUP($B68,REAL!$B$13:$AI$61,'Control Flujo de caja'!AH$16,FALSE)*VLOOKUP($B68,REAL!$B$13:$AI$61,9,FALSE) -> 0 | AI68: =AG68-AH68 -> 0 | AJ68: =VLOOKUP($B68,'FLUJO DE CAJA PROYECTADO '!$B$13:$AI$66,'Control Flujo de caja'!AJ$16,FALSE)*VLOOKUP($B68,'FLUJO DE CAJA PROYECTADO '!$B$13:$AI$66,9,FALSE) -> 0 | AK68: =VLOOKUP($B68,REAL!$B$13:$AI$61,'Control Flujo de caja'!AK$16,FALSE)*VLOOKUP($B68,REAL!$B$13:$AI$61,9,FALSE) -> 0 | AL68: =AJ68-AK68 -> 0 | AM68: =VLOOKUP($B68,'FLUJO DE CAJA PROYECTADO '!$B$13:$AN$66,'Control Flujo de caja'!AM$16,FALSE) -> 0 | AN68: =VLOOKUP($B68,REAL!$B$13:$AS$610,'Control Flujo de caja'!AN$16,FALSE)*REAL!$J54 -> 0 | AO68: =AM68-AN68 -> 0 | AP68: =VLOOKUP($B68,'FLUJO DE CAJA PROYECTADO '!$B$13:$AS$66,'Control Flujo de caja'!AP$16,FALSE) -> 0 | AQ68: =VLOOKUP($B68,REAL!$B$13:$AS$610,'Control Flujo de caja'!AQ$16,FALSE)*REAL!$J54 -> 0 | AR68: =AP68-AQ68 -> 0
B69: 5.1.1.3 | C69: Disolvente epoxicco cuñete | E69: =VLOOKUP(B69,'FLUJO DE CAJA PROYECTADO '!$B$13:$J$61,3,FALSE) -> 13 | F69: =VLOOKUP(B69,'FLUJO DE CAJA PROYECTADO '!$B$13:$J$61,9,FALSE) -> 195750.24 | G69: =VLOOKUP(B69,'FLUJO DE CAJA PROYECTADO '!$B$13:$J$61,8,FALSE) -> 2740503.4 | H69: =D69-G69 -> -2740503.4 | J69: =VLOOKUP($B69,ASEGURADO!$B$3:$J$51,3,FALSE) -> 13 | K69: =VLOOKUP(B69,ASEGURADO!$B$3:$J$52,9,FALSE) -> 195750.24 | L69: =VLOOKUP($B69,ASEGURADO!$B$3:$J$52,8,FALSE) -> 2544753.1 | M69: =G69-L69 -> 195750.24 | P69: =VLOOKUP(B69,REAL!$B$13:$J$61,3,FALSE) -> 13 | Q69: =VLOOKUP(B69,REAL!$B$13:$J$61,9,FALSE) -> 195750.24 | R69: =VLOOKUP(B69,REAL!$B$13:$J$61,8,FALSE) -> 2153252.6 | S69: =G69-R69 -> 587250.72 | U69: =VLOOKUP(B69,Contabilidad!$B$3:$D$51,3,FALSE) -> 0 | V69: =R69-U69 -> 2153252.6 | X69: =VLOOKUP($B69,'FLUJO DE CAJA PROYECTADO '!$B$13:$AI$66,'Control Flujo de caja'!X$16,FALSE)*VLOOKUP($B69,'FLUJO DE CAJA PROYECTADO '!$B$13:$AI$66,9,FALSE) -> 0 | Y69: =VLOOKUP($B69,REAL!$B$13:$AI$61,'Control Flujo de caja'!Y$16,FALSE)*VLOOKUP($B69,REAL!$B$13:$AI$61,9,FALSE) -> 0 | Z69: =X69-Y69 -> 0 | AA69: =VLOOKUP($B69,'FLUJO DE CAJA PROYECTADO '!$B$13:$AI$66,'Control Flujo de caja'!AA$16,FALSE)*VLOOKUP($B69,'FLUJO DE CAJA PROYECTADO '!$B$13:$AI$66,9,FALSE) -> 2740503.4 | AB69: =VLOOKUP($B69,REAL!$B$13:$AI$61,'Control Flujo de caja'!AB$16,FALSE)*VLOOKUP($B69,REAL!$B$13:$AI$61,9,FALSE) -> 0 | AC69: =AA69-AB69 -> 2740503.4 | AD69: =VLOOKUP($B69,'FLUJO DE CAJA PROYECTADO '!$B$13:$AI$66,'Control Flujo de caja'!AD$16,FALSE)*VLOOKUP($B69,'FLUJO DE CAJA PROYECTADO '!$B$13:$AI$66,9,FALSE) -> 0 | AE69: =VLOOKUP($B69,REAL!$B$13:$AI$61,'Control Flujo de caja'!AE$16,FALSE)*VLOOKUP($B69,REAL!$B$13:$AI$61,9,FALSE) -> 1566001.9 | AF69: =AD69-AE69 -> -1566001.9 | AG69: =VLOOKUP($B69,'FLUJO DE CAJA PROYECTADO '!$B$13:$AI$66,'Control Flujo de caja'!AG$16,FALSE)*VLOOKUP($B69,'FLUJO DE CAJA PROYECTADO '!$B$13:$AI$66,9,FALSE) -> 0 | AH69: =VLOOKUP($B69,REAL!$B$13:$AI$61,'Control Flujo de caja'!AH$16,FALSE)*VLOOKUP($B69,REAL!$B$13:$AI$61,9,FALSE) -> 0 | AI69: =AG69-AH69 -> 0 | AJ69: =VLOOKUP($B69,'FLUJO DE CAJA PROYECTADO '!$B$13:$AI$66,'Control Flujo de caja'!AJ$16,FALSE)*VLOOKUP($B69,'FLUJO DE CAJA PROYECTADO '!$B$13:$AI$66,9,FALSE) -> 0 | AK69: =VLOOKUP($B69,REAL!$B$13:$AI$61,'Control Flujo de caja'!AK$16,FALSE)*VLOOKUP($B69,REAL!$B$13:$AI$61,9,FALSE) -> 0 | AL69: =AJ69-AK69 -> 0 | AM69: =VLOOKUP($B69,'FLUJO DE CAJA PROYECTADO '!$B$13:$AN$66,'Control Flujo de caja'!AM$16,FALSE) -> 0 | AN69: =VLOOKUP($B69,REAL!$B$13:$AS$610,'Control Flujo de caja'!AN$16,FALSE)*REAL!$J55 -> 587250.72 | AO69: =AM69-AN69 -> -587250.72 | AP69: =VLOOKUP($B69,'FLUJO DE CAJA PROYECTADO '!$B$13:$AS$66,'Control Flujo de caja'!AP$16,FALSE) -> 0 | AQ69: =VLOOKUP($B69,REAL!$B$13:$AS$610,'Control Flujo de caja'!AQ$16,FALSE)*REAL!$J55 -> 391500.48 | AR69: =AP69-AQ69 -> -391500.48
B70: 5.1.2 | C70: Pintura | D70: =SUM(D71:D73) -> 0 | E70: =SUM(E71:E73) -> 164 | F70: =SUM(F71:F73) -> 1179647 | G70: =SUM(G71:G73) -> 1.4953687e+08 | H70: =D70-G70 -> -1.4953687e+08 | J70: =SUM(J71:J73) -> 164 | K70: =SUM(K71:K73) -> 1179647 | L70: =SUM(L71:L73) -> 1.4953687e+08 | M70: =SUM(M71:M73) -> 0 | P70: =SUM(P71:P73) -> 164 | Q70: =SUM(Q71:Q73) -> 1179647 | R70: =SUM(R71:R73) -> 1179647 | S70: =G70-R70 -> 1.4835722e+08 | U70: =VLOOKUP(B70,Contabilidad!$B$3:$D$51,3,FALSE) -> 0 | V70: =SUM(V71:V73) -> 1179647 | X70: =SUM(X71:X73) -> 0 | Y70: =SUM(Y71:Y73) -> 0 | Z70: =SUM(Z71:Z73) -> 0 | AA70: =SUM(AA71:AA73) -> 0 | AB70: =SUM(AB71:AB73) -> 0 | AC70: =SUM(AC71:AC73) -> 0 | AD70: =SUM(AD71:AD73) -> 0 | AE70: =SUM(AE71:AE73) -> 1179647 | ... AR70: =SUM(AR71:AR73) -> -1.4835722e+08
B71: 5.1.2.1 | C71: Esmalte Urretano | E71: =VLOOKUP(B71,'FLUJO DE CAJA PROYECTADO '!$B$13:$J$61,3,FALSE) -> 149 | F71: =VLOOKUP(B71,'FLUJO DE CAJA PROYECTADO '!$B$13:$J$61,9,FALSE) -> 983896.76 | G71: =VLOOKUP(B71,'FLUJO DE CAJA PROYECTADO '!$B$13:$J$61,8,FALSE) -> 1.4660062e+08 | H71: =D71-G71 -> -1.4660062e+08 | J71: =VLOOKUP($B71,ASEGURADO!$B$3:$J$51,3,FALSE) -> 149 | K71: =VLOOKUP(B71,ASEGURADO!$B$3:$J$52,9,FALSE) -> 983896.76 | L71: =VLOOKUP($B71,ASEGURADO!$B$3:$J$52,8,FALSE) -> 1.4660062e+08 | M71: =G71-L71 -> 0 | P71: =VLOOKUP(B71,REAL!$B$13:$J$61,3,FALSE) -> 149 | Q71: =VLOOKUP(B71,REAL!$B$13:$J$61,9,FALSE) -> 983896.76 | R71: =VLOOKUP(B71,REAL!$B$13:$J$61,8,FALSE) -> 983896.76 | S71: =G71-R71 -> 1.4561672e+08 | U71: =VLOOKUP(B71,Contabilidad!$B$3:$D$51,3,FALSE) -> 0 | V71: =R71-U71 -> 983896.76 | X71: =VLOOKUP($B71,'FLUJO DE CAJA PROYECTADO '!$B$13:$AI$66,'Control Flujo de caja'!X$16,FALSE)*VLOOKUP($B71,'FLUJO DE CAJA PROYECTADO '!$B$13:$AI$66,9,FALSE) -> 0 | Y71: =VLOOKUP($B71,REAL!$B$13:$AI$61,'Control Flujo de caja'!Y$16,FALSE)*VLOOKUP($B71,REAL!$B$13:$AI$61,9,FALSE) -> 0 | Z71: =X71-Y71 -> 0 | AA71: =VLOOKUP($B71,'FLUJO DE CAJA PROYECTADO '!$B$13:$AI$66,'Control Flujo de caja'!AA$16,FALSE)*VLOOKUP($B71,'FLUJO DE CAJA PROYECTADO '!$B$13:$AI$66,9,FALSE) -> 0 | AB71: =VLOOKUP($B71,REAL!$B$13:$AI$61,'Control Flujo de caja'!AB$16,FALSE)*VLOOKUP($B71,REAL!$B$13:$AI$61,9,FALSE) -> 0 | AC71: =AA71-AB71 -> 0 | AD71: =VLOOKUP($B71,'FLUJO DE CAJA PROYECTADO '!$B$13:$AI$66,'Control Flujo de caja'!AD$16,FALSE)*VLOOKUP($B71,'FLUJO DE CAJA PROYECTADO '!$B$13:$AI$66,9,FALSE) -> 0 | AE71: =VLOOKUP($B71,REAL!$B$13:$AI$61,'Control Flujo de caja'!AE$16,FALSE)*VLOOKUP($B71,REAL!$B$13:$AI$61,9,FALSE) -> 983896.76 | AF71: =AD71-AE71 -> -983896.76 | AG71: =VLOOKUP($B71,'FLUJO DE CAJA PROYECTADO '!$B$13:$AI$66,'Control Flujo de caja'!AG$16,FALSE)*VLOOKUP($B71,'FLUJO DE CAJA PROYECTADO '!$B$13:$AI$66,9,FALSE) -> 1.4660062e+08 | AH71: =VLOOKUP($B71,REAL!$B$13:$AI$61,'Control Flujo de caja'!AH$16,FALSE)*VLOOKUP($B71,REAL!$B$13:$AI$61,9,FALSE) -> 0 | AI71: =AG71-AH71 -> 1.4660062e+08 | AJ71: =VLOOKUP($B71,'FLUJO DE CAJA PROYECTADO '!$B$13:$AI$66,'Control Flujo de caja'!AJ$16,FALSE)*VLOOKUP($B71,'FLUJO DE CAJA PROYECTADO '!$B$13:$AI$66,9,FALSE) -> 0 | AK71: =VLOOKUP($B71,REAL!$B$13:$AI$61,'Control Flujo de caja'!AK$16,FALSE)*VLOOKUP($B71,REAL!$B$13:$AI$61,9,FALSE) -> 0 | AL71: =AJ71-AK71 -> 0 | AM71: =VLOOKUP($B71,'FLUJO DE CAJA PROYECTADO '!$B$13:$AN$66,'Control Flujo de caja'!AM$16,FALSE) -> 0 | AN71: =VLOOKUP($B71,REAL!$B$13:$AS$610,'Control Flujo de caja'!AN$16,FALSE)*REAL!$J57 -> 0 | AO71: =AM71-AN71 -> 0 | AP71: =VLOOKUP($B71,'FLUJO DE CAJA PROYECTADO '!$B$13:$AS$66,'Control Flujo de caja'!AP$16,FALSE) -> 0 | AQ71: =VLOOKUP($B71,REAL!$B$13:$AS$610,'Control Flujo de caja'!AQ$16,FALSE)*REAL!$J57 -> 1.4561672e+08 | AR71: =AP71-AQ71 -> -1.4561672e+08
B72: 5.1.2.2 | C72: Catalizador Urretano | E72: =VLOOKUP(B72,'FLUJO DE CAJA PROYECTADO '!$B$13:$J$61,3,FALSE) -> 0 | F72: =VLOOKUP(B72,'FLUJO DE CAJA PROYECTADO '!$B$13:$J$61,9,FALSE) -> 0 | G72: =VLOOKUP(B72,'FLUJO DE CAJA PROYECTADO '!$B$13:$J$61,8,FALSE) -> 0 | H72: =D72-G72 -> 0 | J72: =VLOOKUP($B72,ASEGURADO!$B$3:$J$51,3,FALSE) -> 0 | K72: =VLOOKUP(B72,ASEGURADO!$B$3:$J$52,9,FALSE) -> 0 | L72: =VLOOKUP($B72,ASEGURADO!$B$3:$J$52,8,FALSE) -> 0 | M72: =G72-L72 -> 0 | P72: =VLOOKUP(B72,REAL!$B$13:$J$61,3,FALSE) -> 0 | Q72: =VLOOKUP(B72,REAL!$B$13:$J$61,9,FALSE) -> 0 | R72: =VLOOKUP(B72,REAL!$B$13:$J$61,8,FALSE) -> 0 | S72: =G72-R72 -> 0 | U72: =VLOOKUP(B72,Contabilidad!$B$3:$D$51,3,FALSE) -> 0 | V72: =R72-U72 -> 0 | X72: =VLOOKUP($B72,'FLUJO DE CAJA PROYECTADO '!$B$13:$AI$66,'Control Flujo de caja'!X$16,FALSE)*VLOOKUP($B72,'FLUJO DE CAJA PROYECTADO '!$B$13:$AI$66,9,FALSE) -> 0 | Y72: =VLOOKUP($B72,REAL!$B$13:$AI$61,'Control Flujo de caja'!Y$16,FALSE)*VLOOKUP($B72,REAL!$B$13:$AI$61,9,FALSE) -> 0 | Z72: =X72-Y72 -> 0 | AA72: =VLOOKUP($B72,'FLUJO DE CAJA PROYECTADO '!$B$13:$AI$66,'Control Flujo de caja'!AA$16,FALSE)*VLOOKUP($B72,'FLUJO DE CAJA PROYECTADO '!$B$13:$AI$66,9,FALSE) -> 0 | AB72: =VLOOKUP($B72,REAL!$B$13:$AI$61,'Control Flujo de caja'!AB$16,FALSE)*VLOOKUP($B72,REAL!$B$13:$AI$61,9,FALSE) -> 0 | AC72: =AA72-AB72 -> 0 | AD72: =VLOOKUP($B72,'FLUJO DE CAJA PROYECTADO '!$B$13:$AI$66,'Control Flujo de caja'!AD$16,FALSE)*VLOOKUP($B72,'FLUJO DE CAJA PROYECTADO '!$B$13:$AI$66,9,FALSE) -> 0 | AE72: =VLOOKUP($B72,REAL!$B$13:$AI$61,'Control Flujo de caja'!AE$16,FALSE)*VLOOKUP($B72,REAL!$B$13:$AI$61,9,FALSE) -> 0 | AF72: =AD72-AE72 -> 0 | AG72: =VLOOKUP($B72,'FLUJO DE CAJA PROYECTADO '!$B$13:$AI$66,'Control Flujo de caja'!AG$16,FALSE)*VLOOKUP($B72,'FLUJO DE CAJA PROYECTADO '!$B$13:$AI$66,9,FALSE) -> 0 | AH72: =VLOOKUP($B72,REAL!$B$13:$AI$61,'Control Flujo de caja'!AH$16,FALSE)*VLOOKUP($B72,REAL!$B$13:$AI$61,9,FALSE) -> 0 | AI72: =AG72-AH72 -> 0 | AJ72: =VLOOKUP($B72,'FLUJO DE CAJA PROYECTADO '!$B$13:$AI$66,'Control Flujo de caja'!AJ$16,FALSE)*VLOOKUP($B72,'FLUJO DE CAJA PROYECTADO '!$B$13:$AI$66,9,FALSE) -> 0 | AK72: =VLOOKUP($B72,REAL!$B$13:$AI$61,'Control Flujo de caja'!AK$16,FALSE)*VLOOKUP($B72,REAL!$B$13:$AI$61,9,FALSE) -> 0 | AL72: =AJ72-AK72 -> 0 | AM72: =VLOOKUP($B72,'FLUJO DE CAJA PROYECTADO '!$B$13:$AN$66,'Control Flujo de caja'!AM$16,FALSE) -> 0 | AN72: =VLOOKUP($B72,REAL!$B$13:$AS$610,'Control Flujo de caja'!AN$16,FALSE)*REAL!$J58 -> 0 | AO72: =AM72-AN72 -> 0 | AP72: =VLOOKUP($B72,'FLUJO DE CAJA PROYECTADO '!$B$13:$AS$66,'Control Flujo de caja'!AP$16,FALSE) -> 0 | AQ72: =VLOOKUP($B72,REAL!$B$13:$AS$610,'Control Flujo de caja'!AQ$16,FALSE)*REAL!$J58 -> 0 | AR72: =AP72-AQ72 -> 0
B73: 5.1.2.3 | C73: Solvente Uretano | E73: =VLOOKUP(B73,'FLUJO DE CAJA PROYECTADO '!$B$13:$J$61,3,FALSE) -> 15 | F73: =VLOOKUP(B73,'FLUJO DE CAJA PROYECTADO '!$B$13:$J$61,9,FALSE) -> 195750.24 | G73: =VLOOKUP(B73,'FLUJO DE CAJA PROYECTADO '!$B$13:$J$61,8,FALSE) -> 2936253.6 | H73: =D73-G73 -> -2936253.6 | J73: =VLOOKUP($B73,ASEGURADO!$B$3:$J$51,3,FALSE) -> 15 | K73: =VLOOKUP(B73,ASEGURADO!$B$3:$J$52,9,FALSE) -> 195750.24 | L73: =VLOOKUP($B73,ASEGURADO!$B$3:$J$52,8,FALSE) -> 2936253.6 | M73: =G73-L73 -> 0 | P73: =VLOOKUP(B73,REAL!$B$13:$J$61,3,FALSE) -> 15 | Q73: =VLOOKUP(B73,REAL!$B$13:$J$61,9,FALSE) -> 195750.24 | R73: =VLOOKUP(B73,REAL!$B$13:$J$61,8,FALSE) -> 195750.24 | S73: =G73-R73 -> 2740503.4 | U73: =VLOOKUP(B73,Contabilidad!$B$3:$D$51,3,FALSE) -> 0 | V73: =R73-U73 -> 195750.24 | X73: =VLOOKUP($B73,'FLUJO DE CAJA PROYECTADO '!$B$13:$AI$66,'Control Flujo de caja'!X$16,FALSE)*VLOOKUP($B73,'FLUJO DE CAJA PROYECTADO '!$B$13:$AI$66,9,FALSE) -> 0 | Y73: =VLOOKUP($B73,REAL!$B$13:$AI$61,'Control Flujo de caja'!Y$16,FALSE)*VLOOKUP($B73,REAL!$B$13:$AI$61,9,FALSE) -> 0 | Z73: =X73-Y73 -> 0 | AA73: =VLOOKUP($B73,'FLUJO DE CAJA PROYECTADO '!$B$13:$AI$66,'Control Flujo de caja'!AA$16,FALSE)*VLOOKUP($B73,'FLUJO DE CAJA PROYECTADO '!$B$13:$AI$66,9,FALSE) -> 0 | AB73: =VLOOKUP($B73,REAL!$B$13:$AI$61,'Control Flujo de caja'!AB$16,FALSE)*VLOOKUP($B73,REAL!$B$13:$AI$61,9,FALSE) -> 0 | AC73: =AA73-AB73 -> 0 | AD73: =VLOOKUP($B73,'FLUJO DE CAJA PROYECTADO '!$B$13:$AI$66,'Control Flujo de caja'!AD$16,FALSE)*VLOOKUP($B73,'FLUJO DE CAJA PROYECTADO '!$B$13:$AI$66,9,FALSE) -> 0 | AE73: =VLOOKUP($B73,REAL!$B$13:$AI$61,'Control Flujo de caja'!AE$16,FALSE)*VLOOKUP($B73,REAL!$B$13:$AI$61,9,FALSE) -> 195750.24 | AF73: =AD73-AE73 -> -195750.24 | AG73: =VLOOKUP($B73,'FLUJO DE CAJA PROYECTADO '!$B$13:$AI$66,'Control Flujo de caja'!AG$16,FALSE)*VLOOKUP($B73,'FLUJO DE CAJA PROYECTADO '!$B$13:$AI$66,9,FALSE) -> 2936253.6 | AH73: =VLOOKUP($B73,REAL!$B$13:$AI$61,'Control Flujo de caja'!AH$16,FALSE)*VLOOKUP($B73,REAL!$B$13:$AI$61,9,FALSE) -> 0 | AI73: =AG73-AH73 -> 2936253.6 | AJ73: =VLOOKUP($B73,'FLUJO DE CAJA PROYECTADO '!$B$13:$AI$66,'Control Flujo de caja'!AJ$16,FALSE)*VLOOKUP($B73,'FLUJO DE CAJA PROYECTADO '!$B$13:$AI$66,9,FALSE) -> 0 | AK73: =VLOOKUP($B73,REAL!$B$13:$AI$61,'Control Flujo de caja'!AK$16,FALSE)*VLOOKUP($B73,REAL!$B$13:$AI$61,9,FALSE) -> 0 | AL73: =AJ73-AK73 -> 0 | AM73: =VLOOKUP($B73,'FLUJO DE CAJA PROYECTADO '!$B$13:$AN$66,'Control Flujo de caja'!AM$16,FALSE) -> 0 | AN73: =VLOOKUP($B73,REAL!$B$13:$AS$610,'Control Flujo de caja'!AN$16,FALSE)*REAL!$J59 -> 0 | AO73: =AM73-AN73 -> 0 | AP73: =VLOOKUP($B73,'FLUJO DE CAJA PROYECTADO '!$B$13:$AS$66,'Control Flujo de caja'!AP$16,FALSE) -> 0 | AQ73: =VLOOKUP($B73,REAL!$B$13:$AS$610,'Control Flujo de caja'!AQ$16,FALSE)*REAL!$J59 -> 2740503.4 | AR73: =AP73-AQ73 -> -2740503.4
B74: 6 | C74: Mano de obra | D74: =SUM(D75) -> 2519593500 | E74: =SUM(E75) -> 185262.6 | F74: =SUM(F75) -> 4337.7139 | G74: =SUM(G75) -> 2.4196446e+09 | H74: =D74-G74 -> 99948932 | J74: =SUM(J75) -> #N/A | K74: =SUM(K75) -> #N/A | L74: =SUM(L75) -> #N/A | M74: =SUM(M75) -> #N/A | P74: =SUM(P75) -> #N/A | Q74: =SUM(Q75) -> 4337.7139 | R74: =SUM(R75) -> 9.7713338e+08 | S74: =G74-R74 -> 1.4425112e+09 | U74: =VLOOKUP(B74,Contabilidad!$B$3:$D$51,3,FALSE) -> 0 | V74: =SUM(V75) -> #N/A | X74: =SUM(X75) -> 0 | Y74: =SUM(Y75) -> 0 | Z74: =SUM(Z75) -> 0 | AA74: =SUM(AA75) -> 1.4027126e+08 | AB74: =SUM(AB75) -> 1.4027126e+08 | AC74: =SUM(AC75) -> 0 | AD74: =SUM(AD75) -> 1.5515135e+08 | AE74: =SUM(AE75) -> 1.5515135e+08 | ... AR74: =SUM(AR75) -> 179678
B75: 6.1 | C75: Fabricación de EEMM | D75: =D76 -> 2519593500 | E75: =E76 -> 185262.6 | F75: =F76 -> 4337.7139 | G75: =SUM(G76:G77) -> 2.4196446e+09 | H75: =D75-G75 -> 99948932 | J75: =J76 -> #N/A | K75: =K76 -> #N/A | L75: =L76 -> #N/A | M75: =M76 -> #N/A | P75: =P76 -> #N/A | Q75: =Q76 -> 4337.7139 | R75: =SUM(R76:R77) -> 9.7713338e+08 | S75: =G75-R75 -> 1.4425112e+09 | U75: =VLOOKUP(B75,Contabilidad!$B$3:$D$51,3,FALSE) -> 0 | V75: =V76 -> #N/A | X75: =SUM(X76:X77) -> 0 | Y75: =SUM(Y76:Y77) -> 0 | Z75: =SUM(Z76:Z77) -> 0 | AA75: =SUM(AA76:AA77) -> 1.4027126e+08 | AB75: =SUM(AB76:AB77) -> 1.4027126e+08 | AC75: =SUM(AC76:AC77) -> 0 | AD75: =SUM(AD76:AD77) -> 1.5515135e+08 | AE75: =SUM(AE76:AE77) -> 1.5515135e+08 | ... AR75: =SUM(AR76:AR77) -> 179678
B76: 6.1.1. | C76: Proveedor 1 | D76: 2519593500 | E76: =VLOOKUP(B76,'FLUJO DE CAJA PROYECTADO '!$B$13:$J$610,3,FALSE) -> 185262.6 | F76: =VLOOKUP(B76,'FLUJO DE CAJA PROYECTADO '!$B$13:$J$610,9,FALSE) -> 4337.7139 | G76: =VLOOKUP(B76,'FLUJO DE CAJA PROYECTADO '!$B$13:$J$610,8,FALSE) -> 8.0361615e+08 | H76: =D76-G76 -> 1.7159773e+09 | J76: =VLOOKUP($B76,ASEGURADO!$B$3:$J$510,3,FALSE) -> #N/A | K76: =VLOOKUP(B76,ASEGURADO!$B$3:$J$52,9,FALSE) -> #N/A | L76: =VLOOKUP($B76,ASEGURADO!$B$3:$J$52,8,FALSE) -> #N/A | M76: =G76-L76 -> #N/A | P76: =VLOOKUP(B76,REAL!$B$13:$J$61,3,FALSE) -> #N/A | Q76: =VLOOKUP(B76,REAL!$B$13:$J$610,9,FALSE) -> 4337.7139 | R76: =VLOOKUP(B76,REAL!$B$13:$J$610,8,FALSE) -> 9.7713338e+08 | S76: =G76-R76 -> -1.7351723e+08 | U76: =VLOOKUP(B76,Contabilidad!$B$3:$D$51,3,FALSE) -> #N/A | V76: =R76-U76 -> #N/A | X76: =VLOOKUP($B76,'FLUJO DE CAJA PROYECTADO '!$B$13:$AI$66,'Control Flujo de caja'!X$16,FALSE)*REAL!$J$62 -> 0 | Y76: =VLOOKUP($B76,REAL!$B$13:$AI$610,'Control Flujo de caja'!Y$16,FALSE)*REAL!$J62 -> 0 | Z76: =X76-Y76 -> 0 | AA76: =VLOOKUP($B76,'FLUJO DE CAJA PROYECTADO '!$B$13:$AI$66,'Control Flujo de caja'!AA$16,FALSE)*REAL!$J$62 -> 1.4027126e+08 | AB76: =VLOOKUP($B76,REAL!$B$13:$AI$610,'Control Flujo de caja'!AB$16,FALSE)*REAL!$J62 -> 1.4027126e+08 | AC76: =AA76-AB76 -> 0 | AD76: =VLOOKUP($B76,'FLUJO DE CAJA PROYECTADO '!$B$13:$AI$66,'Control Flujo de caja'!AD$16,FALSE)*REAL!$J$62 -> 1.5515135e+08 | AE76: =VLOOKUP($B76,REAL!$B$13:$AI$610,'Control Flujo de caja'!AE$16,FALSE)*REAL!$J62 -> 1.5515135e+08 | AF76: =AD76-AE76 -> 0 | AG76: =VLOOKUP($B76,'FLUJO DE CAJA PROYECTADO '!$B$13:$AI$66,'Control Flujo de caja'!AG$16,FALSE)*REAL!$J$62 -> 2.4162368e+08 | AH76: =VLOOKUP($B76,REAL!$B$13:$AI$610,'Control Flujo de caja'!AH$16,FALSE)*REAL!$J62 -> 2.2406895e+08 | AI76: =AG76-AH76 -> 17554728 | AJ76: =VLOOKUP($B76,'FLUJO DE CAJA PROYECTADO '!$B$13:$AI$66,'Control Flujo de caja'!AJ$16,FALSE)*REAL!$J$62 -> 2.6656987e+08 | AK76: =VLOOKUP($B76,REAL!$B$13:$AI$610,'Control Flujo de caja'!AK$16,FALSE)*REAL!$J62 -> 3.7105672e+08 | AL76: =AJ76-AK76 -> -1.0448685e+08 | AM76: =VLOOKUP($B76,'FLUJO DE CAJA PROYECTADO '!$B$13:$AN$660,'Control Flujo de caja'!AM$16,FALSE)*REAL!$J$62 -> 0 | AN76: =VLOOKUP($B76,REAL!$B$13:$AS$610,'Control Flujo de caja'!AN$16,FALSE)*REAL!$J62 -> 86585107 | AO76: =AM76-AN76 -> -86585107 | AP76: =VLOOKUP($B76,'FLUJO DE CAJA PROYECTADO '!$B$13:$AS$66,'Control Flujo de caja'!AP$16,FALSE) -> 0 | AQ76: =VLOOKUP($B76,REAL!$B$13:$AS$610,'Control Flujo de caja'!AQ$16,FALSE)*REAL!$J62 -> 0 | AR76: =AP76-AQ76 -> 0
B77: 6.1.2. | C77: Proveedor 2 | E77: =VLOOKUP(B77,'FLUJO DE CAJA PROYECTADO '!$B$13:$J$547,3,FALSE) -> 0 | F77: =VLOOKUP(B77,'FLUJO DE CAJA PROYECTADO '!$B$13:$J$610,9,FALSE) -> 4687.7139 | G77: =VLOOKUP(B77,'FLUJO DE CAJA PROYECTADO '!$B$13:$J$610,8,FALSE) -> 1.6160284e+09 | H77: =D77-G77 -> -1.6160284e+09 | P77: =VLOOKUP(B77,REAL!$B$13:$J$530,3,FALSE) -> 0 | Q77: =VLOOKUP(B77,REAL!$B$13:$J$530,9,FALSE) -> 4687.7139 | R77: =VLOOKUP(B77,REAL!$B$13:$J$610,8,FALSE) -> 0 | S77: =G77-R77 -> 1.6160284e+09 | X77: =VLOOKUP($B77,'FLUJO DE CAJA PROYECTADO '!$B$13:$AI$66,'Control Flujo de caja'!X$16,FALSE)*REAL!$J$63 -> 0 | Y77: =VLOOKUP($B77,REAL!$B$13:$AI$610,'Control Flujo de caja'!Y$16,FALSE)*REAL!$J63 -> 0 | Z77: =X77-Y77 -> 0 | AA77: =VLOOKUP($B77,'FLUJO DE CAJA PROYECTADO '!$B$13:$AI$66,'Control Flujo de caja'!AA$16,FALSE)*REAL!$J$63 -> 0 | AB77: =VLOOKUP($B77,REAL!$B$13:$AI$610,'Control Flujo de caja'!AB$16,FALSE)*REAL!$J63 -> 0 | AC77: =AA77-AB77 -> 0 | AD77: =VLOOKUP($B77,'FLUJO DE CAJA PROYECTADO '!$B$13:$AI$66,'Control Flujo de caja'!AD$16,FALSE)*REAL!$J$63 -> 0 | AE77: =VLOOKUP($B77,REAL!$B$13:$AI$610,'Control Flujo de caja'!AE$16,FALSE)*REAL!$J63 -> 0 | AF77: =AD77-AE77 -> 0 | AG77: =VLOOKUP($B77,'FLUJO DE CAJA PROYECTADO '!$B$13:$AI$66,'Control Flujo de caja'!AG$16,FALSE)*REAL!$J$63 -> 0 | AH77: =VLOOKUP($B77,REAL!$B$13:$AI$610,'Control Flujo de caja'!AH$16,FALSE)*REAL!$J63 -> 0 | AI77: =AG77-AH77 -> 0 | AJ77: =VLOOKUP($B77,'FLUJO DE CAJA PROYECTADO '!$B$13:$AI$66,'Control Flujo de caja'!AJ$16,FALSE)*REAL!$J$63 -> 0 | AK77: =VLOOKUP($B77,REAL!$B$13:$AI$610,'Control Flujo de caja'!AK$16,FALSE)*REAL!$J63 -> 0 | AL77: =AJ77-AK77 -> 0 | AM77: =VLOOKUP($B77,'FLUJO DE CAJA PROYECTADO '!$B$13:$AN$66,'Control Flujo de caja'!AM$16,FALSE)*REAL!$J$63 -> 7.7374936e+08 | AN77: =VLOOKUP($B77,REAL!$B$13:$AS$610,'Control Flujo de caja'!AN$16,FALSE)*REAL!$J63 -> 0 | AO77: =AM77-AN77 -> 7.7374936e+08 | AP77: =VLOOKUP($B77,'FLUJO DE CAJA PROYECTADO '!$B$13:$AS$66,'Control Flujo de caja'!AP$16,FALSE) -> 179678 | AQ77: =VLOOKUP($B77,REAL!$B$13:$AS$610,'Control Flujo de caja'!AQ$16,FALSE)*REAL!$J63 -> 0 | AR77: =AP77-AQ77 -> 179678
L79: =L74+L64+L61+L55+L28 -> #N/A
C80: Total costos | D80: =D74+D64+D61+D55+D28 -> 2670127484 | G80: =G74+G64+G61+G55+G28 -> 2.791884e+09 | H80: =H74+H64+H61+H55+H28 -> -1.2175654e+08 | R80: =R74+R64+R61+R55+R28 -> 1.1370423e+09 | S80: =S74+S64+S61+S55+S28 -> 1.6548417e+09 | X80: =X74+X64+X61+X55+X28 -> 67561312 | Y80: =Y74+Y64+Y61+Y55+Y28 -> 66899755 | Z80: =Z74+Z64+Z61+Z55+Z28 -> 661557 | AA80: =AA74+AA64+AA61+AA55+AA28 -> 2.4604161e+08 | AB80: =AB74+AB64+AB61+AB55+AB28 -> 1.5213124e+08 | AC80: =AC74+AC64+AC61+AC55+AC28 -> 93910377 | AD80: =AD74+AD64+AD61+AD55+AD28 -> 1.6775173e+08 | AE80: =AE74+AE64+AE61+AE55+AE28 -> 2.1303079e+08 | ... AL80: =AL74+AL64+AL61+AL55+AL28 -> -87172016 | AM80: =IFERROR(AM74+AM64+AM61+AM55+AM28,0) -> 7.8273886e+08 | AN80: =IFERROR(AN74+AN64+AN61+AN55+AN28,0) -> 1.1205762e+08 | AO80: =IFERROR(AO74+AO64+AO61+AO55+AO28,0) -> 6.7068124e+08
C81: Total margen | D81: =D21-D80 -> 257197666
C82: Total venta | D82: 2927325150
C83: IVA 19% sobre utilidad del 5%
C84: Total venta + IVA
C86: MES | D86: PRESUPUESTO | E86: Proyectada | X86: ABRIL | AA86: MAYO | AD86: JUNIO | AG86: JULIO | AJ86: AGOSTO | AM86: SEPTIEMBRE
W87: FLUJO DEL PROYECTO | X87: Proyectado | Y87: ="Real"&Z86 -> Real | Z87: Diferencia | AA87: Proyectado | AB87: ="Real"&AC86 -> Real | AC87: Diferencia | AD87: Proyectado | AE87: ="Real"&AF86 -> Real | AF87: Diferencia | AG87: Proyectado | AH87: ="Real"&AI86 -> Real | AI87: Diferencia | AJ87: Proyectado | AK87: ="Real"&AL86 -> Real | AL87: Diferencia | AM87: Proyectado | AN87: ="Real"&AO86 -> Real | AO87: Diferencia
V88: =AB88+AE88+AH88+AK88+AN88 -> 1.1021602e+09 | W88: COBRO DE FACTURAS | X88: =X24 -> 870811200 | Y88: =Y24 -> 870811200 | Z88: =Y88-X88 -> 0 | AA88: =AA24 -> 0 | AB88: =AB24 -> 0 | AC88: =AB88-AA88 -> 0 | AD88: =AD24 -> 3.016487e+08 | AE88: =AE24 -> 3.016487e+08 | AF88: =AE88-AD88 -> 0 | AG88: =AG24 -> 2.732718e+08 | AH88: =AH24 -> 3.0440545e+08 | AI88: =AH88-AG88 -> 31133648 | AJ88: =AJ24 -> 994140000 | AK88: =AK24 -> 3.2349017e+08 | AL88: =AK88-AJ88 -> -6.7064983e+08 | AM88: =AM24 -> 552300000 | AN88: =AN24 -> 172615842 | AO88: =AN88-AM88 -> -379684158
V89: =Y89+AB89+AE89+AH89+AK89+AN89 -> 0 | W89: AMORTIZACIÓN ANTICIPO | Z89: =Y89-X89 -> 0 | AC89: =AB89-AA89 -> 0 | AF89: =AE89-AD89 -> 0 | AI89: =AH89-AG89 -> 0 | AL89: =AK89-AJ89 -> 0 | AO89: =AN89-AM89 -> 0
V90: =Y90+AB90+AE90+AH90+AK90+AN90 -> 1.1496763e+09 | W90: GASTO MENSUAL | X90: =X80 -> 67561312 | Y90: =Y80 -> 66899755 | Z90: =Y90-X90 -> -661557 | AA90: =AA80 -> 2.4604161e+08 | AB90: =AB80 -> 1.5213124e+08 | AC90: =AB90-AA90 -> -93910377 | AD90: =AD80 -> 1.6775173e+08 | AE90: =AE80 -> 2.1303079e+08 | AF90: =AE90-AD90 -> 45279056 | AG90: =AG80 -> 3.9932675e+08 | AH90: =AH80 -> 2.3220014e+08 | AI90: =AH90-AG90 -> -1.6712661e+08 | AJ90: =AJ80 -> 2.861847e+08 | AK90: =AK80 -> 3.7335672e+08 | AL90: =AK90-AJ90 -> 87172016 | AM90: =AM80 -> 7.8273886e+08 | AN90: =AN80 -> 1.1205762e+08 | AO90: =AN90-AM90 -> -6.7068124e+08
V91: =Y91+AB91+AE91+AH91+AK91+AN91 -> 8.232951e+08 | W91: FLUJO DE CAJA MENSUAL | X91: =X88-X90 -> 803249888 | Y91: =Y88-Y90 -> 803911445 | Z91: =Y91-X91 -> 661557 | AA91: =AA88-AA90 -> -2.4604161e+08 | AB91: =AB88-AB90 -> -1.5213124e+08 | AC91: =AB91-AA91 -> 93910377 | AD91: =AD88-AD90 -> 1.3389697e+08 | AE91: =AE88-AE90 -> 88617909 | AF91: =AE91-AD91 -> -45279056 | AG91: =AG88-AG90 -> -1.2605495e+08 | AH91: =AH88-AH90 -> 72205311 | AI91: =AH91-AG91 -> 1.9826026e+08 | AJ91: =AJ88-AJ90 -> 7.079553e+08 | AK91: =AK88-AK90 -> -49866552 | AL91: =AK91-AJ91 -> -7.5782185e+08 | AM91: =AM88-AM90 -> -2.3043886e+08 | AN91: =AN88-AN90 -> 60558224 | AO91: =AN91-AM91 -> 2.9099708e+08
V92: =Y92+AB92+AE92+AH92+AK92+AN92 -> 4.5947252e+09 | W92: FLUJO DE CAJA ACUMULADO | X92: =X91 -> 803249888 | Y92: =Y91 -> 803911445 | Z92: =Y92-X92 -> 661557 | AA92: =AA91+X92 -> 5.5720828e+08 | AB92: =AB91+Y92 -> 6.5178021e+08 | AC92: =AB92-AA92 -> 94571934 | AD92: =AD91+AA92 -> 6.9110524e+08 | AE92: =AE91+AB92 -> 7.4039812e+08 | AF92: =AE92-AD92 -> 49292878 | AG92: =AG91+AD92 -> 5.6505029e+08 | AH92: =AH91+AE92 -> 8.1260343e+08 | AI92: =AH92-AG92 -> 2.4755314e+08 | AJ92: =AJ91+AG92 -> 1.2730056e+09 | AK92: =AK91+AH92 -> 7.6273688e+08 | AL92: =AK92-AJ92 -> -5.1026871e+08 | AM92: =AM91+AJ92 -> 1.0425667e+09 | AN92: =AN91+AK92 -> 8.232951e+08 | AO92: =AN92-AM92 -> -2.1927163e+08
D93: ='[8]Flujo de caja PRESU'!D79 -> -3.7589358e+08 | E93: =MIN(AB92,AF92,AJ92,AN92,#REF!) -> #REF! | AM93: =AM92/D21 -> 0.35614996
W96: NECESIDAD FINANCIERA | X96: =MIN(X92:AO92) -> -5.1026871e+08

Sheet FLUJO DE CAJA PRESU
B2: NORTON EDIFICIOS INDUSTRIALES COLOMBIA SAS
B4: EMPRESA: | C4: NORTON EDIFICIOS INDUSTRIALES COLOMBIA SAS
B5: DOMICILIO: | C5: Calle 93 # 12 - 14, Edificio Tempo 93, Oficina 704
B7: OBRA: | C7: Edificio CL 16 | G7: CÓDIGO: | H7: 5396-R1
B8: UBICACIÓN: | C8: Bogotá - Colombia | G8: FECHA: | H8: 46100
B11: DATOS DE EXPLOTACIÓN | C11: Meses o costo/u | D11: Detalles | E11: Mes 1 | F11: Mes 2 | G11: Mes 3 | H11: Mes 4
B12: FACTURACIÓN
B13: % DE FACTURACIÓN | E13: 0.4 | F13: 0.4 | G13: 0.2 | H13: 0
B14: FACTURACION PROYECTO | C14: 2902704000
B15: VALOR FACUTADO | E15: 1161081600 | F15: 1161081600 | G15: 580540800 | H15: $ -
B16: ANTICIPO | D16: 0.4 | E16: 1161081600
B17: DESGLOSE DE COSTOS DEL PROYECTO
B18: Indirectos | C18: 150533985 | D18: 150533985 | E18: 95974715 | F18: 29378068 | G18: 25181201 | H18: $ -
B19: Personal de obra | D19: 24640000 | E19: 8624000 | F19: 8624000 | G19: 7392000 | H19: $ -
B20: Campamento y equipos de oficina | D20: - | E20: $ - | F20: $ - | G20: $ - | H20: $ -
B21: Protecciones individuales | D21: 750834 | E21: 262792.04 | F21: 262792.04 | G21: 225250.32 | H21: $ -
B22: Viaticos personal | D22: - | E22: $ - | F22: $ - | G22: $ - | H22: $ -
B23: Topografia | D23: - | E23: $ - | F23: $ - | G23: $ - | H23: $ -
B24: Diseños | D24: - | E24: $ - | F24: $ - | G24: $ - | H24: $ -
B25: Comisión comercial | D25: 58546503 | E25: 20491276 | F25: 20491276 | G25: 17563951 | H25: $ -
B26: Garantias | D26: 18295782 | E26: 18295782 | F26: $ - | G26: $ - | H26: $ -
B27: Impuestos | D27: 48300865 | E27: 48300865 | F27: $ - | G27: $ - | H27: $ -
B28: Intereses prestamos España | D28: - | E28: $ - | F28: $ - | G28: $ - | H28: $ -
B30: EEMM | C30: 2519593500 | D30: 2519593500 | E30: 881857725 | F30: 881857725 | G30: 755878050 | H30: $ -
B31: EEMM | D31: 2519593500 | E31: 881857725 | F31: 881857725 | G31: 755878050 | H31: $ -
B33: FLUJO DEL PROYECTO
B34: COBRO DE FACTURAS | E34: $ - | F34: 1161081600 | G34: 1161081600 | H34: 580540800
B35: AMORTIZACIÓN ANTICIPO | E35: $ - | F35: -464432640 | G35: -464432640 | H35: -232216320
B36: GASTO MENSUAL | E36: -9.7783244e+08 | F36: -9.1123579e+08 | G36: -7.8105925e+08 | H36: $ -
B37: FLUJO DE CAJA MENSUAL | E37: 1.8324916e+08 | F37: -2.1458683e+08 | G37: -84410291 | H37: 348324480
B38: FLUJO DE CAJA ACUMULADO | E38: 1.8324916e+08 | F38: -31337673 | G38: -1.1574796e+08 | H38: 2.3257652e+08 | I38: MARGEN FINAL
B39: NECESIDAD FINANCIERA | C39: -1.1574796e+08

Sheet FLUJO DE CAJA PROYECTADO 
J5: =J12 -> 9 | K5: =K12 -> 10 | L5: =L12 -> 11 | M5: =M12 -> 12 | N5: =N12 -> 13 | O5: =O12 -> 14 | P5: =P12 -> 15 | Q5: =Q12 -> 16 | ... AS5: =AS12 -> 44
I6: Valor total | J6: Valor Unitario | K6: semana 1 | L6: semana 2 | M6: semana 3 | N6: semana 4 | O6: Total Abril 2026 | P6: semana 5 | Q6: semana 6 | R6: semana 7 | S6: semana 8 | T6: Total mayo 2026 | U6: semana 9 | V6: semana 10 | W6: semana 11 | X6: semana 12 | Y6: Total junio 2026 | Z6: semana 13 | AA6: semana 14 | AB6: semana 15 | AC6: semana 16 | AD6: Total julio 2026 | AE6: semana 17 | AF6: semana 18 | AG6: semana 19 | AH6: semana 20 | AI6: Total Agosto 2026 | AJ6: semana 17 | AK6: semana 18 | AL6: semana 19 | AM6: semana 20 | AN6: Total Septiembre 2026 | AO6: semana 21 | AP6: semana 22 | AQ6: semana 23 | AR6: semana 24 | AS6: Total Septiembre 2027
C7: % DE FACTURACIÓN | D7: 530000 | E7: Kg | F7: 4753.95 | G7: =+D7*F7 -> 2519593500 | O7: =SUM(K7:N7) -> 0 | S7: 0 | T7: =SUM(P7:S7) -> 0 | W7: 54616.82 | Y7: =SUM(U7:X7) -> 54616.82 | AA7: 23957.46 | AC7: 25521.41 | AD7: =SUM(Z7:AC7) -> 49478.87 | AF7: 80000 | AH7: 100000 | AI7: =SUM(AE7:AH7) -> 180000 | AK7: 31254 | AM7: 68746 | AN7: =SUM(AJ7:AM7) -> 100000 | AP7: 145905 | AS7: =SUM(AO7:AR7) -> 145905
I8: =(O7+T7+Y7+AD7+AI7)*J8 -> 1.5690605e+09 | J8: 5523 | M8: 870811200 | O8: =M8 -> 870811200 | T8: =$J$8*T7 -> 0 | U8: =$J$8*U7 -> 0 | V8: =$J$8*V7 -> 0 | W8: =$J$8*W7 -> 3.016487e+08 | X8: =$J$8*X7 -> 0 | Y8: =$J$8*Y7 -> 3.016487e+08 | Z8: =$J$8*Z7 -> 0 | AA8: =$J$8*AA7 -> 1.3231705e+08 | ... AS8: =$J$8*AS7 -> 805833315
B12: 1 | C12: 2 | D12: 3 | E12: 4 | F12: 5 | G12: 6 | H12: 7 | I12: 8 | J12: 9 | K12: 10 | L12: 11 | M12: 12 | N12: 13 | O12: 14 | P12: 15 | Q12: 16 | R12: 17 | S12: 18 | T12: 19 | U12: 20 | V12: 21 | W12: 22 | X12: 23 | Y12: 24 | Z12: 25 | AA12: 26 | AB12: 27 | AC12: 28 | AD12: 29 | AE12: 30 | AF12: 31 | AG12: 32 | AH12: 33 | AI12: 34 | AJ12: 35 | AK12: 36 | AL12: 37 | AM12: 38 | AN12: 39 | AO12: 40 | AP12: 41 | AQ12: 42 | AR12: 43 | AS12: 44
B13: Código | C13: ITEM | D13: Cantidad+desp. | E13: Unidad de medida | F13: Valor Unitario | G13: Total presupuesto | I13: Valor total | J13: Valor Unitario | K13: semana 1 | L13: semana 2 | M13: semana 3 | N13: semana 4 | O13: Total Abril 2026 | P13: semana 5 | Q13: semana 6 | R13: semana 7 | S13: semana 8 | T13: Total mayo 2026 | U13: semana 9 | V13: semana 10 | W13: semana 11 | X13: semana 12 | Y13: Total junio 2026 | Z13: semana 13 | AA13: semana 14 | AB13: semana 15 | AC13: semana 16 | AD13: Total julio 2026 | AE13: semana 17 | AF13: semana 18 | AG13: semana 19 | AH13: semana 20 | AI13: Total Agosto 2026 | AJ13: semana 17 | AK13: semana 18 | AL13: semana 19 | AM13: semana 20 | AN13: Total Septiembre 2026 | AO13: semana 17 | AP13: semana 18 | AQ13: semana 19 | AR13: semana 20 | AS13: Total Octubre 2026
B14: 1 | C14: Indirectos | G14: =SUM(G15,G22,G26,G29,G39) -> 1.5053398e+08 | I14: =SUM(I15,I22,I26,I29,I39) -> 99465371 | J14: =SUM(J15,J22,J26,J29,J39) -> 123876289 | K14: =SUM(K15,K22,K26,K29,K39) -> 0 | L14: =SUM(L15,L22,L26,L29,L39) -> 0 | M14: =SUM(M15,M22,M26,M29,M39) -> 64463869 | N14: =SUM(N15,N22,N26,N29,N39) -> 3097443 | O14: =SUM(O15,O22,O26,O29,O39) -> 67561312 | P14: =SUM(P15,P22,P26,P29,P39) -> 0 | ... AS14: =SUM(AS15,AS22,AS26,AS29,AS39) -> 60108545
B15: 1.1 | C15: Polizas talleres | D15: =SUM(D16:D21) -> 6 | E15: =SUM(E16:E21) -> 0 | F15: =SUM(F16:F21) -> 18295782 | G15: =SUM(G16:G21) -> 18295782 | I15: =SUM(I16:I21) -> 5917366 | J15: =SUM(J16:J21) -> 5917366 | K15: =SUM(K16:K21) -> 0 | L15: =SUM(L16:L21) -> 0 | M15: =SUM(M16:M21) -> 5917366 | N15: =SUM(N16:N21) -> 0 | O15: =SUM(O16:O21) -> 5917366 | P15: =SUM(P16:P21) -> 0 | ... AS15: =SUM(AS16:AS21) -> 7534385
B16: 1.1.1 | C16: Buen manejo de anticipo | D16: 1 | E16: glb | F16: 3512790.2 | G16: =+D16*F16 -> 3512790.2 | I16: =(O16+T16+Y16+AD16+AI16+AN16) -> 516713.12 | J16: 516713.12 | M16: 516713.12 | O16: =SUM(K16:N16) -> 516713.12 | T16: =SUM(P16:S16) -> 0 | Y16: =SUM(U16:X16) -> 0 | AD16: =SUM(Z16:AC16) -> 0 | AI16: =SUM(AE16:AH16) -> 0 | AN16: =SUM(AJ16:AM16) -> 0 | AR16: 1328123 | AS16: =SUM(AO16:AR16) -> 1328123
B17: 1.1.2 | C17: Cumplimiento | D17: 1 | E17: glb | F17: 3073691.4 | G17: =+D17*F17 -> 3073691.4 | I17: =(O17+T17+Y17+AD17+AI17+AN17) -> 465741.43 | J17: 465741.43 | M17: 465741.43 | O17: =SUM(K17:N17) -> 465741.43 | T17: =SUM(P17:S17) -> 0 | Y17: =SUM(U17:X17) -> 0 | AD17: =SUM(Z17:AC17) -> 0 | AI17: =SUM(AE17:AH17) -> 0 | AN17: =SUM(AJ17:AM17) -> 0 | AR17: 444632 | AS17: =SUM(AO17:AR17) -> 444632
B18: 1.1.3 | C18: Salarios y prestaciones sociales | D18: 1 | E18: glb | F18: 2049127.6 | G18: =+D18*F18 -> 2049127.6 | I18: =(O18+T18+Y18+AD18+AI18+AN18) -> 349306.07 | J18: 349306.07 | M18: 349306.07 | O18: =SUM(K18:N18) -> 349306.07 | T18: =SUM(P18:S18) -> 0 | Y18: =SUM(U18:X18) -> 0 | AD18: =SUM(Z18:AC18) -> 0 | AI18: =SUM(AE18:AH18) -> 0 | AN18: =SUM(AJ18:AM18) -> 0 | AR18: 262737 | AS18: =SUM(AO18:AR18) -> 262737
B19: 1.1.4 | C19: Estabilidad de obra | D19: 1 | E19: glb | F19: 3073691.4 | G19: =+D19*F19 -> 3073691.4 | I19: =(O19+T19+Y19+AD19+AI19+AN19) -> 4184037.9 | J19: 4184037.9 | M19: 4184037.9 | O19: =SUM(K19:N19) -> 4184037.9 | T19: =SUM(P19:S19) -> 0 | Y19: =SUM(U19:X19) -> 0 | AD19: =SUM(Z19:AC19) -> 0 | AI19: =SUM(AE19:AH19) -> 0 | AN19: =SUM(AJ19:AM19) -> 0 | AR19: 3695647 | AS19: =SUM(AO19:AR19) -> 3695647
B20: 1.1.5 | C20: Calidad de obra | D20: 1 | E20: glb | F20: 3073691.4 | G20: =+D20*F20 -> 3073691.4 | I20: =(O20+T20+Y20+AD20+AI20+AN20) -> 9282 | J20: 9282 | M20: 9282 | O20: =SUM(K20:N20) -> 9282 | T20: =SUM(P20:S20) -> 0 | Y20: =SUM(U20:X20) -> 0 | AD20: =SUM(Z20:AC20) -> 0 | AI20: =SUM(AE20:AH20) -> 0 | AN20: =SUM(AJ20:AM20) -> 0 | AR20: 1212969 | AS20: =SUM(AO20:AR20) -> 1212969
B21: 1.1.6 | C21: Responsabilidad civil extracontractural | D21: 1 | E21: glb | F21: 3512790.2 | G21: =+D21*F21 -> 3512790.2 | I21: =(O21+T21+Y21+AD21+AI21+AN21) -> 392285.52 | J21: =197018.52+195267 -> 392285.52 | M21: =197018.52+195267 -> 392285.52 | O21: =SUM(K21:N21) -> 392285.52 | T21: =SUM(P21:S21) -> 0 | Y21: =SUM(U21:X21) -> 0 | AD21: =SUM(Z21:AC21) -> 0 | AI21: =SUM(AE21:AH21) -> 0 | AN21: =SUM(AJ21:AM21) -> 0 | AR21: 590277 | AS21: =SUM(AO21:AR21) -> 590277
B22: 1.2. | C22: Impuestos | G22: =SUM(G23:G25) -> 48300865 | I22: =SUM(I23:I25) -> 0 | J22: =SUM(J23:J25) -> 48300863 | K22: =SUM(K23:K25) -> 0 | L22: =SUM(L23:L25) -> 0 | M22: =SUM(M23:M25) -> 0 | N22: =SUM(N23:N25) -> 0 | O22: =SUM(O23:O25) -> 0 | P22: =SUM(P23:P25) -> 0 | ... AS22: =SUM(AS23:AS25) -> 48300865
B23: 1.2.1 | C23: FIC | D23: 1 | E23: glb | F23: 7318312.9 | G23: =+D23*F23 -> 7318312.9 | I23: =(O23+T23+Y23+AD23+AI23+AN23) -> 0 | J23: 7318312 | O23: =SUM(K23:N23) -> 0 | T23: =SUM(P23:S23) -> 0 | Y23: =SUM(U23:X23) -> 0 | AD23: =SUM(Z23:AC23) -> 0 | AI23: =SUM(AE23:AH23) -> 0 | AN23: =SUM(AJ23:AM23) -> 0 | AP23: 7318312.9 | AS23: =SUM(AO23:AR23) -> 7318312.9
B24: 1.2.2 | C24: ICA | D24: 1 | E24: glb | F24: 29273252 | G24: =+D24*F24 -> 29273252 | I24: =(O24+T24+Y24+AD24+AI24+AN24) -> 0 | J24: 29273251 | O24: =SUM(K24:N24) -> 0 | T24: =SUM(P24:S24) -> 0 | Y24: =SUM(U24:X24) -> 0 | AD24: =SUM(Z24:AC24) -> 0 | AI24: =SUM(AE24:AH24) -> 0 | AN24: =SUM(AJ24:AM24) -> 0 | AP24: 29273252 | AS24: =SUM(AO24:AR24) -> 29273252
B25: 1.2.3 | C25: Cuatro por 1000 | D25: 1 | E25: glb | F25: 11709301 | G25: =+D25*F25 -> 11709301 | I25: =(O25+T25+Y25+AD25+AI25+AN25) -> 0 | J25: 11709300 | O25: =SUM(K25:N25) -> 0 | T25: =SUM(P25:S25) -> 0 | Y25: =SUM(U25:X25) -> 0 | AD25: =SUM(Z25:AC25) -> 0 | AI25: =SUM(AE25:AH25) -> 0 | AN25: =SUM(AJ25:AM25) -> 0 | AP25: 11709301 | AS25: =SUM(AO25:AR25) -> 11709301
B26: 1.3 | C26: Personal administración | G26: =G27 -> 24640000 | I26: =SUM(I27:I28) -> 34339945 | J26: =SUM(J27:J28) -> 10450000 | K26: =SUM(K27:K28) -> 0 | L26: =SUM(L27:L28) -> 0 | M26: =SUM(M27:M28) -> 0 | N26: =SUM(N27:N28) -> 2435886 | O26: =SUM(O27:O28) -> 2435886 | P26: =SUM(P27:P28) -> 0 | ... AS26: =SUM(AS27:AS28) -> 4273295
B27: 1.3.1 | C27: Profesional de calidad 100% | D27: 4 | E27: mes | F27: 6160000 | G27: =+D27*F27 -> 24640000 | I27: =(O27+T27+Y27+AD27+AI27+AN27) -> 17089945 | J27: 7000000 | N27: 2435886 | O27: =SUM(K27:N27) -> 2435886 | S27: 6915382 | T27: =SUM(P27:S27) -> 6915382 | X27: 6915382 | Y27: =SUM(U27:X27) -> 6915382 | AD27: =SUM(Z27:AC27) -> 0 | AI27: =SUM(AE27:AH27) -> 0 | AM27: 823295 | AN27: =SUM(AJ27:AM27) -> 823295 | AR27: 823295 | AS27: =SUM(AO27:AR27) -> 823295
B28: 1.3.2 | C28: Residente administrativo | D28: 4 | E28: mes | F28: =2300000*1.5 -> 3450000 | G28: =F28*D28 -> 13800000 | I28: =(O28+T28+Y28+AD28+AI28+AN28) -> 17250000 | J28: =2300000*1.5 -> 3450000 | O28: =SUM(K28:N28) -> 0 | S28: 3450000 | T28: =SUM(P28:S28) -> 3450000 | X28: =2300000*1.5 -> 3450000 | Y28: =SUM(U28:X28) -> 3450000 | AC28: =2300000*1.5 -> 3450000 | AD28: =SUM(Z28:AC28) -> 3450000 | AH28: =2300000*1.5 -> 3450000 | AI28: =SUM(AE28:AH28) -> 3450000 | AM28: =2300000*1.5 -> 3450000 | AN28: =SUM(AJ28:AM28) -> 3450000 | AR28: =2300000*1.5 -> 3450000 | AS28: =SUM(AO28:AR28) -> 3450000
B29: 1.4 | C29: Campamentos, protecciones e insumos de obra | G29: =SUM(G30:G38) -> 750834.4 | I29: =SUM(I30:I38) -> 661557 | J29: =SUM(J30:J38) -> 661557 | K29: =SUM(K30:K38) -> 0 | L29: =SUM(L30:L38) -> 0 | M29: =SUM(M30:M38) -> 0 | N29: =SUM(N30:N38) -> 661557 | O29: =SUM(O30:O38) -> 661557 | P29: =SUM(P30:P38) -> 0 | ... AS29: =SUM(AS30:AS38) -> 0
B30: 1.4.1 | C30: Kit señalización para campamentos (hasta 120 m2) | D30: 3 | E30: und | F30: 125384.3 | G30: =+D30*F30 -> 376152.9 | I30: =(O30+T30+Y30+AD30+AI30+AN30) -> 150000 | J30: 150000 | N30: 150000 | O30: =SUM(K30:N30) -> 150000 | T30: =SUM(P30:S30) -> 0 | Y30: =SUM(U30:X30) -> 0 | AD30: =SUM(Z30:AC30) -> 0 | AI30: =SUM(AE30:AH30) -> 0 | AN30: =SUM(AJ30:AM30) -> 0 | AS30: =SUM(AO30:AR30) -> 0
B31: 1.4.2 | C31: Cascos de seguridad | D31: 1 | E31: und | F31: 17867 | G31: =+D31*F31 -> 17867 | I31: =(O31+T31+Y31+AD31+AI31+AN31) -> 17850 | J31: 17850 | N31: 17850 | O31: =SUM(K31:N31) -> 17850 | T31: =SUM(P31:S31) -> 0 | Y31: =SUM(U31:X31) -> 0 | AD31: =SUM(Z31:AC31) -> 0 | AI31: =SUM(AE31:AH31) -> 0 | AN31: =SUM(AJ31:AM31) -> 0 | AS31: =SUM(AO31:AR31) -> 0
B32: 1.4.3 | C32: Protección auditiva | D32: 3 | E32: und | F32: 2627.5 | G32: =+D32*F32 -> 7882.5 | I32: =(O32+T32+Y32+AD32+AI32+AN32) -> 4341 | J32: 4341 | N32: 4341 | O32: =SUM(K32:N32) -> 4341 | T32: =SUM(P32:S32) -> 0 | Y32: =SUM(U32:X32) -> 0 | AD32: =SUM(Z32:AC32) -> 0 | AI32: =SUM(AE32:AH32) -> 0 | AN32: =SUM(AJ32:AM32) -> 0 | AS32: =SUM(AO32:AR32) -> 0
B33: 1.4.4 | C33: Guantes de nitrilo | D33: 3 | E33: und | F33: 5780.5 | G33: =+D33*F33 -> 17341.5 | I33: =(O33+T33+Y33+AD33+AI33+AN33) -> 23324 | J33: 23324 | N33: 23324 | O33: =SUM(K33:N33) -> 23324 | T33: =SUM(P33:S33) -> 0 | Y33: =SUM(U33:X33) -> 0 | AD33: =SUM(Z33:AC33) -> 0 | AI33: =SUM(AE33:AH33) -> 0 | AN33: =SUM(AJ33:AM33) -> 0 | AS33: =SUM(AO33:AR33) -> 0
B34: 1.4.5 | C34: Par de botas de agua | D34: 1 | E34: und | F34: 72519 | G34: =+D34*F34 -> 72519 | I34: =(O34+T34+Y34+AD34+AI34+AN34) -> 66640 | J34: 66640 | N34: 66640 | O34: =SUM(K34:N34) -> 66640 | T34: =SUM(P34:S34) -> 0 | Y34: =SUM(U34:X34) -> 0 | AD34: =SUM(Z34:AC34) -> 0 | AI34: =SUM(AE34:AH34) -> 0 | AN34: =SUM(AJ34:AM34) -> 0 | AS34: =SUM(AO34:AR34) -> 0
B35: 1.4.6 | C35: Par de botas de seguridad | D35: 1 | E35: und | F35: 118763 | G35: =+D35*F35 -> 118763 | I35: =(O35+T35+Y35+AD35+AI35+AN35) -> 116739 | J35: 116739 | N35: 116739 | O35: =SUM(K35:N35) -> 116739 | T35: =SUM(P35:S35) -> 0 | Y35: =SUM(U35:X35) -> 0 | AD35: =SUM(Z35:AC35) -> 0 | AI35: =SUM(AE35:AH35) -> 0 | AN35: =SUM(AJ35:AM35) -> 0 | AS35: =SUM(AO35:AR35) -> 0
B36: 1.4.7 | C36: Gafas de seguridad | D36: 3 | E36: und | F36: 3678.5 | G36: =+D36*F36 -> 11035.5 | I36: =(O36+T36+Y36+AD36+AI36+AN36) -> 14756 | J36: 14756 | N36: 14756 | O36: =SUM(K36:N36) -> 14756 | T36: =SUM(P36:S36) -> 0 | Y36: =SUM(U36:X36) -> 0 | AD36: =SUM(Z36:AC36) -> 0 | AI36: =SUM(AE36:AH36) -> 0 | AN36: =SUM(AJ36:AM36) -> 0 | AS36: =SUM(AO36:AR36) -> 0
B37: 1.4.8 | C37: Chalecos reflectivos | D37: 1 | E37: und | F37: 78825 | G37: =+D37*F37 -> 78825 | I37: =(O37+T37+Y37+AD37+AI37+AN37) -> 81037 | J37: 81037 | N37: 81037 | O37: =SUM(K37:N37) -> 81037 | T37: =SUM(P37:S37) -> 0 | Y37: =SUM(U37:X37) -> 0 | AD37: =SUM(Z37:AC37) -> 0 | AI37: =SUM(AE37:AH37) -> 0 | AN37: =SUM(AJ37:AM37) -> 0 | AS37: =SUM(AO37:AR37) -> 0
B38: 1.4.9 | C38: Overoles | D38: 1 | E38: und | F38: 50448 | G38: =+D38*F38 -> 50448 | I38: =(O38+T38+Y38+AD38+AI38+AN38) -> 186870 | J38: 186870 | N38: 186870 | O38: =SUM(K38:N38) -> 186870 | T38: =SUM(P38:S38) -> 0 | Y38: =SUM(U38:X38) -> 0 | AD38: =SUM(Z38:AC38) -> 0 | AI38: =SUM(AE38:AH38) -> 0 | AN38: =SUM(AJ38:AM38) -> 0 | AS38: =SUM(AO38:AR38) -> 0
B39: 1.5 | C39: G.C. | D39: =SUM(D40) -> 1 | E39: =SUM(E40) -> 0 | F39: =SUM(F40) -> 58546503 | G39: =SUM(G40) -> 58546503 | I39: =SUM(I40) -> 58546503 | J39: =SUM(J40) -> 58546503 | K39: =SUM(K40) -> 0 | L39: =SUM(L40) -> 0 | M39: =SUM(M40) -> 58546503 | N39: =SUM(N40) -> 0 | O39: =SUM(O40) -> 58546503 | P39: =SUM(P40) -> 0 | ... AS39: =SUM(AS40) -> 0
B40: 1.5.1 | C40: TRANSPORTES | D40: 1 | E40: glb | F40: 58546503 | G40: =+D40*F40 -> 58546503 | I40: =(O40+T40+Y40+AD40+AI40+AN40) -> 58546503 | J40: 58546503 | M40: 58546503 | O40: =SUM(K40:N40) -> 58546503 | T40: =SUM(P40:S40) -> 0 | Y40: =SUM(U40:X40) -> 0 | AD40: =SUM(Z40:AC40) -> 0 | AI40: =SUM(AE40:AH40) -> 0 | AN40: =SUM(AJ40:AM40) -> 0 | AS40: =SUM(AO40:AR40) -> 0
B41: 3 | C41: Viaticos | G41: =G42 -> 0 | I41: =I42 -> 17881010 | J41: =J42 -> 4200000 | K41: =K42 -> 0 | L41: =L42 -> 0 | M41: =M42 -> 0 | N41: =N42 -> 0 | O41: =O42 -> 0 | P41: =P42 -> 1497410 | ... AS41: =AS42 -> 4716200
B42: 3.1 | C42: Viaticos | G42: =SUM(G43:G46) -> 0 | I42: =SUM(I43:I46) -> 17881010 | J42: =SUM(J43:J46) -> 4200000 | K42: =SUM(K43:K46) -> 0 | L42: =SUM(L43:L46) -> 0 | M42: =SUM(M43:M46) -> 0 | N42: =SUM(N43:N46) -> 0 | O42: =SUM(O43:O46) -> 0 | P42: =SUM(P43:P46) -> 1497410 | ... AS42: =SUM(AS43:AS46) -> 4716200
B43: 3.1.1 | C43: Hospedaje | I43: =(O43+T43+Y43+AD43+AI43+AN43) -> 9048000 | J43: 1237600 | O43: =SUM(K43:N43) -> 0 | P43: 500000 | T43: =SUM(P43:S43) -> 500000 | V43: 1348000 | Y43: =SUM(U43:X43) -> 1348000 | AB43: 2400000 | AD43: =SUM(Z43:AC43) -> 2400000 | AG43: 2400000 | AI43: =SUM(AE43:AH43) -> 2400000 | AL43: 2400000 | AN43: =SUM(AJ43:AM43) -> 2400000 | AQ43: 2400000 | AS43: =SUM(AO43:AR43) -> 2400000
B44: 3.1.2 | C44: Transportes | I44: =(O44+T44+Y44+AD44+AI44+AN44) -> 586500 | J44: 292400 | O44: =SUM(K44:N44) -> 0 | P44: 147900 | T44: =SUM(P44:S44) -> 147900 | Y44: =SUM(U44:X44) -> 0 | AB44: 146200 | AD44: =SUM(Z44:AC44) -> 146200 | AG44: 146200 | AI44: =SUM(AE44:AH44) -> 146200 | AL44: 146200 | AN44: =SUM(AJ44:AM44) -> 146200 | AQ44: 146200 | AS44: =SUM(AO44:AR44) -> 146200
B45: 3.1.3 | C45: Pasajes | I45: =(O45+T45+Y45+AD45+AI45+AN45) -> 1539510 | J45: 2190000 | O45: =SUM(K45:N45) -> 0 | P45: 609510 | T45: =SUM(P45:S45) -> 609510 | Y45: =SUM(U45:X45) -> 0 | AB45: 310000 | AD45: =SUM(Z45:AC45) -> 310000 | AG45: 310000 | AI45: =SUM(AE45:AH45) -> 310000 | AL45: 310000 | AN45: =SUM(AJ45:AM45) -> 310000 | AQ45: 310000 | AS45: =SUM(AO45:AR45) -> 310000
B46: 3.1.4 | C46: Alimentacion | I46: =(O46+T46+Y46+AD46+AI46+AN46) -> 6707000 | J46: 480000 | O46: =SUM(K46:N46) -> 0 | P46: 240000 | T46: =SUM(P46:S46) -> 240000 | V46: 887000 | Y46: =SUM(U46:X46) -> 887000 | AB46: 1860000 | AD46: =SUM(Z46:AC46) -> 1860000 | AG46: 1860000 | AI46: =SUM(AE46:AH46) -> 1860000 | AL46: 1860000 | AN46: =SUM(AJ46:AM46) -> 1860000 | AQ46: 1860000 | AS46: =SUM(AO46:AR46) -> 1860000
B47: 4 | C47: INGENIERÍA | G47: =G48 -> 0 | I47: =I48 -> 11448636 | J47: =J48 -> 11448635 | K47: =K48 -> 0 | L47: =L48 -> 0 | M47: =M48 -> 0 | N47: =N48 -> 0 | O47: =O48 -> 0 | P47: =P48 -> 0 | ... AS47: =AS48 -> 0
B48: 4.1 | C48: Ingenieria de taller | G48: =G49 -> 0 | I48: =I49 -> 11448636 | J48: =J49 -> 11448635 | K48: =K49 -> 0 | L48: =L49 -> 0 | M48: =M49 -> 0 | N48: =N49 -> 0 | O48: =O49 -> 0 | P48: =P49 -> 0 | ... AS48: =AS49 -> 0
B49: 4.1.1 | C49: Ingenieria de taller | I49: =(O49+T49+Y49+AD49+AI49+AN49) -> 11448636 | J49: 11448635 | O49: =SUM(K49:N49) -> 0 | T49: =SUM(P49:S49) -> 0 | Y49: =SUM(U49:X49) -> 0 | AD49: =SUM(Z49:AC49) -> 0 | AF49: 5724317.5 | AH49: 5724318 | AI49: =SUM(AE49:AH49) -> 11448636 | AN49: =SUM(AJ49:AM49) -> 0 | AS49: =SUM(AO49:AR49) -> 0
B50: 5 | C50: Suministros | G50: =SUM(G51) -> 0 | I50: =SUM(I51) -> 2.4344444e+08 | J50: =SUM(J51) -> 2045743.3 | K50: =SUM(K51) -> 0 | L50: =SUM(L51) -> 0 | M50: =SUM(M51) -> 0 | N50: =SUM(N51) -> 0 | O50: =SUM(O51) -> 0 | P50: =SUM(P51) -> 0 | ... AS50: =SUM(AS51) -> 0
B51: 5.1 | C51: PINTURA | G51: =G53 -> 0 | I51: =I52+I56 -> 2.4344444e+08 | J51: =J52+J56 -> 2045743.3 | K51: =K52+K56 -> 0 | L51: =L52+L56 -> 0 | M51: =M52+M56 -> 0 | N51: =N52+N56 -> 0 | O51: =O52+O56 -> 0 | P51: =P52+P56 -> 0 | ... AS51: =AS52+AS56 -> 0
B52: 5.1.1 | C52: Epoxico | I52: =SUM(I53:I55) -> 93907565 | J52: =SUM(J53:J55) -> 866096.28 | K52: =SUM(K53:K55) -> 0 | L52: =SUM(L53:L55) -> 0 | M52: =SUM(M53:M55) -> 0 | N52: =SUM(N53:N55) -> 0 | O52: =SUM(O53:O55) -> 0 | P52: =SUM(P53:P55) -> 0 | ... AS52: =SUM(AS53:AS55) -> 0
B53: 5.1.1.1 | C53: Anticorrosivo epoxico x cuñete | D53: 136 | E53: Cuñetes | I53: =(O53+T53+Y53+AD53+AI53+AN53)*J53 -> 91167061 | J53: =563316*1.19 -> 670346.04 | O53: =SUM(K53:N53) -> 0 | Q53: 43 | S53: 93 | T53: =SUM(P53:S53) -> 136 | Y53: =SUM(U53:X53) -> 0 | AD53: =SUM(Z53:AC53) -> 0 | AI53: =SUM(AE53:AH53) -> 0 | AN53: =SUM(AJ53:AM53) -> 0 | AS53: =SUM(AO53:AR53) -> 0
B54: 5.1.1.2 | C54: Catalizador | I54: =(O54+T54+Y54+AD54+AI54+AN54)*J54 -> 0 | O54: =SUM(K54:N54) -> 0 | T54: =SUM(P54:S54) -> 0 | Y54: =SUM(U54:X54) -> 0 | AD54: =SUM(Z54:AC54) -> 0 | AI54: =SUM(AE54:AH54) -> 0 | AN54: =SUM(AJ54:AM54) -> 0 | AS54: =SUM(AO54:AR54) -> 0
B55: 5.1.1.3 | C55: Disolvente epoxicco cuñete | D55: 13 | E55: Cuñetes | I55: =(O55+T55+Y55+AD55+AI55+AN55)*J55 -> 2740503.4 | J55: =164496*1.19 -> 195750.24 | O55: =SUM(K55:N55) -> 0 | Q55: 5 | S55: 9 | T55: =SUM(P55:S55) -> 14 | Y55: =SUM(U55:X55) -> 0 | AD55: =SUM(Z55:AC55) -> 0 | AI55: =SUM(AE55:AH55) -> 0 | AN55: =SUM(AJ55:AM55) -> 0 | AS55: =SUM(AO55:AR55) -> 0
B56: 5.1.2 | C56: Pintura | I56: =SUM(I57:I59) -> 1.4953687e+08 | J56: =SUM(J57:J59) -> 1179647 | K56: =SUM(K57:K59) -> 0 | L56: =SUM(L57:L59) -> 0 | M56: =SUM(M57:M59) -> 0 | N56: =SUM(N57:N59) -> 0 | O56: =SUM(O57:O59) -> 0 | P56: =SUM(P57:P59) -> 0 | ... AS56: =SUM(AS57:AS59) -> 0
B57: 5.1.2.1 | C57: Esmalte Urretano | D57: 149 | E57: Cuñetes | I57: =(O57+T57+Y57+AD57+AI57+AN57)*J57 -> 1.4660062e+08 | J57: =826804*1.19 -> 983896.76 | O57: =SUM(K57:N57) -> 0 | T57: =SUM(P57:S57) -> 0 | Y57: =SUM(U57:X57) -> 0 | AA57: 149 | AD57: =SUM(Z57:AC57) -> 149 | AI57: =SUM(AE57:AH57) -> 0 | AN57: =SUM(AJ57:AM57) -> 0 | AS57: =SUM(AO57:AR57) -> 0
B58: 5.1.2.2 | C58: Catalizador Urretano | I58: =(O58+T58+Y58+AD58+AI58+AN58)*J58 -> 0 | O58: =SUM(K58:N58) -> 0 | T58: =SUM(P58:S58) -> 0 | Y58: =SUM(U58:X58) -> 0 | AD58: =SUM(Z58:AC58) -> 0 | AI58: =SUM(AE58:AH58) -> 0 | AN58: =SUM(AJ58:AM58) -> 0 | AS58: =SUM(AO58:AR58) -> 0
B59: 5.1.2.3 | C59: Solvente Uretano | D59: 15 | E59: Cuñetes | I59: =(O59+T59+Y59+AD59+AI59+AN59)*J59 -> 2936253.6 | J59: =164496*1.19 -> 195750.24 | O59: =SUM(K59:N59) -> 0 | T59: =SUM(P59:S59) -> 0 | Y59: =SUM(U59:X59) -> 0 | AA59: 15 | AD59: =SUM(Z59:AC59) -> 15 | AI59: =SUM(AE59:AH59) -> 0 | AN59: =SUM(AJ59:AM59) -> 0 | AS59: =SUM(AO59:AR59) -> 0
B60: 6 | C60: Mano de obra | G60: =SUM(G61) -> #REF! | I60: =SUM(I61) -> 2.4196446e+09 | J60: =SUM(J61) -> 9025.4277 | K60: =SUM(K61) -> 0 | L60: =SUM(L61) -> 0 | M60: =SUM(M61) -> 0 | N60: =SUM(N61) -> 0 | O60: =SUM(O61) -> 0 | P60: =SUM(P61) -> 0 | ... AS60: =SUM(AS61) -> 179678 | AU60: =AS60+AN60+AI60+AD60+Y60+T60 -> 529999.6
B61: 6.1 | C61: Fabricación de EEMM | G61: =#REF! -> #REF! | I61: =SUM(I62:I63) -> 2.4196446e+09 | J61: =SUM(J62:J63) -> 9025.4277 | K61: =SUM(K62:K63) -> 0 | L61: =SUM(L62:L63) -> 0 | M61: =SUM(M62:M63) -> 0 | N61: =SUM(N62:N63) -> 0 | O61: =SUM(O62:O63) -> 0 | P61: =SUM(P62:P63) -> 0 | ... AS61: =SUM(AS62:AS63) -> 179678
B62: 6.1.1. | C62: Proveedor 1 | D62: =O62+T62+Y62+AD62+AI62+AN62 -> 185262.6 | I62: =(O62+T62+Y62+AD62+AI62+AN62+AS62)*J62 -> 8.0361615e+08 | J62: 4337.7139 | O62: =SUM(K62:N62) -> 0 | P62: 0 | Q62: 5072.4 | R62: 9583 | S62: 17682.2 | T62: =SUM(P62:S62) -> 32337.6 | V62: 11678 | W62: 17785 | X62: 6305 | Y62: =SUM(U62:X62) -> 35768 | Z62: 10678 | AA62: 5287 | AB62: 14738 | AC62: 25000 | AD62: =SUM(Z62:AC62) -> 55703 | AF62: 30200 | AH62: 31254 | AI62: =SUM(AE62:AH62) -> 61454 | AN62: =SUM(AJ62:AM62) -> 0 | AS62: =SUM(AO62:AR62) -> 0
B63: 6.1.2. | C63: Proveedor 2 | I63: =(O63+T63+Y63+AD63+AI63+AN63+AS63)*J63 -> 1.6160284e+09 | J63: =J62+350 -> 4687.7139 | T63: =SUM(P63:S63) -> 0 | Y63: =SUM(U63:X63) -> 0 | AD63: =SUM(Z63:AC63) -> 0 | AI63: =SUM(AE63:AH63) -> 0 | AK63: 85059 | AM63: 80000 | AN63: =SUM(AJ63:AM63) -> 165059 | AO63: 90000 | AP63: 89678 | AS63: =SUM(AO63:AR63) -> 179678
C66: Totales | F66: =F53*D53 -> 0 | G66: =G60+G50+G47+G41+G14 -> #REF! | I66: =I60+I50+I47+I41+I14 -> 2.791884e+09 | K66: =(K60*#REF!)+(K53*$J$53)+(K54*$J$54)+(K55*$J$55)+(K57*$J$57)+(K58*$J$58)+(K59*$J$59)+K47+K41+K14 -> #REF! | L66: =(L60*#REF!)+(L53*$J$53)+(L54*$J$54)+(L55*$J$55)+(L57*$J$57)+(L58*$J$58)+(L59*$J$59)+L47+L41+L14 -> #REF! | M66: =(M60*#REF!)+(M53*$J$53)+(M54*$J$54)+(M55*$J$55)+(M57*$J$57)+(M58*$J$58)+(M59*$J$59)+M47+M41+M14 -> #REF! | N66: =(N60*#REF!)+(N53*$J$53)+(N54*$J$54)+(N55*$J$55)+(N57*$J$57)+(N58*$J$58)+(N59*$J$59)+N47+N41+N14 -> #REF! | O66: =(O60*#REF!)+(O53*$J$53)+(O54*$J$54)+(O55*$J$55)+(O57*$J$57)+(O58*$J$58)+(O59*$J$59)+O47+O41+O14 -> #REF! | P66: =(P60*#REF!)+(P53*$J$53)+(P54*$J$54)+(P55*$J$55)+(P57*$J$57)+(P58*$J$58)+(P59*$J$59)+P47+P41+P14 -> #REF! | Q66: =(Q60*#REF!)+(Q53*$J$53)+(Q54*$J$54)+(Q55*$J$55)+(Q57*$J$57)+(Q58*$J$58)+(Q59*$J$59)+Q47+Q41+Q14 -> #REF! | R66: =(R60*#REF!)+(R53*$J$53)+(R54*$J$54)+(R55*$J$55)+(R57*$J$57)+(R58*$J$58)+(R59*$J$59)+R47+R41+R14 -> #REF! | ... U66: =(U60*#REF!)+(U53*$J$53)+(U54*$J$54)+(U55*$J$55)+(U57*$J$57)+(U58*$J$58)+(U59*$J$59)+U47+U41+U14 -> #REF! | V66: =(V60*#REF!)+(V53*$J$53)+(V54*$J$54)+(V55*$J$55)+(AA57*$J$57)+(AA58*$J$58)+(AA59*$J$59)+V47+V41+V14 -> #REF! | W66: =(W60*#REF!)+(W53*$J$53)+(W54*$J$54)+(W55*$J$55)+(W57*$J$57)+(W58*$J$58)+(W59*$J$59)+W47+W41+W14 -> #REF! | X66: =(X60*#REF!)+(X53*$J$53)+(X54*$J$54)+(X55*$J$55)+(X57*$J$57)+(X58*$J$58)+(X59*$J$59)+X47+X41+X14 -> #REF! | Y66: =(Y60*#REF!)+(Y53*$J$53)+(Y54*$J$54)+(Y55*$J$55)+(Y57*$J$57)+(Y58*$J$58)+(Y59*$J$59)+Y47+Y41+Y14 -> #REF! | Z66: =(Z60*#REF!)+(Z53*$J$53)+(Z54*$J$54)+(Z55*$J$55)+(Z57*$J$57)+(Z58*$J$58)+(Z59*$J$59)+Z47+Z41+Z14 -> #REF! | AA66: =(AA60*#REF!)+(AA53*$J$53)+(AA54*$J$54)+(AA55*$J$55)+(#REF!*$J$57)+(#REF!*$J$58)+(#REF!*$J$59)+AA47+AA41+AA14 -> #REF! | AB66: =(AB60*#REF!)+(AB53*$J$53)+(AB54*$J$54)+(AB55*$J$55)+(AB57*$J$57)+(AB58*$J$58)+(AB59*$J$59)+AB47+AB41+AB14 -> #REF!
B75: OPC 1
B76: Costo | C76: 3824.47
B77: A | C77: =C76*6.42% -> 245.53097 | G77: =SUM(C77:C79)/C76 -> 0.1342
B78: I | C78: =C76*2% -> 76.4894
B79: U | C79: =C76*5% -> 191.2235
B80: IVA | C80: =C79*19% -> 36.332465
B81: Total | C81: =SUM(C76:C80) -> 4374.0463 | D81: 530000 | E81: =C81*D81 -> 2.3182446e+09
B83: Costo | C83: 3970.41
B84: A | C84: 254.9
B85: I | C85: 79.41
B86: U | C86: 198.52
B87: IVA | C87: =C86*19% -> 37.7188
B88: Total | C88: =SUM(C83:C87) -> 4540.9588 | D88: 530000 | E88: =C88*D88 -> 2.4067082e+09
L104: Anticipo | P104: Corte avance (2 semanas) 50 ton pago en 30 días | R104: Corte avance (2 semanas) 50 ton pago en 30 días | U104: Corte avance (2 semanas) 50 ton pago en 30 días | W104: Corte avance (2 semanas) 50 ton pago en 30 días | Z104: Corte avance (2 semanas) 50 ton pago en 30 días | AB104: Corte avance entrega final 30 ton pago en 30 días
J105: 530000 | L105: 151169.52 | P105: 50000 | S105: 50000 | U105: 88000 | W105: 88000 | Z105: 88000 | AB105: 14830.48 | AE105: 64869261
J106: =J105*#REF! -> #REF! | L106: =L105*#REF! -> #REF! | P106: =P105*#REF! -> #REF! | S106: =S105*#REF! -> #REF! | U106: =U105*#REF! -> #REF! | W106: =W105*#REF! -> #REF! | Z106: =W106 -> #REF! | AB106: =AB105*#REF! -> #REF!

Sheet REAL
I5: =I12 -> 8 | J5: =J12 -> 9 | K5: =K12 -> 10 | L5: =L12 -> 11 | M5: =M12 -> 12 | N5: =N12 -> 13 | O5: =O12 -> 14 | P5: =P12 -> 15 | ... AS5: =AS12 -> 44
I6: Valor total | J6: Valor Unitario | K6: semana 1 | L6: semana 2 | M6: semana 3 | N6: semana 4 | O6: Total Abril 2026 | P6: semana 5 | Q6: semana 6 | R6: semana 7 | S6: semana 8 | T6: Total mayo 2026 | U6: semana 9 | V6: semana 10 | W6: semana 11 | X6: semana 12 | Y6: Total junio 2026 | Z6: semana 13 | AA6: semana 14 | AB6: semana 15 | AC6: semana 16 | AD6: Total julio 2026 | AE6: semana 17 | AF6: semana 18 | AG6: semana 19 | AH6: semana 20 | AI6: Total Agosto 2026 | AJ6: semana 17 | AK6: semana 18 | AL6: semana 19 | AM6: semana 20 | AN6: Total Septiembre 2026 | AO6: semana 17 | AP6: semana 18 | AQ6: semana 19 | AR6: semana 20 | AS6: Total oCTUBRE 2026
C7: % DE FACTURACIÓN | D7: 530000 | E7: Kg | F7: 4753.95 | G7: =+D7*F7 -> 2519593500 | H7: Toneladas | O7: =SUM(K7:N7) -> 0 | S7: 0 | T7: =SUM(P7:S7) -> 0 | W7: 54616.82 | Y7: =SUM(U7:X7) -> 54616.82 | AA7: 29594.551 | AB7: 25521.409 | AD7: =SUM(Z7:AC7) -> 55115.96 | AE7: 31010.073 | AG7: 27561.386 | AI7: =SUM(AE7:AH7) -> 58571.459 | AJ7: 31254 | AN7: =SUM(AJ7:AM7) -> 31254 | AS7: =SUM(AO7:AR7) -> 0
H8: Precio | I8: =(O8+T8+Y8+AD8+AI8+AN8)-O8 -> 1.1021602e+09 | J8: 5523 | M8: 870811200 | O8: =M8 -> 870811200 | P8: =$J$8*P7 -> 0 | Q8: =$J$8*Q7 -> 0 | R8: =$J$8*R7 -> 0 | S8: =$J$8*S7 -> 0 | T8: =$J$8*T7 -> 0 | U8: =$J$8*U7 -> 0 | V8: =$J$8*V7 -> 0 | W8: =$J$8*W7 -> 3.016487e+08 | ... AS8: =$J$8*AS7 -> 0
B12: 1 | C12: 2 | D12: 3 | E12: 4 | F12: 5 | G12: 6 | H12: 7 | I12: 8 | J12: 9 | K12: 10 | L12: 11 | M12: 12 | N12: 13 | O12: 14 | P12: 15 | Q12: 16 | R12: 17 | S12: 18 | T12: 19 | U12: 20 | V12: 21 | W12: 22 | X12: 23 | Y12: 24 | Z12: 25 | AA12: 26 | AB12: 27 | AC12: 28 | AD12: 29 | AE12: 30 | AF12: 31 | AG12: 32 | AH12: 33 | AI12: 34 | AJ12: 35 | AK12: 36 | AL12: 37 | AM12: 38 | AN12: 39 | AO12: 40 | AP12: 41 | AQ12: 42 | AR12: 43 | AS12: 44
B13: Código | C13: ITEM | D13: Cantidad+desp. | E13: Unidad de medida | F13: Valor Unitario | G13: Total presupuesto | I13: Valor total | J13: Valor Unitario | K13: semana 1 | L13: semana 2 | M13: semana 3 | N13: semana 4 | O13: Total Abril 2026 | P13: semana 5 | Q13: semana 6 | R13: semana 7 | S13: semana 8 | T13: Total mayo 2026 | U13: semana 9 | V13: semana 10 | W13: semana 11 | X13: semana 12 | Y13: Total junio 2026 | Z13: semana 13 | AA13: semana 14 | AB13: semana 15 | AC13: semana 16 | AD13: Total julio 2026 | AE13: semana 17 | AF13: semana 18 | AG13: semana 19 | AH13: semana 20 | AI13: Total Agosto 2026 | AJ13: semana 17 | AK13: semana 18 | AL13: semana 19 | AM13: semana 20 | AN13: Total Agosto 2026 | AO13: semana 17 | AP13: semana 18 | AQ13: semana 19 | AR13: semana 20 | AS13: Total Agosto 2026
B14: 1 | C14: Indirectos | G14: =SUM(G15,G22,G26,G29,G39) -> 1.5053398e+08 | I14: =SUM(I15,I22,I26,I29,I39) -> 88200771 | J14: =SUM(J15,J22,J26,J29,J39) -> 123876289 | K14: =SUM(K15,K22,K26,K29,K39) -> 0 | L14: =SUM(L15,L22,L26,L29,L39) -> 0 | M14: =SUM(M15,M22,M26,M29,M39) -> 64463869 | N14: =SUM(N15,N22,N26,N29,N39) -> 2435886 | O14: =SUM(O15,O22,O26,O29,O39) -> 66899755 | P14: =SUM(P15,P22,P26,P29,P39) -> 0 | ... AS14: =SUM(AS15,AS22,AS26,AS29,AS39) -> 0
B15: 1.1 | C15: Polizas talleres | D15: =SUM(D16:D21) -> 6 | E15: =SUM(E16:E21) -> 0 | F15: =SUM(F16:F21) -> 18295782 | G15: =SUM(G16:G21) -> 18295782 | I15: =SUM(I16:I21) -> 5917366 | J15: =SUM(J16:J21) -> 5917366 | K15: =SUM(K16:K21) -> 0 | L15: =SUM(L16:L21) -> 0 | M15: =SUM(M16:M21) -> 5917366 | N15: =SUM(N16:N21) -> 0 | O15: =SUM(O16:O21) -> 5917366 | P15: =SUM(P16:P21) -> 0 | ... AS15: =SUM(AS16:AS21) -> 0
B16: 1.1.1 | C16: Buen manejo de anticipo | D16: 1 | E16: glb | F16: 3512790.2 | G16: =+D16*F16 -> 3512790.2 | I16: =O16+T16+Y16+AD16+AI16+AN16 -> 516713.12 | J16: 516713.12 | M16: 516713.12 | O16: =SUM(K16:N16) -> 516713.12 | T16: =SUM(P16:S16) -> 0 | Y16: =SUM(U16:X16) -> 0 | AD16: =SUM(Z16:AC16) -> 0 | AI16: =SUM(AE16:AH16) -> 0 | AN16: =SUM(AJ16:AM16) -> 0 | AS16: =SUM(AO16:AR16) -> 0
B17: 1.1.2 | C17: Cumplimiento | D17: 1 | E17: glb | F17: 3073691.4 | G17: =+D17*F17 -> 3073691.4 | I17: =O17+T17+Y17+AD17+AI17+AN17 -> 465741.43 | J17: 465741.43 | M17: 465741.43 | O17: =SUM(K17:N17) -> 465741.43 | T17: =SUM(P17:S17) -> 0 | Y17: =SUM(U17:X17) -> 0 | AD17: =SUM(Z17:AC17) -> 0 | AI17: =SUM(AE17:AH17) -> 0 | AN17: =SUM(AJ17:AM17) -> 0 | AS17: =SUM(AO17:AR17) -> 0
B18: 1.1.3 | C18: Salarios y prestaciones sociales | D18: 1 | E18: glb | F18: 2049127.6 | G18: =+D18*F18 -> 2049127.6 | I18: =O18+T18+Y18+AD18+AI18+AN18 -> 349306.07 | J18: 349306.07 | M18: 349306.07 | O18: =SUM(K18:N18) -> 349306.07 | T18: =SUM(P18:S18) -> 0 | Y18: =SUM(U18:X18) -> 0 | AD18: =SUM(Z18:AC18) -> 0 | AI18: =SUM(AE18:AH18) -> 0 | AN18: =SUM(AJ18:AM18) -> 0 | AS18: =SUM(AO18:AR18) -> 0
B19: 1.1.4 | C19: Estabilidad de obra | D19: 1 | E19: glb | F19: 3073691.4 | G19: =+D19*F19 -> 3073691.4 | I19: =O19+T19+Y19+AD19+AI19+AN19 -> 4184037.9 | J19: 4184037.9 | M19: 4184037.9 | O19: =SUM(K19:N19) -> 4184037.9 | T19: =SUM(P19:S19) -> 0 | Y19: =SUM(U19:X19) -> 0 | AD19: =SUM(Z19:AC19) -> 0 | AI19: =SUM(AE19:AH19) -> 0 | AN19: =SUM(AJ19:AM19) -> 0 | AS19: =SUM(AO19:AR19) -> 0
B20: 1.1.5 | C20: Calidad de obra | D20: 1 | E20: glb | F20: 3073691.4 | G20: =+D20*F20 -> 3073691.4 | I20: =O20+T20+Y20+AD20+AI20+AN20 -> 9282 | J20: 9282 | M20: 9282 | O20: =SUM(K20:N20) -> 9282 | T20: =SUM(P20:S20) -> 0 | Y20: =SUM(U20:X20) -> 0 | AD20: =SUM(Z20:AC20) -> 0 | AI20: =SUM(AE20:AH20) -> 0 | AN20: =SUM(AJ20:AM20) -> 0 | AS20: =SUM(AO20:AR20) -> 0
B21: 1.1.6 | C21: Responsabilidad civil extracontractural | D21: 1 | E21: glb | F21: 3512790.2 | G21: =+D21*F21 -> 3512790.2 | I21: =O21+T21+Y21+AD21+AI21+AN21 -> 392285.52 | J21: =197018.52+195267 -> 392285.52 | M21: =197018.52+195267 -> 392285.52 | O21: =SUM(K21:N21) -> 392285.52 | T21: =SUM(P21:S21) -> 0 | Y21: =SUM(U21:X21) -> 0 | AD21: =SUM(Z21:AC21) -> 0 | AI21: =SUM(AE21:AH21) -> 0 | AN21: =SUM(AJ21:AM21) -> 0 | AS21: =SUM(AO21:AR21) -> 0
B22: 1.2. | C22: Impuestos | G22: =SUM(G23:G25) -> 48300865 | I22: =SUM(I23:I25) -> 0 | J22: =SUM(J23:J25) -> 48300863 | K22: =SUM(K23:K25) -> 0 | L22: =SUM(L23:L25) -> 0 | M22: =SUM(M23:M25) -> 0 | N22: =SUM(N23:N25) -> 0 | O22: =SUM(O23:O25) -> 0 | P22: =SUM(P23:P25) -> 0 | ... AS22: =SUM(AS23:AS25) -> 0
B23: 1.2.1 | C23: FIC | D23: 1 | E23: glb | F23: 7318312.9 | G23: =+D23*F23 -> 7318312.9 | I23: =O23+T23+Y23+AD23+AI23+AN23 -> 0 | J23: 7318312 | O23: =SUM(K23:N23) -> 0 | T23: =SUM(P23:S23) -> 0 | Y23: =SUM(U23:X23) -> 0 | AD23: =SUM(Z23:AC23) -> 0 | AI23: =SUM(AE23:AH23) -> 0 | AN23: =SUM(AJ23:AM23) -> 0 | AS23: =SUM(AO23:AR23) -> 0
B24: 1.2.2 | C24: ICA | D24: 1 | E24: glb | F24: 29273252 | G24: =+D24*F24 -> 29273252 | I24: =O24+T24+Y24+AD24+AI24+AN24 -> 0 | J24: 29273251 | O24: =SUM(K24:N24) -> 0 | T24: =SUM(P24:S24) -> 0 | Y24: =SUM(U24:X24) -> 0 | AD24: =SUM(Z24:AC24) -> 0 | AI24: =SUM(AE24:AH24) -> 0 | AN24: =SUM(AJ24:AM24) -> 0 | AS24: =SUM(AO24:AR24) -> 0
B25: 1.2.3 | C25: Cuatro por 1000 | D25: 1 | E25: glb | F25: 11709301 | G25: =+D25*F25 -> 11709301 | I25: =O25+T25+Y25+AD25+AI25+AN25 -> 0 | J25: 11709300 | O25: =SUM(K25:N25) -> 0 | T25: =SUM(P25:S25) -> 0 | Y25: =SUM(U25:X25) -> 0 | AD25: =SUM(Z25:AC25) -> 0 | AI25: =SUM(AE25:AH25) -> 0 | AN25: =SUM(AJ25:AM25) -> 0 | AS25: =SUM(AO25:AR25) -> 0
B26: 1.3 | C26: Personal administración | G26: =G27 -> 24640000 | I26: =SUM(I27:I28) -> 23736902 | J26: =SUM(J27:J28) -> 10450000 | K26: =SUM(K27:K28) -> 0 | L26: =SUM(L27:L28) -> 0 | M26: =SUM(M27:M28) -> 0 | N26: =SUM(N27:N28) -> 2435886 | O26: =SUM(O27:O28) -> 2435886 | P26: =SUM(P27:P28) -> 0 | ... AS26: =SUM(AS27:AS28) -> 0
B27: 1.3.1 | C27: Profesional de calidad 100% | D27: 4 | E27: mes | F27: 6160000 | G27: =+D27*F27 -> 24640000 | I27: =O27+T27+Y27+AD27+AI27+AN27 -> 12643338 | J27: 7000000 | N27: 2435886 | O27: =SUM(K27:N27) -> 2435886 | S27: 6515382 | T27: =SUM(P27:S27) -> 6515382 | X27: 3692070 | Y27: =SUM(U27:X27) -> 3692070 | AD27: =SUM(Z27:AC27) -> 0 | AI27: =SUM(AE27:AH27) -> 0 | AN27: =SUM(AJ27:AM27) -> 0 | AS27: =SUM(AO27:AR27) -> 0
B28: 1.3.2 | C28: residente administrativo | D28: 4 | E28: mes | F28: =2300000*1.5 -> 3450000 | G28: =F28*D28 -> 13800000 | I28: =O28+T28+Y28+AD28+AI28+AN28 -> 11093564 | J28: =2300000*1.5 -> 3450000 | S28: 3847188 | T28: =SUM(P28:S28) -> 3847188 | X28: 3623188 | Y28: =SUM(U28:X28) -> 3623188 | AC28: 3623188 | AD28: =SUM(Z28:AC28) -> 3623188 | AH28: 3623188
B29: 1.4 | C29: Campamentos, protecciones e insumos de obra | G29: =SUM(G30:G38) -> 750834.4 | I29: =SUM(I30:I38) -> 0 | J29: =SUM(J30:J38) -> 661557 | K29: =SUM(K30:K38) -> 0 | L29: =SUM(L30:L38) -> 0 | M29: =SUM(M30:M38) -> 0 | N29: =SUM(N30:N38) -> 0 | O29: =SUM(O30:O38) -> 0 | P29: =SUM(P30:P38) -> 0 | ... AS29: =SUM(AS30:AS38) -> 0
B30: 1.4.1 | C30: Kit señalización para campamentos (hasta 120 m2) | D30: 3 | E30: und | F30: 125384.3 | G30: =+D30*F30 -> 376152.9 | I30: =O30+T30+Y30+AD30+AI30+AN30 -> 0 | J30: 150000 | O30: =SUM(K30:N30) -> 0 | T30: =SUM(P30:S30) -> 0 | Y30: =SUM(U30:X30) -> 0 | AD30: =SUM(Z30:AC30) -> 0 | AI30: =SUM(AE30:AH30) -> 0 | AN30: =SUM(AJ30:AM30) -> 0 | AS30: =SUM(AO30:AR30) -> 0
B31: 1.4.2 | C31: Cascos de seguridad | D31: 1 | E31: und | F31: 17867 | G31: =+D31*F31 -> 17867 | I31: =O31+T31+Y31+AD31+AI31+AN31 -> 0 | J31: 17850 | O31: =SUM(K31:N31) -> 0 | T31: =SUM(P31:S31) -> 0 | Y31: =SUM(U31:X31) -> 0 | AD31: =SUM(Z31:AC31) -> 0 | AI31: =SUM(AE31:AH31) -> 0 | AN31: =SUM(AJ31:AM31) -> 0 | AS31: =SUM(AO31:AR31) -> 0
B32: 1.4.3 | C32: Protección auditiva | D32: 3 | E32: und | F32: 2627.5 | G32: =+D32*F32 -> 7882.5 | I32: =O32+T32+Y32+AD32+AI32+AN32 -> 0 | J32: 4341 | O32: =SUM(K32:N32) -> 0 | T32: =SUM(P32:S32) -> 0 | Y32: =SUM(U32:X32) -> 0 | AD32: =SUM(Z32:AC32) -> 0 | AI32: =SUM(AE32:AH32) -> 0 | AN32: =SUM(AJ32:AM32) -> 0 | AS32: =SUM(AO32:AR32) -> 0
B33: 1.4.4 | C33: Guantes de nitrilo | D33: 3 | E33: und | F33: 5780.5 | G33: =+D33*F33 -> 17341.5 | I33: =O33+T33+Y33+AD33+AI33+AN33 -> 0 | J33: 23324 | O33: =SUM(K33:N33) -> 0 | T33: =SUM(P33:S33) -> 0 | Y33: =SUM(U33:X33) -> 0 | AD33: =SUM(Z33:AC33) -> 0 | AI33: =SUM(AE33:AH33) -> 0 | AN33: =SUM(AJ33:AM33) -> 0 | AS33: =SUM(AO33:AR33) -> 0
B34: 1.4.5 | C34: Par de botas de agua | D34: 1 | E34: und | F34: 72519 | G34: =+D34*F34 -> 72519 | I34: =O34+T34+Y34+AD34+AI34+AN34 -> 0 | J34: 66640 | O34: =SUM(K34:N34) -> 0 | T34: =SUM(P34:S34) -> 0 | Y34: =SUM(U34:X34) -> 0 | AD34: =SUM(Z34:AC34) -> 0 | AI34: =SUM(AE34:AH34) -> 0 | AN34: =SUM(AJ34:AM34) -> 0 | AS34: =SUM(AO34:AR34) -> 0
B35: 1.4.6 | C35: Par de botas de seguridad | D35: 1 | E35: und | F35: 118763 | G35: =+D35*F35 -> 118763 | I35: =O35+T35+Y35+AD35+AI35+AN35 -> 0 | J35: 116739 | O35: =SUM(K35:N35) -> 0 | T35: =SUM(P35:S35) -> 0 | Y35: =SUM(U35:X35) -> 0 | AD35: =SUM(Z35:AC35) -> 0 | AI35: =SUM(AE35:AH35) -> 0 | AN35: =SUM(AJ35:AM35) -> 0 | AS35: =SUM(AO35:AR35) -> 0
B36: 1.4.7 | C36: Gafas de seguridad | D36: 3 | E36: und | F36: 3678.5 | G36: =+D36*F36 -> 11035.5 | I36: =O36+T36+Y36+AD36+AI36+AN36 -> 0 | J36: 14756 | O36: =SUM(K36:N36) -> 0 | T36: =SUM(P36:S36) -> 0 | Y36: =SUM(U36:X36) -> 0 | AD36: =SUM(Z36:AC36) -> 0 | AI36: =SUM(AE36:AH36) -> 0 | AN36: =SUM(AJ36:AM36) -> 0 | AS36: =SUM(AO36:AR36) -> 0
B37: 1.4.8 | C37: Chalecos reflectivos | D37: 1 | E37: und | F37: 78825 | G37: =+D37*F37 -> 78825 | I37: =O37+T37+Y37+AD37+AI37+AN37 -> 0 | J37: 81037 | O37: =SUM(K37:N37) -> 0 | T37: =SUM(P37:S37) -> 0 | Y37: =SUM(U37:X37) -> 0 | AD37: =SUM(Z37:AC37) -> 0 | AI37: =SUM(AE37:AH37) -> 0 | AN37: =SUM(AJ37:AM37) -> 0 | AS37: =SUM(AO37:AR37) -> 0
B38: 1.4.9 | C38: Overoles | D38: 1 | E38: und | F38: 50448 | G38: =+D38*F38 -> 50448 | I38: =O38+T38+Y38+AD38+AI38+AN38 -> 0 | J38: 186870 | O38: =SUM(K38:N38) -> 0 | T38: =SUM(P38:S38) -> 0 | Y38: =SUM(U38:X38) -> 0 | AD38: =SUM(Z38:AC38) -> 0 | AI38: =SUM(AE38:AH38) -> 0 | AN38: =SUM(AJ38:AM38) -> 0 | AS38: =SUM(AO38:AR38) -> 0
B39: 1.5 | C39: G.C. | D39: =SUM(D40) -> 1 | E39: =SUM(E40) -> 0 | F39: =SUM(F40) -> 58546503 | G39: =SUM(G40) -> 58546503 | I39: =SUM(I40) -> 58546503 | J39: =SUM(J40) -> 58546503 | K39: =SUM(K40) -> 0 | L39: =SUM(L40) -> 0 | M39: =SUM(M40) -> 58546503 | N39: =SUM(N40) -> 0 | O39: =SUM(O40) -> 58546503 | P39: =SUM(P40) -> 0 | ... AS39: =SUM(AS40) -> 0
B40: 1.5.1 | C40: TRANSPORTES | D40: 1 | E40: glb | F40: 58546503 | G40: =+D40*F40 -> 58546503 | I40: =O40+T40+Y40+AD40+AI40+AN40 -> 58546503 | J40: 58546503 | M40: 58546503 | O40: =SUM(K40:N40) -> 58546503 | T40: =SUM(P40:S40) -> 0 | Y40: =SUM(U40:X40) -> 0 | AD40: =SUM(Z40:AC40) -> 0 | AI40: =SUM(AE40:AH40) -> 0 | AN40: =SUM(AJ40:AM40) -> 0 | AS40: =SUM(AO40:AR40) -> 0
B41: 3 | C41: Viaticos | G41: =G42 -> 0 | I41: =I42 -> 12633905 | J41: =J42 -> 4200000 | K41: =K42 -> 0 | L41: =L42 -> 0 | M41: =M42 -> 0 | N41: =N42 -> 0 | O41: =O42 -> 0 | P41: =P42 -> 0 | ... AS41: =AS42 -> 0
B42: 3.1 | C42: Viaticos | G42: =SUM(G43:G46) -> 0 | I42: =SUM(I43:I46) -> 12633905 | J42: =SUM(J43:J46) -> 4200000 | K42: =SUM(K43:K46) -> 0 | L42: =SUM(L43:L46) -> 0 | M42: =SUM(M43:M46) -> 0 | N42: =SUM(N43:N46) -> 0 | O42: =SUM(O43:O46) -> 0 | P42: =SUM(P43:P46) -> 0 | ... AS42: =SUM(AS43:AS46) -> 0
B43: 3.1.1 | C43: Hospedaje | I43: =O43+T43+Y43+AD43+AI43+AN43 -> 6341495 | J43: 1237600 | O43: =SUM(K43:N43) -> 0 | Q43: 500000 | T43: =SUM(P43:S43) -> 500000 | W43: 1348000 | Y43: =SUM(U43:X43) -> 1348000 | AA43: 2400000 | AD43: =SUM(Z43:AC43) -> 2400000 | AI43: =SUM(AE43:AH43) -> 0 | AJ43: 2093495 | AN43: =SUM(AJ43:AM43) -> 2093495 | AS43: =SUM(AO43:AR43) -> 0
B44: 3.1.2 | C44: Transportes | I44: =O44+T44+Y44+AD44+AI44+AN44 -> 821900 | J44: 292400 | O44: =SUM(K44:N44) -> 0 | Q44: 147900 | T44: =SUM(P44:S44) -> 147900 | Y44: =SUM(U44:X44) -> 0 | AA44: 248000 | AD44: =SUM(Z44:AC44) -> 248000 | AE44: 426000 | AI44: =SUM(AE44:AH44) -> 426000 | AN44: =SUM(AJ44:AM44) -> 0 | AS44: =SUM(AO44:AR44) -> 0
B45: 3.1.3 | C45: Pasajes | I45: =O45+T45+Y45+AD45+AI45+AN45 -> 609510 | J45: 2190000 | O45: =SUM(K45:N45) -> 0 | Q45: 609510 | T45: =SUM(P45:S45) -> 609510 | Y45: =SUM(U45:X45) -> 0 | AD45: =SUM(Z45:AC45) -> 0 | AI45: =SUM(AE45:AH45) -> 0 | AN45: =SUM(AJ45:AM45) -> 0 | AS45: =SUM(AO45:AR45) -> 0
B46: 3.1.4 | C46: Alimentacion | I46: =O46+T46+Y46+AD46+AI46+AN46 -> 4861000 | J46: 480000 | O46: =SUM(K46:N46) -> 0 | Q46: 240000 | T46: =SUM(P46:S46) -> 240000 | W46: 887000 | Y46: =SUM(U46:X46) -> 887000 | AA46: 1860000 | AD46: =SUM(Z46:AC46) -> 1860000 | AE46: 1874000 | AI46: =SUM(AE46:AH46) -> 1874000 | AN46: =SUM(AJ46:AM46) -> 0 | AS46: =SUM(AO46:AR46) -> 0
B47: 4 | C47: INGENIERÍA | G47: =G48 -> 0 | I47: =I48 -> 0 | J47: =J48 -> 11448635 | K47: =K48 -> 0 | L47: =L48 -> 0 | M47: =M48 -> 0 | N47: =N48 -> 0 | O47: =O48 -> 0 | P47: =P48 -> 0 | ... AS47: =AS48 -> 0
B48: 4.1 | C48: Ingenieria de taller | G48: =G49 -> 0 | I48: =I49 -> 0 | J48: =J49 -> 11448635 | K48: =K49 -> 0 | L48: =L49 -> 0 | M48: =M49 -> 0 | N48: =N49 -> 0 | O48: =O49 -> 0 | P48: =P49 -> 0 | ... AS48: =AS49 -> 0
B49: 4.1.1 | C49: Ingenieria de taller | I49: =O49+T49+Y49+AD49+AI49+AN49 -> 0 | J49: 11448635 | O49: =SUM(K49:N49) -> 0 | T49: =SUM(P49:S49) -> 0 | Y49: =SUM(U49:X49) -> 0 | AD49: =SUM(Z49:AC49) -> 0 | AI49: =SUM(AE49:AH49) -> 0 | AN49: =SUM(AJ49:AM49) -> 0 | AS49: =SUM(AO49:AR49) -> 0
B50: 5 | C50: Suministros | G50: =SUM(G51) -> 0 | I50: =SUM(I51) -> 71708196 | J50: =SUM(J51) -> 2045743.3 | K50: =SUM(K51) -> 0 | L50: =SUM(L51) -> 0 | M50: =SUM(M51) -> 0 | N50: =SUM(N51) -> 0 | O50: =SUM(O51) -> 0 | P50: =SUM(P51) -> 0 | ... AS50: =SUM(AS51) -> 198
B51: 5.1 | C51: PINTURA | G51: =G53 -> 0 | I51: =I52+I56 -> 71708196 | J51: =J52+J56 -> 2045743.3 | K51: =K52+K56 -> 0 | L51: =L52+L56 -> 0 | M51: =M52+M56 -> 0 | N51: =N52+N56 -> 0 | O51: =O52+O56 -> 0 | P51: =P52+P56 -> 0 | ... AS51: =AS52+AS56 -> 198
B52: 5.1.1 | C52: Epoxico | I52: =SUM(I53:I55) -> 70528549 | J52: =SUM(J53:J55) -> 866096.28 | K52: =SUM(K53:K55) -> 0 | L52: =SUM(L53:L55) -> 0 | M52: =SUM(M53:M55) -> 0 | N52: =SUM(N53:N55) -> 0 | O52: =SUM(O53:O55) -> 0 | P52: =SUM(P53:P55) -> 0 | ... AS52: =SUM(AS53:AS55) -> 36
B53: 5.1.1.1 | C53: Anticorrosivo epoxico x cuñete | D53: 136 | E53: Cuñetes | I53: =(O53+T53+Y53+AD53+AI53+AN53)*J53 -> 68375296 | J53: =563316*1.19 -> 670346.04 | O53: =SUM(K53:N53) -> 0 | T53: =SUM(P53:S53) -> 0 | W53: 68 | Y53: =SUM(U53:X53) -> 68 | AD53: =SUM(Z53:AC53) -> 0 | AI53: =SUM(AE53:AH53) -> 0 | AM53: 34 | AN53: =SUM(AJ53:AM53) -> 34 | AP53: 34 | AS53: =SUM(AO53:AR53) -> 34
B54: 5.1.1.2 | C54: Catalizador | I54: =(O54+T54+Y54+AD54+AI54+AN54)*J54 -> 0 | O54: =SUM(K54:N54) -> 0 | T54: =SUM(P54:S54) -> 0 | Y54: =SUM(U54:X54) -> 0 | AD54: =SUM(Z54:AC54) -> 0 | AI54: =SUM(AE54:AH54) -> 0 | AN54: =SUM(AJ54:AM54) -> 0 | AS54: =SUM(AO54:AR54) -> 0
B55: 5.1.1.3 | C55: Disolvente epoxicco cuñete | D55: 13 | E55: Cuñetes | I55: =(O55+T55+Y55+AD55+AI55+AN55)*J55 -> 2153252.6 | J55: =164496*1.19 -> 195750.24 | O55: =SUM(K55:N55) -> 0 | T55: =SUM(P55:S55) -> 0 | W55: 8 | Y55: =SUM(U55:X55) -> 8 | AD55: =SUM(Z55:AC55) -> 0 | AI55: =SUM(AE55:AH55) -> 0 | AM55: 3 | AN55: =SUM(AJ55:AM55) -> 3 | AP55: 2 | AS55: =SUM(AO55:AR55) -> 2
B56: 5.1.2 | C56: Pintura | I56: =SUM(I57:I59) -> 1179647 | J56: =SUM(J57:J59) -> 1179647 | K56: =SUM(K57:K59) -> 0 | L56: =SUM(L57:L59) -> 0 | M56: =SUM(M57:M59) -> 0 | N56: =SUM(N57:N59) -> 0 | O56: =SUM(O57:O59) -> 0 | P56: =SUM(P57:P59) -> 0 | ... AS56: =SUM(AS57:AS59) -> 162
B57: 5.1.2.1 | C57: Esmalte Urretano | D57: 149 | E57: Cuñetes | I57: =(O57+T57+Y57+AD57+AI57+AN57)*J57 -> 983896.76 | J57: =826804*1.19 -> 983896.76 | O57: =SUM(K57:N57) -> 0 | T57: =SUM(P57:S57) -> 0 | W57: 1 | Y57: =SUM(U57:X57) -> 1 | AD57: =SUM(Z57:AC57) -> 0 | AI57: =SUM(AE57:AH57) -> 0 | AN57: =SUM(AJ57:AM57) -> 0 | AR57: 148 | AS57: =SUM(AO57:AR57) -> 148
B58: 5.1.2.2 | C58: Catalizador Urretano | I58: =(O58+T58+Y58+AD58+AI58+AN58)*J58 -> 0 | O58: =SUM(K58:N58) -> 0 | T58: =SUM(P58:S58) -> 0 | Y58: =SUM(U58:X58) -> 0 | AD58: =SUM(Z58:AC58) -> 0 | AI58: =SUM(AE58:AH58) -> 0 | AN58: =SUM(AJ58:AM58) -> 0 | AS58: =SUM(AO58:AR58) -> 0
B59: 5.1.2.3 | C59: Solvente Uretano | D59: 15 | E59: Cuñetes | I59: =(O59+T59+Y59+AD59+AI59+AN59)*J59 -> 195750.24 | J59: =164496*1.19 -> 195750.24 | O59: =SUM(K59:N59) -> 0 | T59: =SUM(P59:S59) -> 0 | W59: 1 | Y59: =SUM(U59:X59) -> 1 | AD59: =SUM(Z59:AC59) -> 0 | AI59: =SUM(AE59:AH59) -> 0 | AN59: =SUM(AJ59:AM59) -> 0 | AR59: 14 | AS59: =SUM(AO59:AR59) -> 14
B60: 6 | C60: Mano de obra | G60: =SUM(G61) -> #REF! | I60: =SUM(I61) -> 9.7713338e+08 | J60: =SUM(J61) -> 4337.7139 | K60: =SUM(K61) -> 0 | L60: =SUM(L61) -> 0 | M60: =SUM(M61) -> 0 | N60: =SUM(N61) -> 0 | O60: =SUM(O61) -> 0 | P60: =SUM(P61) -> 0 | ... AS60: =SUM(AS61) -> 0
B61: 6.1 | C61: Fabricación de EEMM | G61: =#REF! -> #REF! | I61: =I62 -> 9.7713338e+08 | J61: =J62 -> 4337.7139 | K61: =(K62*$J$61)+(K63*$J$63) -> 0 | L61: =(L62*$J$61)+(L63*$J$63) -> 0 | M61: =(M62*$J$61)+(M63*$J$63) -> 0 | N61: =(N62*$J$61)+(N63*$J$63) -> 0 | O61: =(O62*$J$61)+(O63*$J$63) -> 0 | P61: =(P62*$J$61)+(P63*$J$63) -> 0 | Q61: =(Q62*$J$61)+(Q63*$J$63) -> 22002620 | R61: =(R62*$J$61)+(R63*$J$63) -> 41568312 | ... AS61: =(AS62*$J$61)+(AS63*$J$63) -> 0
B62: 6.1.1. | C62: Proveedor 1 | I62: =(O62+T62+Y62+AD62+AI62+AN62)*J62 -> 9.7713338e+08 | J62: 4337.7139 | O62: =SUM(K62:N62) -> 0 | P62: 0 | Q62: 5072.4 | R62: 9583 | S62: 17682.2 | T62: =SUM(P62:S62) -> 32337.6 | V62: 11678 | W62: 17785 | X62: 6305 | Y62: =SUM(U62:X62) -> 35768 | Z62: 10678 | AA62: 5287 | AB62: 14738 | AC62: 20953 | AD62: =SUM(Z62:AC62) -> 51656 | AE62: 20953 | AF62: 22822 | AG62: 4767 | AH62: =37000 -> 37000 | AI62: =SUM(AE62:AH62) -> 85542 | AJ62: 19961 | AN62: =SUM(AJ62:AM62) -> 19961 | AS62: =SUM(AO62:AR62) -> 0
B63: 6.1.2. | C63: Proveedor 2 | I63: =(O63+T63+Y63+AD63+AI63+AN63)*J63 -> 0 | J63: =J62+350 -> 4687.7139
C65: Totales | F65: =F53*D53 -> 0 | G65: =G60+G50+G47+G41+G14 -> #REF! | I65: =I60+I50+I47+I41+I14 -> 1.1496763e+09 | K65: =(K60*$J$60)+(K53*$J$53)+(K54*$J$54)+(K55*$J$55)+(K57*$J$57)+(K58*$J$58)+(K59*$J$59)+K47+K41+K14 -> 0 | L65: =(L60*$J$60)+(L53*$J$53)+(L54*$J$54)+(L55*$J$55)+(L57*$J$57)+(L58*$J$58)+(L59*$J$59)+L47+L41+L14 -> 0 | M65: =(M60*$J$60)+(M53*$J$53)+(M54*$J$54)+(M55*$J$55)+(M57*$J$57)+(M58*$J$58)+(M59*$J$59)+M47+M41+M14 -> 64463869 | N65: =(N60*$J$60)+(N53*$J$53)+(N54*$J$54)+(N55*$J$55)+(N57*$J$57)+(N58*$J$58)+(N59*$J$59)+N47+N41+N14 -> 2435886 | O65: =(O60*$J$60)+(O53*$J$53)+(O54*$J$54)+(O55*$J$55)+(O57*$J$57)+(O58*$J$58)+(O59*$J$59)+O47+O41+O14 -> 66899755 | P65: =(P60*$J$60)+(P53*$J$53)+(P54*$J$54)+(P55*$J$55)+(P57*$J$57)+(P58*$J$58)+(P59*$J$59)+P47+P41+P14 -> 0 | Q65: =(Q60*$J$60)+(Q53*$J$53)+(Q54*$J$54)+(Q55*$J$55)+(Q57*$J$57)+(Q58*$J$58)+(Q59*$J$59)+Q47+Q41+Q14 -> 9.5442567e+10 | R65: =(R60*$J$60)+(R53*$J$53)+(R54*$J$54)+(R55*$J$55)+(R57*$J$57)+(R58*$J$58)+(R59*$J$59)+R47+R41+R14 -> 1.8031144e+11 | ... AS65: =(AS60*$J$60)+(AS53*$J$53)+(AS54*$J$54)+(AS55*$J$55)+(AS57*$J$57)+(AS58*$J$58)+(AS59*$J$59)+AS47+AS41+AS14 -> 1.7154049e+08
AH68: 4453
E69: descuento a nivel de kilos y precios

Sheet ASEGURADO
B2: 1 | C2: 2 | D2: 3 | E2: 4 | F2: 5 | G2: 6 | H2: 7 | I2: 8 | J2: 9 | K2: 10 | L2: 11 | M2: 12 | N2: 13 | O2: 14 | P2: 15 | Q2: 16 | R2: 17 | S2: 18 | T2: 19 | U2: 20 | V2: 21 | W2: 22 | X2: 23 | Y2: 24 | Z2: 25 | AA2: 26 | AB2: 27 | AC2: 28 | AD2: 29 | AE2: 30 | AF2: 31 | AG2: 32 | AH2: 33 | AI2: 34
B3: Código | C3: ITEM | D3: Cantidad+desp. | E3: Unidad de medida | F3: Valor Unitario | G3: Total presupuesto | I3: Valor total | J3: Valor Unitario | K3: semana 1 | L3: semana 2 | M3: semana 3 | N3: semana 4 | O3: Total Abril 2026 | P3: semana 5 | Q3: semana 6 | R3: semana 7 | S3: semana 8 | T3: Total mayo 2026 | U3: semana 9 | V3: semana 10 | W3: semana 11 | X3: semana 12 | Y3: Total junio 2026 | Z3: semana 13 | AA3: semana 14 | AB3: semana 15 | AC3: semana 16 | AD3: Total julio 2026 | AE3: semana 17 | AF3: semana 18 | AG3: semana 19 | AH3: semana 20 | AI3: Total Agosto 2026
B4: 1 | C4: Indirectos | G4: =SUM(G5,G12,G16,G19,G29) -> 1.5053398e+08 | I4: =SUM(I5,I12,I16,I19,I29) -> 86899755 | J4: =SUM(J5,J12,J16,J19,J29) -> 124426289 | K4: =SUM(K5,K12,K16,K19,K29) -> 0 | L4: =SUM(L5,L12,L16,L19,L29) -> 0 | M4: =SUM(M5,M12,M16,M19,M29) -> 64463869 | N4: =SUM(N5,N12,N16,N19,N29) -> 6435886 | O4: =SUM(O5,O12,O16,O19,O29) -> 70899755 | P4: =SUM(P5,P12,P16,P19,P29) -> 0 | ... AI4: =SUM(AI5,AI12,AI16,AI19,AI29) -> 4000000
B5: 1.1 | C5: Polizas talleres | D5: =SUM(D6:D11) -> 6 | E5: =SUM(E6:E11) -> 0 | F5: =SUM(F6:F11) -> 18295782 | G5: =SUM(G6:G11) -> 18295782 | I5: =SUM(I6:I11) -> 5917366 | J5: =SUM(J6:J11) -> 5917366 | K5: =SUM(K6:K11) -> 0 | L5: =SUM(L6:L11) -> 0 | M5: =SUM(M6:M11) -> 5917366 | N5: =SUM(N6:N11) -> 0 | O5: =SUM(O6:O11) -> 5917366 | P5: =SUM(P6:P11) -> 0 | ... AI5: =SUM(AI6:AI11) -> 0
B6: 1.1.1 | C6: Buen manejo de anticipo | D6: 1 | E6: glb | F6: 3512790.2 | G6: =+D6*F6 -> 3512790.2 | I6: =O6+T6+Y6+AD6+AI6 -> 516713.12 | J6: 516713.12 | M6: 516713.12 | O6: =SUM(K6:N6) -> 516713.12 | T6: =SUM(P6:S6) -> 0 | Y6: =SUM(U6:X6) -> 0 | AD6: =SUM(Z6:AC6) -> 0 | AI6: =SUM(AE6:AH6) -> 0
B7: 1.1.2 | C7: Cumplimiento | D7: 1 | E7: glb | F7: 3073691.4 | G7: =+D7*F7 -> 3073691.4 | I7: =O7+T7+Y7+AD7+AI7 -> 465741.43 | J7: 465741.43 | M7: 465741.43 | O7: =SUM(K7:N7) -> 465741.43 | T7: =SUM(P7:S7) -> 0 | Y7: =SUM(U7:X7) -> 0 | AD7: =SUM(Z7:AC7) -> 0 | AI7: =SUM(AE7:AH7) -> 0
B8: 1.1.3 | C8: Salarios y prestaciones sociales | D8: 1 | E8: glb | F8: 2049127.6 | G8: =+D8*F8 -> 2049127.6 | I8: =O8+T8+Y8+AD8+AI8 -> 349306.07 | J8: 349306.07 | M8: 349306.07 | O8: =SUM(K8:N8) -> 349306.07 | T8: =SUM(P8:S8) -> 0 | Y8: =SUM(U8:X8) -> 0 | AD8: =SUM(Z8:AC8) -> 0 | AI8: =SUM(AE8:AH8) -> 0
B9: 1.1.4 | C9: Estabilidad de obra | D9: 1 | E9: glb | F9: 3073691.4 | G9: =+D9*F9 -> 3073691.4 | I9: =O9+T9+Y9+AD9+AI9 -> 4184037.9 | J9: 4184037.9 | M9: 4184037.9 | O9: =SUM(K9:N9) -> 4184037.9 | T9: =SUM(P9:S9) -> 0 | Y9: =SUM(U9:X9) -> 0 | AD9: =SUM(Z9:AC9) -> 0 | AI9: =SUM(AE9:AH9) -> 0
B10: 1.1.5 | C10: Calidad de obra | D10: 1 | E10: glb | F10: 3073691.4 | G10: =+D10*F10 -> 3073691.4 | I10: =O10+T10+Y10+AD10+AI10 -> 9282 | J10: 9282 | M10: 9282 | O10: =SUM(K10:N10) -> 9282 | T10: =SUM(P10:S10) -> 0 | Y10: =SUM(U10:X10) -> 0 | AD10: =SUM(Z10:AC10) -> 0 | AI10: =SUM(AE10:AH10) -> 0
B11: 1.1.6 | C11: Responsabilidad civil extracontractural | D11: 1 | E11: glb | F11: 3512790.2 | G11: =+D11*F11 -> 3512790.2 | I11: =O11+T11+Y11+AD11+AI11 -> 392285.52 | J11: =197018.52+195267 -> 392285.52 | M11: =197018.52+195267 -> 392285.52 | O11: =SUM(K11:N11) -> 392285.52 | T11: =SUM(P11:S11) -> 0 | Y11: =SUM(U11:X11) -> 0 | AD11: =SUM(Z11:AC11) -> 0 | AI11: =SUM(AE11:AH11) -> 0
B12: 1.2. | C12: Impuestos | G12: =SUM(G13:G15) -> 48300865 | I12: =SUM(I13:I15) -> 0 | J12: =SUM(J13:J15) -> 48300863 | K12: =SUM(K13:K15) -> 0 | L12: =SUM(L13:L15) -> 0 | M12: =SUM(M13:M15) -> 0 | N12: =SUM(N13:N15) -> 0 | O12: =SUM(O13:O15) -> 0 | P12: =SUM(P13:P15) -> 0 | ... AI12: =SUM(AI13:AI15) -> 0
B13: 1.2.1 | C13: FIC | D13: 1 | E13: glb | F13: 7318312.9 | G13: =+D13*F13 -> 7318312.9 | I13: =O13+T13+Y13+AD13+AI13 -> 0 | J13: 7318312 | O13: =SUM(K13:N13) -> 0 | T13: =SUM(P13:S13) -> 0 | Y13: =SUM(U13:X13) -> 0 | AD13: =SUM(Z13:AC13) -> 0 | AI13: =SUM(AE13:AH13) -> 0
B14: 1.2.2 | C14: ICA | D14: 1 | E14: glb | F14: 29273252 | G14: =+D14*F14 -> 29273252 | I14: =O14+T14+Y14+AD14+AI14 -> 0 | J14: 29273251 | O14: =SUM(K14:N14) -> 0 | T14: =SUM(P14:S14) -> 0 | Y14: =SUM(U14:X14) -> 0 | AD14: =SUM(Z14:AC14) -> 0 | AI14: =SUM(AE14:AH14) -> 0
B15: 1.2.3 | C15: Cuatro por 1000 | D15: 1 | E15: glb | F15: 11709301 | G15: =+D15*F15 -> 11709301 | I15: =O15+T15+Y15+AD15+AI15 -> 0 | J15: 11709300 | O15: =SUM(K15:N15) -> 0 | T15: =SUM(P15:S15) -> 0 | Y15: =SUM(U15:X15) -> 0 | AD15: =SUM(Z15:AC15) -> 0 | AI15: =SUM(AE15:AH15) -> 0
B16: 1.3 | C16: Personal administración | G16: =G17 -> 24640000 | I16: =I17+I18 -> 22435886 | J16: =J17+J18 -> 11000000 | K16: =K17+K18 -> 0 | L16: =L17+L18 -> 0 | M16: =M17+M18 -> 0 | N16: =N17+N18 -> 6435886 | O16: =O17+O18 -> 6435886 | P16: =P17+P18 -> 0 | ... AI16: =AI17+AI18 -> 4000000
B17: 1.3.1 | C17: Profesional de calidad 100% | D17: 4 | E17: mes | F17: 6160000 | G17: =+D17*F17 -> 24640000 | I17: =O17+T17+Y17+AD17+AI17 -> 2435886 | J17: 7000000 | N17: 2435886 | O17: =SUM(K17:N17) -> 2435886 | T17: =SUM(P17:S17) -> 0 | Y17: =SUM(U17:X17) -> 0 | AD17: =SUM(Z17:AC17) -> 0 | AI17: =SUM(AE17:AH17) -> 0
B18: 1.3.2 | C18: Residente administrativo | I18: =O18+T18+Y18+AD18+AI18 -> 20000000 | J18: 4000000 | N18: 4000000 | O18: =SUM(K18:N18) -> 4000000 | S18: 4000000 | T18: =SUM(P18:S18) -> 4000000 | X18: 4000000 | Y18: =SUM(U18:X18) -> 4000000 | AC18: 4000000 | AD18: =SUM(Z18:AC18) -> 4000000 | AH18: 4000000 | AI18: =SUM(AE18:AH18) -> 4000000
B19: 1.4 | C19: Campamentos, protecciones e insumos de obra | G19: =SUM(G20:G28) -> 750834.4 | I19: =SUM(I20:I28) -> 0 | J19: =SUM(J20:J28) -> 661557 | K19: =SUM(K20:K28) -> 0 | L19: =SUM(L20:L28) -> 0 | M19: =SUM(M20:M28) -> 0 | N19: =SUM(N20:N28) -> 0 | O19: =SUM(O20:O28) -> 0 | P19: =SUM(P20:P28) -> 0 | ... AI19: =SUM(AI20:AI28) -> 0
B20: 1.4.1 | C20: Kit señalización para campamentos (hasta 120 m2) | D20: 3 | E20: und | F20: 125384.3 | G20: =+D20*F20 -> 376152.9 | I20: =O20+T20+Y20+AD20+AI20 -> 0 | J20: 150000 | O20: =SUM(K20:N20) -> 0 | T20: =SUM(P20:S20) -> 0 | Y20: =SUM(U20:X20) -> 0 | AD20: =SUM(Z20:AC20) -> 0 | AI20: =SUM(AE20:AH20) -> 0
B21: 1.4.2 | C21: Cascos de seguridad | D21: 1 | E21: und | F21: 17867 | G21: =+D21*F21 -> 17867 | I21: =O21+T21+Y21+AD21+AI21 -> 0 | J21: 17850 | O21: =SUM(K21:N21) -> 0 | T21: =SUM(P21:S21) -> 0 | Y21: =SUM(U21:X21) -> 0 | AD21: =SUM(Z21:AC21) -> 0 | AI21: =SUM(AE21:AH21) -> 0
B22: 1.4.3 | C22: Protección auditiva | D22: 3 | E22: und | F22: 2627.5 | G22: =+D22*F22 -> 7882.5 | I22: =O22+T22+Y22+AD22+AI22 -> 0 | J22: 4341 | O22: =SUM(K22:N22) -> 0 | T22: =SUM(P22:S22) -> 0 | Y22: =SUM(U22:X22) -> 0 | AD22: =SUM(Z22:AC22) -> 0 | AI22: =SUM(AE22:AH22) -> 0
